Workbook

Sheet IS_Rules
A1: Rule Name | B1: Rule Desciption | C1: Rule Dimanesion | D1: Rule Expression
A2: ZB_G13_MATNR_TargetQMSystemReference | B2: Rule to check if Target QM System value for Material master data is valid according to the available values in the appropriate reference table in a standard SAP ECC 6.0 system. | C2: Consistency | D2: BEGIN RETURN exists('SAP', 'TQ02', 'QSSYS', $P_I_TargetQMSystem); END
A3: ZB_G13_MATNR_FairShareRuleDomainReference | B3: Rule to check if Fair Share Rule value for a Material master is valid according to the appropriate reference domain or value range for a standard SAP ECC 6.0 system. | C3: Consistency | D3: BEGIN RETURN $P_I_FairShare_Rule IS NULL OR length($P_I_FairShare_Rule) = 0 OR $P_I_FairShare_Rule IN ('A', 'B', 'X'); END
A4: ZB_G13_MATNR_TaskListTypeReference | B4: Rule to check if Task List Type value for Material master data is valid according to the available values in the appropriate reference table in a standard SAP ECC 6.0 system. | C4: Consistency | D4: BEGIN RETURN exists('SAP', 'H_TCA01', 'PLNTY', $P_I_TaskListType); END
A5: ZB_G14_CUST_TradingPartnerReference | B5: Rule to check if Trading Partner value for Business Partner / Customer / Vendor master data is valid according to the available values in the appropriate reference table in a standard SAP ECC 6.0 system. | C5: Consistency | D5: BEGIN RETURN exists('SAP', 'T880', 'RCOMP', $P_I_TradingPartner); END
A6: ZB_G14_CUST_SalesCurrencyExists | B6: Rule to validate if Customer Sales Currency is set | C6: Completeness | D6: BEGIN RETURN $P_I_Currency IS NOT NULL AND $P_I_Currency != ''; END
A7: ZB_G15_VNDR_LicensevalidToDateExists | B7: Rule to check if the License valid to date for Business Partner / Customer / Vendor exists | C7: Completeness | D7: BEGIN RETURN $P_I_LicenseValidToDate IS NOT NULL AND $P_I_LicenseValidToDate != to_date('', 'yyyy.mm.dd'); END
A8: ZB_G13_MATNR_AvailabilityCheckExists | B8: Rule to check for existence of Availability check in Material master data for a standard SAP ECC 6.0 system | C8: Completeness | D8: BEGIN RETURN $P_I_AvailabilityCheck IS NOT NULL AND $P_I_AvailabilityCheck != ''; END
A9: ZB_G14_CUST_CompanyCodeExists | B9: Rule to check if Company code exists for Business Partner / Customer / Vendor master data for a standard SAP ECC 6.0 system | C9: Completeness | D9: BEGIN RETURN $P_I_CompanyCode IS NOT NULL AND $P_I_CompanyCode != ''; END
A10: ZB_G15_VNDR_StatisticeGroupReference | B10: Rule to check if Statistics Group value for Business Partner / Customer / Vendor master data is valid according to the available values in the appropriate reference table in a standard SAP ECC 6.0 system. | C10: Consistency | D10: BEGIN RETURN exists('SAP', 'TVSD', 'STGKU', $P_I_StatisticsGroup); END
A11: ZB_G15_VNDR_TaxNumberReference | B11: Rule to check if Tax Number value for Vendor master data is valid according to the available values in the appropriate reference table in a standard SAP ECC 6.0 system. | C11: Consistency | D11: BEGIN RETURN exists('SAP', 'M_KREDA', 'LIFNR', $P_I_TaxNumber); END
A12: ZB_G13_MATNR_MRPTypeReference | B12: Rule to check if MRP Type value for Material master data is valid according to the available values in the appropriate reference table in a standard SAP ECC 6.0 system. | C12: Consistency | D12: BEGIN RETURN exists('SAP', 'T438A', 'DISMM', $P_I_MRPType); END
... A169: ZB_G13_MATNR_PlanningCycleReference | B169: Rule to check if Planning Cycle value for Material master data is valid according to the available values in the appropriate reference table in a standard SAP ECC 6.0 system. | C169: Consistency | D169: BEGIN RETURN exists('SAP', 'MARC', 'MRPPP', $P_I_PlanningCycle); END
A170: ZB_G13_MATNR_TaxIndicatorforMaterialReference | C170: Consistency | D170: BEGIN RETURN exists('SAP', 'TMKM1', 'TAXIM', $P_I_TaxIndicator); END
A171: ZB_G14_CUST_PostalCodeAndCityExists | B171: Rule to check if Postal Code and City exist for Business Partner (Customer / Vendor) Master data in a standard SAP ECC 6.0 system | C171: Completeness | D171: BEGIN RETURN $P_I_PostalCodeCity IS NOT NULL AND $P_I_PostalCodeCity != ''; END
A172: ZB_G14_CUST_PlanningGroupExists | B172: Rule to validate if Customer Planning group exists. | C172: Completeness | D172: BEGIN RETURN $P_I_PlanningGroup IS NOT NULL AND $P_I_PlanningGroup != ''; END
A173: ZB_G13_MATNR_ProductAllocationReference | B173: Rule to check if Product Allocation value for Material master data is valid according to the available values in the appropriate reference table in a standard SAP ECC 6.0 system. | C173: Consistency | D173: BEGIN RETURN exists('SAP', 'T190S', 'KOSCH', $P_I_ProductAllocation); END
A174: ZB_G14_CUST_DistributionChannelExists | B174: Rule to check if Distribution Channel exists for Customer master data for a standard SAP ECC 6.0 system | C174: Completeness | D174: BEGIN RETURN $P_I_DistributionChannel IS NOT NULL AND $P_I_DistributionChannel != ''; END
A175: ZB_G14_CUST_LicenseValidFromDateExists | B175: Rule to check if License Valid from date exists for Business Partner / Customer / Vendor exists | C175: Completeness | D175: BEGIN RETURN $P_I_LicenseValidFromDate IS NOT NULL AND $P_I_LicenseValidFromDate != to_date('', 'yyyy.mm.dd'); END
A176: ZB_G14_CUST_CustomerAccountGroupReference | B176: Rule to check if Account group value for Customer master data is valid according to the available values in the appropriate reference table in a standard SAP ECC 6.0 system. | C176: Consistency | D176: BEGIN RETURN exists('SAP', 'T077D', 'KTOKD', $P_I_AccountGroup); END
A177: ZB_G14_CUST_TransportationZoneExists | B177: ule to check if Transportation zone exists for Customer master data for a standard SAP ECC 6.0 system | C177: Completeness | D177: BEGIN RETURN $P_I_TransportationZone IS NOT NULL AND $P_I_TransportationZone != ''; END
A178: ZB_G14_CUST_AccountAssignmentGroupReference | B178: Rule to check if Account Assignment Group value for Customer master data is valid according to the available values in the appropriate reference table in a standard SAP ECC 6.0 system. | C178: Consistency | D178: BEGIN RETURN exists('SAP', 'TVKT', 'KTGRD', $P_I_AccountAssignmentGroup); END
A179: ZB_G13_MATNR_MaterialGroupReference | B179: Rule to check if Material Group value for Material master data is valid according to the available values in the appropriate reference table in a standard SAP ECC 6.0 system. | C179: Consistency | D179: BEGIN RETURN exists('SAP', 'T023', 'MATKL', $P_I_MaterialGroup); END
A180: ZB_G13_MATNR_QuotaArrangementUsageReference | B180: Rule to check if Quota Arrangement Usage value for Material master data is valid according to the available values in the appropriate reference table in a standard SAP ECC 6.0 system. | C180: Consistency | D180: BEGIN RETURN exists('SAP', 'TMQ2', 'USEQU', $P_I_QuotaArrangementUsage); END
A181: ZB_G13_MATNR_PurchasingValueKeyReference | B181: Rule to check if Purchasing Value Key value for Material master data is valid according to the available values in the appropriate reference table in a standard SAP ECC 6.0 system. | C181: Consistency | D181: BEGIN RETURN exists('SAP', 'T405', 'EKWSL', $P_I_PurchasingValueKey); END
A182: ZB_G14_CUST_ReconciliationAccountReference | B182: Rule to check if Reconciliation Account value for Business Partner / Customer / Vendor master data is valid according to the available values in the appropriate reference table in a standard SAP ECC 6.0 system. | C182: Consistency | D182: BEGIN RETURN exists('SAP', 'SKB1', 'SAKNR', $P_I_ReconciliationAccount); END
... A194: ZB_G15_VNDR_BankCountryKeyExists | B194: Rule to check if Bank country key exists for Business Partner / Customer / Vendor master data for a standard SAP ECC 6.0 system | C194: Completeness | D194: BEGIN RETURN $P_I_BankCountryKey IS NOT NULL AND $P_I_BankCountryKey != ''; END
A195: ZB_G15_VNDR_TitleDomainReference | C195: Consistency | D195: BEGIN RETURN exists('SAP', 'TSAD3T', 'TITLE_MEDI', $P_I_Title) OR $P_I_Title IS NULL OR $P_I_Title=''; END
A196: ZB_G15_VNDR_AccountGroupExists | B196: Rule to validate if Business Partner / Customer / Vendor Account group exists. | C196: Completeness | D196: BEGIN RETURN $P_I_AccountGroup IS NOT NULL AND $P_I_AccountGroup != ''; END
A197: ZB_G13_MATNR_BulkStorageRefeference | B197: Rule to check if Bulk Storage value for Material master data is valid according to the available values in the appropriate reference table in a standard SAP ECC 6.0 system. | C197: Consistency | D197: BEGIN RETURN exists('SAP', 'T338', 'BLOCK', $P_I_BulkStorage); END
A198: ZB_G14_CUST_DunningRecipientReference | B198: Rule to check if Dunning Recipient value for Business Partner / Customer / Vendor master data is valid according to the available values in the appropriate reference table in a standard SAP ECC 6.0 system. | C198: Consistency | D198: BEGIN RETURN exists('SAP', 'M_DEBID', 'KUNNR', $P_I_DunningRecipient); END
A199: ZB_G15_VNDR_ServiceAgentProcedureGroupReference | B199: Rule to check if Service Agent Procedure Group value for Vendor master data is valid according to the available values in the appropriate reference table in a standard SAP ECC 6.0 system. | C199: Consistency | D199: BEGIN RETURN exists('SAP', 'TVFCD', 'DLGRP', $P_I_ServiceAgentProcGroup); END
A200: ZB_G13_MATNR_DescriptionExists | B200: Rule to check for existence of Material Description in Material master data for a standard SAP ECC 6.0 system | C200: Completeness | D200: BEGIN RETURN $P_I_Description IS NOT NULL AND $P_I_Description != ''; END
A201: ZB_G14_CUST_VATRegistrationNumberExists | B201: Rule to validate if Business Partner / Customer / Vendor VAT Registration Number exists. It is specific to EU countries mostly | C201: Completeness | D201: BEGIN RETURN $P_I_VATRegNumber IS NOT NULL AND $P_I_VATRegNumber != ''; END
A202: ZB_G15_VNDR_FIYearVariantReference | B202: Rule to check if Fiscal Year Variant value for Business Partner / Customer / Vendor master data is valid according to the available values in the appropriate reference table in a standard SAP ECC 6.0 system. | C202: Consistency | D202: BEGIN RETURN exists('SAP', 'T009', 'PERIV', $P_I_FIYearVariant); END
A203: ZB_G15_VNDR_PODRelevantDomainReference | B203: Rule to check if POD Relevant value for a Business Partner / Customer / Vendor is valid according to the appropriate reference domain or value range for a standard SAP ECC 6.0 system. | C203: Consistency | D203: BEGIN RETURN $P_I_PODRelevant IS NULL OR length($P_I_PODRelevant) = 0 OR $P_I_PODRelevant IN ('A', 'B'); END
A204: ZB_G14_CUST_ReconAccountExists | B204: Rule to check if Reconciliation Account exists for Business Partner / Customer / Vendor master data for a standard SAP ECC 6.0 system | C204: Completeness | D204: BEGIN RETURN $P_I_ReconAccount IS NOT NULL AND $P_I_ReconAccount != ''; END
A205: ZB_G15_VNDR_TermsOfPaymentReference | B205: Rule to check if Terms of Payment key value for Business Partner / Customer / Vendor master data is valid according to the available values in the appropriate reference table in a standard SAP ECC 6.0 system. | C205: Consistency | D205: BEGIN RETURN exists('SAP', 'T052', 'ZTERM', $P_I_TermsOfPayment); END
A206: ZB_G13_MATNR_DeliveringPlantReference | B206: Rule to check if Delivering Plant value for Material master data is valid according to the available values in the appropriate reference table in a standard SAP ECC 6.0 system. | C206: Consistency | D206: BEGIN RETURN exists('SAP', 'T001W', 'WERKS', $P_I_DeliveringPlant); END
A207: ZB_G14_CUST_SortFieldExists | B207: Rule to validate if Sort Field for a Business Partner / Customer / Vendor exists. | C207: Completeness | D207: BEGIN RETURN $P_I_SortField IS NOT NULL AND $P_I_SortField != ''; END
... A251: ZB_G14_CUST_ToleranceGroupReference | B251: Rule to check if Tolerance Group value for Business Partner / Customer / Vendor master data is valid according to the available values in the appropriate reference table in a standard SAP ECC 6.0 system. | C251: Consistency | D251: BEGIN RETURN exists('SAP', 'T043G', 'TOGRU', $P_I_ToleranceGroup); END
A252: ZB_G13_MATNR_PlanningPlantReference | C252: Consistency | D252: BEGIN RETURN exists('SAP', 'H_MARC', 'WERKS', $P_I_PlanningPlant); END
A253: ZB_G13_MATNR_ControlCodeReference | B253: Rule to check if Control Code value for Material master data is valid according to the available values in the appropriate reference table in a standard SAP ECC 6.0 system. | C253: Consistency | D253: BEGIN RETURN exists('SAP', 'T604F', 'STEUC', $P_I_ControlCode); END
A254: ZB_G13_MATNR_IndividualOrCollectiveDomainReference | B254: Rule to check if Individual or Collective Requirements value for a Material master is valid according to the appropriate reference domain or value range for a standard SAP ECC 6.0 system. | C254: Consistency | D254: BEGIN RETURN $P_I_IndividualOrCollective IS NULL OR length($P_I_IndividualOrCollective) = 0 OR $P_I_IndividualOrCollective IN ('1', '2'); END
A255: ZB_G13_MATNR_SUT1or2or3Reference | B255: Rule to check if SUT 1 or 2 or 3 value for Material master data is valid according to the available values in the appropriate reference table in a standard SAP ECC 6.0 system. | C255: Consistency | D255: BEGIN RETURN exists('SAP', 'T307', 'LETYP', $P_I_SUT123); END
A256: ZB_G14_CUST_CanadaPOBoxPostalCodeFormat | B256: Rule to check if the PO Box Postal Code for Canadian address is in the format A9A 9A9 | C256: Conformity | D256: BEGIN RETURN $P_I_Country = 'CA' AND match_pattern($P_I_PostalCode, 'X9X 9X9'); END
A257: ZB_G15_VNDR_SortFieldExists | B257: Rule to validate if Sort Field for a Business Partner / Customer / Vendor exists. | C257: Completeness | D257: BEGIN RETURN $P_I_SortField IS NOT NULL AND $P_I_SortField != ''; END
A258: ZB_G13_MATNR_MixedMRPDomainReference | B258: Rule to check if Mixed MRP value for a Material master is valid according to the appropriate reference domain or value range for a standard SAP ECC 6.0 system. | C258: Consistency | D258: BEGIN RETURN $P_I_MixedMRP IS NULL OR $P_I_MixedMRP IN ('1','2', '3'); END
A259: ZB_G14_CUST_MissiletechnologyDomainReference | B259: Rule to check if Missle Technology Indicator value for a Customer is valid according to the appropriate reference domain or value range for a standard SAP ECC 6.0 system. | C259: Consistency | D259: BEGIN RETURN $P_I_MissleTechnologyInd IS NULL OR length($P_I_MissleTechnologyInd) = 0 OR $P_I_MissleTechnologyInd = 'X'; END
A260: ZB_G15_VNDR_NextPayeeReference | B260: Rule to check if Next Payee value for Business Partner / Customer / Vendor master data is valid according to the available values in the appropriate reference table in a standard SAP ECC 6.0 system. | C260: Consistency | D260: BEGIN RETURN exists('SAP', 'M_DEBID', 'KUNNR', $P_I_NextPayee); END
A261: ZB_G14_CUST_USPostalCodeFormat | B261: Rule to check if a US ZIP code is in the valid format | C261: Conformity | D261: BEGIN RETURN match_pattern($P_I_ZIP, '99999') OR match_pattern($P_I_ZIP, '99999-9999'); END
A262: ZB_G13_MATNR_JITSchedulingIndicatordomainReference | B262: Rule to check if JIT Scheduling Indicator value for a Material master is valid according to the appropriate reference domain or value range for a standard SAP ECC 6.0 system. | C262: Consistency | D262: BEGIN RETURN $P_I_JITSchedulingInd IS NULL OR length($P_I_JITSchedulingInd) = 0 OR $P_I_JITSchedulingInd IN ('1'); END
A263: ZB_G14_CUST_MaritalStatusReference | B263: Rule to check if Marital Status value for Business Partner / Customer / Vendor master data is valid according to the available values in the appropriate reference table in a standard SAP ECC 6.0 system. | C263: Consistency | D263: BEGIN RETURN exists('SAP', 'T502T', 'FAMST', $P_I_MaritalStatus); END
A264: ZB_G14_CUST_CanadaPostalCodeFormat | B264: Rule to check if the Postal Code for Canadian address is in the format A9A 9A9 | C264: Conformity | D264: BEGIN RETURN $P_I_Country = 'CA' AND match_pattern($P_I_PostalCode, 'X9X 9X9'); END
... A319: ZB_G15_VNDR_IncotermsPart1Reference | B319: Rule to check if Incoterms (Part 1) value for Business Partner / Customer / Vendor master data is valid according to the available values in the appropriate reference table in a standard SAP ECC 6.0 system. | C319: Consistency | D319: BEGIN RETURN exists('SAP', 'TINC', 'INCO1', $P_I_Incoterms); END
A320: ZB_G14_CUST_TitleDomainReference | C320: Consistency | D320: BEGIN RETURN exists('SAP', 'TSAD3T', 'TITLE_MEDI', $P_I_Title) OR $P_I_Title IS NULL OR $P_I_Title=''; END
A321: ZB_G13_MATNR_MaterialGroup2Reference | B321: Rule to check if Material Group 2 value for Material master data is valid according to the available values in the appropriate reference table in a standard SAP ECC 6.0 system. | C321: Consistency | D321: BEGIN RETURN exists('SAP', 'TVM2', 'MVGR2', $P_I_MatGroup2); END
A322: ZB_G14_CUST_TDOBoycottListDomainReference | B322: Rule to check if TDO Boycott list value for a Customer is valid according to the appropriate reference domain or value range for a standard SAP ECC 6.0 system. | C322: Consistency | D322: BEGIN RETURN $P_I_TDOBoycottList IS NULL OR length($P_I_TDOBoycottList) = 0 OR $P_I_TDOBoycottList = 'X'; END
A323: ZB_G15_VNDR_ToleranceGroupReference | B323: Rule to check if Tolerance Group value for Business Partner / Customer / Vendor master data is valid according to the available values in the appropriate reference table in a standard SAP ECC 6.0 system. | C323: Consistency | D323: BEGIN RETURN exists('SAP', 'T043G', 'TOGRU', $P_I_ToleranceGroup); END
A324: ZB_G15_VNDR_ActualQMSystemReference | B324: Rule to check if Actual QM System value for Vendor master data is valid according to the available values in the appropriate reference table in a standard SAP ECC 6.0 system. | C324: Consistency | D324: BEGIN RETURN exists('SAP', 'TQ02B', 'QSSYSFAM', $P_I_ActuaQMSystem); END
A325: ZB_G15_VNDR_ConfirmationControlReference | B325: Rule to check if Confirmation Control value for Vendor master data is valid according to the available values in the appropriate reference table in a standard SAP ECC 6.0 system. | C325: Consistency | D325: BEGIN RETURN exists('SAP', 'T163L', 'BSTAE', $P_I_ConfirmationControl); END
A326: ZB_G14_CUST_DunningProcedureReference | B326: Rule to check if Dunning Procedure value for Business Partner / Customer / Vendor master data is valid according to the available values in the appropriate reference table in a standard SAP ECC 6.0 system. | C326: Consistency | D326: BEGIN RETURN exists('SAP', 'T047A', 'MAHNA', $P_I_DunningProcedure); END
A327: ZB_G14_CUST_ContactPersonDepartmentReference | B327: Rule to check if Contact Person > Department value for Business Partner / Customer / Vendor master data is valid according to the available values in the appropriate reference table in a standard SAP ECC 6.0 system. | C327: Consistency | D327: BEGIN RETURN exists('SAP', 'TSAB', 'ABTNR', $P_I_Department); END
A328: ZB_G15_VNDR_PaymentMethodReference | B328: Rule to check if Payment Method value for Business Partner / Customer / Vendor master data is valid according to the available values in the appropriate reference table in a standard SAP ECC 6.0 system. | C328: Consistency | D328: BEGIN RETURN exists('SAP', 'T042Z', 'ZLSCH', $P_I_PaymentMethod); END
A329: ZB_G15_VNDR_DunningBlockReference | B329: Rule to check if Dunning Block value for Business Partner / Customer / Vendor master data is valid according to the available values in the appropriate reference table in a standard SAP ECC 6.0 system. | C329: Consistency | D329: BEGIN RETURN exists('SAP', 'T040S', 'MANSP', $P_I_DunningBlock); END
A330: ZB_G15_VNDR_TaxNumberTypeReference | B330: Rule to check if Tax Number Type value for Vendor master data is valid according to the available values in the appropriate reference table in a standard SAP ECC 6.0 system. | C330: Consistency | D330: BEGIN RETURN exists('SAP', 'J_1ATODC', 'J_1ATODC', $P_I_TaxNumberType); END
A331: ZB_G15_VNDR_CustomerNumber1Reference | B331: Rule to check if Customer Number 1 value for Vendor master data is valid according to the available values in the appropriate reference table in a standard SAP ECC 6.0 system. | C331: Consistency | D331: BEGIN RETURN exists('SAP', 'M_DEBIA', 'KUNNR', $P_I_CustomerNumber); END
A332: ZB_G13_MATNR_MaterialTypeExists | B332: Rule to check for existence of Material Type in Material master data for a standard SAP ECC 6.0 system | C332: Completeness | D332: BEGIN RETURN $P_I_MaterialType IS NOT NULL AND $P_I_MaterialType != ''; END
... A371: ZB_G15_VNDR_DunningProcedureReference | B371: Rule to check if Dunning Procedure value for Business Partner / Customer / Vendor master data is valid according to the available values in the appropriate reference table in a standard SAP ECC 6.0 system. | C371: Consistency | D371: BEGIN RETURN exists('SAP', 'T047A', 'MAHNA', $P_I_DunningProcedure); END

Sheet IS_Binding_Rule_to_Views
A1: Rule Name | B1: Attribute | C1: Attribute Parameter (IS Internal) | D1: View Name (IS Internal) | E1: Notes
A2: ZB_G14_CUST_AccountingClerkReference | B2: Acctg clerk | C2: $P_I_AccountingClerk | D2: ZB_G14_CUST_CompanyCodeData_Correspondence
A3: ZB_G14_CUST_BankStatementIndicatorReference | B3: Bank statement | C3: $P_I_BankStmtInd | D3: ZB_G14_CUST_CompanyCodeData_Correspondence
A4: ZB_G14_CUST_DunningBlockReference | B4: Dunning block | C4: $P_I_DunningBlock | D4: ZB_G14_CUST_CompanyCodeData_Correspondence
A5: ZB_G14_CUST_DunningClerkReference | B5: Dunning clerk | C5: $P_I_DunningClerk | D5: ZB_G14_CUST_CompanyCodeData_Correspondence
A6: ZB_G14_CUST_DunningNoticeGroupingKeyReference | B6: Grouping key | C6: $P_I_DunningNoticeGroupingkey | D6: ZB_G14_CUST_CompanyCodeData_Correspondence
A7: ZB_G14_CUST_DunningProcedureReference | B7: Dunn Procedure | C7: $P_I_DunningProcedure | D7: ZB_G14_CUST_CompanyCodeData_Correspondence
A8: ZB_G14_CUST_DunningRecipientReference | B8: Dunn Recipient | C8: $P_I_DunningRecipient | D8: ZB_G14_CUST_CompanyCodeData_Correspondence
A9: ZB_G14_CUST_TermsOfPaymentExists | B9: Terms of payment | C9: $P_I_TermsOfPayment | D9: ZB_G14_CUST_CompanyCodeData_PaymentTransactions
A10: ZB_G14_CUST_CompanyCodeExists | B10: Company Code | C10: $P_I_CompanyCode | D10: ZB_G14_CUST_CompanyCodeData_PaymentTransactions
A11: ZB_G14_CUST_BillOfExchangePaymentTermReference | B11: B e charges payt term | C11: $P_I_BePaymentTerm | D11: ZB_G14_CUST_CompanyCodeData_PaymentTransactions
A12: ZB_G14_CUST_CustomerCompanyCodeReference | B12: Company Code | C12: $P_I_CompanyCode | D12: ZB_G14_CUST_CompanyCodeData_PaymentTransactions
A13: ZB_G14_CUST_GroupingKeyReference | B13: Grouping key | C13: $P_I_GroupingKey | D13: ZB_G14_CUST_CompanyCodeData_PaymentTransactions
... A324: ZB_G14_CUST_USPostalCodeFormat | B324: Country | C324: $P_I_Country | D324: ZB_G14_CUST_GeneralData_Address

Sheet IS_Views
A1: View Name (IS Internal) | B1: View Description | C1: Nullable Attribute | D1: Attribute Description | E1: SAP Table.AttributeName | F1: Attribute Name | G1: Attribute Description2 | H1: Data Type | I1: Length | J1: Precision | K1: Scale | L1: Connection Name | M1: Table Name | N1: Join Type | O1: Join Expression | P1: Filter expression
A2: ZB_G13_MATNR_Accounting1 | B2: Material Accounting data view 1 for a standard SAP ECC 6.0 system | C2: FALSE | D2: Material | E2: SAP.MARA.MATNR | F2: MATNR | H2: varchar | I2: 18 | P2: SAP.MAKT.SPRAS = 'E'
A3: ZB_G13_MATNR_Accounting1 | B3: Material Accounting data view 1 for a standard SAP ECC 6.0 system | C3: TRUE | D3: Description | E3: SAP.MAKT.MAKTX | F3: MAKTX | H3: varchar | I3: 40 | P3: SAP.MAKT.SPRAS = 'E'
A4: ZB_G13_MATNR_Accounting1 | B4: Material Accounting data view 1 for a standard SAP ECC 6.0 system | C4: TRUE | D4: Material Type | E4: SAP.MARA.MTART | F4: MTART | G4: Material Type | H4: varchar | I4: 4 | P4: SAP.MAKT.SPRAS = 'E'
A5: ZB_G13_MATNR_Accounting1 | B5: Material Accounting data view 1 for a standard SAP ECC 6.0 system | C5: FALSE | D5: Plant | E5: SAP.MARC.WERKS | F5: WERKS | H5: varchar | I5: 4 | P5: SAP.MAKT.SPRAS = 'E'
A6: ZB_G13_MATNR_Accounting1 | B6: Material Accounting data view 1 for a standard SAP ECC 6.0 system | C6: TRUE | D6: Base Unit of Measure | E6: SAP.MARA.MEINS | F6: MEINS | H6: varchar | I6: 3 | P6: SAP.MAKT.SPRAS = 'E'
A7: ZB_G13_MATNR_Accounting1 | B7: Material Accounting data view 1 for a standard SAP ECC 6.0 system | C7: TRUE | D7: Valuation Category | E7: SAP.MARC.BWTTY | F7: BWTTY | H7: varchar | I7: 1 | P7: SAP.MAKT.SPRAS = 'E'
A8: ZB_G13_MATNR_Accounting1 | B8: Material Accounting data view 1 for a standard SAP ECC 6.0 system | C8: TRUE | D8: Division | E8: SAP.MARA.SPART | F8: SPART | H8: varchar | I8: 2 | P8: SAP.MAKT.SPRAS = 'E'
A9: ZB_G13_MATNR_Accounting1 | B9: Material Accounting data view 1 for a standard SAP ECC 6.0 system | C9: TRUE | D9: Price determ | E9: SAP.MBEW.MLAST | F9: MLAST | G9: Material Price Determination: Control | H9: varchar | I9: 1 | P9: SAP.MAKT.SPRAS = 'E'
A10: ZB_G13_MATNR_Accounting1 | B10: Material Accounting data view 1 for a standard SAP ECC 6.0 system | C10: TRUE | D10: ML act | E10: SAP.MBEW.MLMAA | F10: MLMAA | G10: Material ledger activated at material level | H10: varchar | I10: 1 | P10: SAP.MAKT.SPRAS = 'E'
A11: ZB_G13_MATNR_Accounting1 | B11: Material Accounting data view 1 for a standard SAP ECC 6.0 system | C11: TRUE | D11: Valuation Class | E11: SAP.MBEW.BKLAS | F11: BKLAS | G11: Valuation Class | H11: varchar | I11: 4 | P11: SAP.MAKT.SPRAS = 'E'
A12: ZB_G13_MATNR_Accounting1 | B12: Material Accounting data view 1 for a standard SAP ECC 6.0 system | C12: TRUE | D12: VC Sales order stk | E12: SAP.MBEW.EKLAS | F12: EKLAS | G12: Valuation Class for Sales Order Stock | H12: varchar | I12: 4 | P12: SAP.MAKT.SPRAS = 'E'
A13: ZB_G13_MATNR_Accounting1 | B13: Material Accounting data view 1 for a standard SAP ECC 6.0 system | C13: TRUE | D13: Proj stk val class | E13: SAP.MBEW.QKLAS | F13: QKLAS | G13: Valuation Class for Project Stock | H13: varchar | I13: 4 | P13: SAP.MAKT.SPRAS = 'E'
A14: ZB_G13_MATNR_Accounting1 | B14: Material Accounting data view 1 for a standard SAP ECC 6.0 system | C14: TRUE | D14: Price control | E14: SAP.MBEW.VPRSV | F14: VPRSV | G14: Price control indicator | H14: varchar | I14: 1 | P14: SAP.MAKT.SPRAS = 'E'
A15: ZB_G13_MATNR_Accounting1 | B15: Material Accounting data view 1 for a standard SAP ECC 6.0 system | C15: TRUE | D15: Price unit | E15: SAP.MBEW.PEINH | F15: PEINH | G15: Price Unit | H15: decimal | J15: 5 | K15: 0 | P15: SAP.MAKT.SPRAS = 'E'
A16: ZB_G13_MATNR_Accounting1 | B16: Material Accounting data view 1 for a standard SAP ECC 6.0 system | C16: TRUE | D16: Moving price | E16: SAP.MBEW.VERPR | F16: VERPR | G16: Moving Average Price/Periodic Unit Price | H16: decimal | J16: 11 | K16: 2 | P16: SAP.MAKT.SPRAS = 'E'
A17: ZB_G13_MATNR_Accounting1 | B17: Material Accounting data view 1 for a standard SAP ECC 6.0 system | C17: TRUE | D17: Standard price | E17: SAP.MBEW.STPRS | F17: STPRS | G17: Standard price | H17: decimal | J17: 11 | K17: 2 | P17: SAP.MAKT.SPRAS = 'E'
A18: ZB_G13_MATNR_Accounting1 | B18: Material Accounting data view 1 for a standard SAP ECC 6.0 system | C18: TRUE | D18: Total Stock | E18: SAP.MBEW.LBKUM | F18: LBKUM | G18: Total Valuated Stock | H18: decimal | J18: 13 | K18: 3 | P18: SAP.MAKT.SPRAS = 'E'
A19: ZB_G13_MATNR_Accounting1 | B19: Material Accounting data view 1 for a standard SAP ECC 6.0 system | C19: TRUE | D19: Total value | E19: SAP.MBEW.SALK3 | F19: SALK3 | G19: Value of Total Valuated Stock | H19: decimal | J19: 13 | K19: 2 | P19: SAP.MAKT.SPRAS = 'E'
A20: ZB_G13_MATNR_Accounting1 | B20: Material Accounting data view 1 for a standard SAP ECC 6.0 system | C20: TRUE | D20: Valuated Un | E20: SAP.MBEW.XBEWM | F20: XBEWM | G20: Valuation based on the batch-specific unit of measure | H20: varchar | I20: 1 | P20: SAP.MAKT.SPRAS = 'E'
A21: ZB_G13_MATNR_Accounting1 | B21: Material Accounting data view 1 for a standard SAP ECC 6.0 system | C21: TRUE | D21: Future price | E21: SAP.MBEW.ZKPRS | F21: ZKPRS | G21: Future price | H21: decimal | J21: 11 | K21: 2 | P21: SAP.MAKT.SPRAS = 'E'
A22: ZB_G13_MATNR_Accounting1 | B22: Material Accounting data view 1 for a standard SAP ECC 6.0 system | C22: TRUE | D22: Valid from | E22: SAP.MBEW.ZKDAT | F22: ZKDAT | G22: Date as of which the price is valid | H22: date | P22: SAP.MAKT.SPRAS = 'E'
A23: ZB_G13_MATNR_Accounting1 | B23: Material Accounting data view 1 for a standard SAP ECC 6.0 system | L23: SAP | M23: MAKT | P23: SAP.MAKT.SPRAS = 'E'
A24: ZB_G13_MATNR_Accounting1 | B24: Material Accounting data view 1 for a standard SAP ECC 6.0 system | L24: SAP | M24: MARA | P24: SAP.MAKT.SPRAS = 'E'
A25: ZB_G13_MATNR_Accounting1 | B25: Material Accounting data view 1 for a standard SAP ECC 6.0 system | L25: SAP | M25: MARC | P25: SAP.MAKT.SPRAS = 'E'
A26: ZB_G13_MATNR_Accounting1 | B26: Material Accounting data view 1 for a standard SAP ECC 6.0 system | L26: SAP | M26: MBEW | P26: SAP.MAKT.SPRAS = 'E'
A27: ZB_G13_MATNR_Accounting1 | B27: Material Accounting data view 1 for a standard SAP ECC 6.0 system | N27: inner | O27: ZB_G14_CUST_DunningRecipientReference | P27: SAP.MAKT.SPRAS = 'E'
A28: ZB_G13_MATNR_Accounting1 | B28: Material Accounting data view 1 for a standard SAP ECC 6.0 system | N28: inner | O28: SAP.MAKT.MATNR = SAP.MBEW.MATNR | P28: SAP.MAKT.SPRAS = 'E'
A29: ZB_G13_MATNR_Accounting1 | B29: Material Accounting data view 1 for a standard SAP ECC 6.0 system | N29: inner | O29: SAP.MAKT.MATNR = SAP.MARA.MATNR AND SAP.MARA.MATNR = SAP.MBEW.MATNR | P29: SAP.MAKT.SPRAS = 'E'
A30: ZB_G13_MATNR_Accounting1 | B30: Material Accounting data view 1 for a standard SAP ECC 6.0 system | N30: inner | O30: SAP.MAKT.MATNR = SAP.MARA.MATNR AND SAP.MARA.MATNR = SAP.MBEW.MATNR | P30: SAP.MAKT.SPRAS = 'E'
A31: ZB_G13_MATNR_Accounting1 | B31: Material Accounting data view 1 for a standard SAP ECC 6.0 system | N31: inner | O31: SAP.MAKT.MATNR = SAP.MARA.MATNR AND SAP.MARA.MATNR = SAP.MBEW.MATNR | P31: SAP.MAKT.SPRAS = 'E'
A32: ZB_G13_MATNR_Accounting1 | B32: Material Accounting data view 1 for a standard SAP ECC 6.0 system | N32: inner | O32: SAP.MAKT.MATNR = SAP.MARC.MATNR AND SAP.MARA.MATNR = SAP.MARC.MATNR AND SAP.MARC.MATNR = SAP.MBEW.MATNR | P32: SAP.MAKT.SPRAS = 'E'
A33: ZB_G13_MATNR_Accounting1 | B33: Material Accounting data view 1 for a standard SAP ECC 6.0 system | N33: inner | O33: SAP.MAKT.MATNR = SAP.MARC.MATNR AND SAP.MARA.MATNR = SAP.MARC.MATNR AND SAP.MARC.MATNR = SAP.MBEW.MATNR | P33: SAP.MAKT.SPRAS = 'E'
A34: ZB_G13_MATNR_Accounting1 | B34: Material Accounting data view 1 for a standard SAP ECC 6.0 system | N34: inner | O34: SAP.MAKT.MATNR = SAP.MARC.MATNR AND SAP.MARA.MATNR = SAP.MARC.MATNR AND SAP.MARC.MATNR = SAP.MBEW.MATNR | P34: SAP.MAKT.SPRAS = 'E'
A35: ZB_G13_MATNR_Accounting1 | B35: Material Accounting data view 1 for a standard SAP ECC 6.0 system | N35: inner | O35: SAP.MAKT.MATNR = SAP.MARC.MATNR AND SAP.MARA.MATNR = SAP.MARC.MATNR AND SAP.MARC.MATNR = SAP.MBEW.MATNR | P35: SAP.MAKT.SPRAS = 'E'
A36: ZB_G13_MATNR_Accounting2 | B36: Material Accounting data view 2 for a standard SAP ECC 6.0 system | C36: FALSE | D36: Material | E36: SAP.MARA.MATNR | F36: MATNR | H36: varchar | I36: 18 | P36: SAP.MAKT.SPRAS = 'E'
A37: ZB_G13_MATNR_Accounting2 | B37: Material Accounting data view 2 for a standard SAP ECC 6.0 system | C37: TRUE | D37: Description | E37: SAP.MAKT.MAKTX | F37: MAKTX | H37: varchar | I37: 40 | P37: SAP.MAKT.SPRAS = 'E'
A38: ZB_G13_MATNR_Accounting2 | B38: Material Accounting data view 2 for a standard SAP ECC 6.0 system | C38: TRUE | D38: Material Type | E38: SAP.MARA.MTART | F38: MTART | G38: Material Type | H38: varchar | I38: 4 | P38: SAP.MAKT.SPRAS = 'E'
A39: ZB_G13_MATNR_Accounting2 | B39: Material Accounting data view 2 for a standard SAP ECC 6.0 system | C39: FALSE | D39: Plant | E39: SAP.MARC.WERKS | F39: WERKS | H39: varchar | I39: 4 | P39: SAP.MAKT.SPRAS = 'E'
A40: ZB_G13_MATNR_Accounting2 | B40: Material Accounting data view 2 for a standard SAP ECC 6.0 system | C40: TRUE | D40: Tax price 1 | E40: SAP.MBEW.BWPRS | F40: BWPRS | G40: Valuation price based on tax law: level 1 | H40: decimal | J40: 11 | K40: 2 | P40: SAP.MAKT.SPRAS = 'E'
A41: ZB_G13_MATNR_Accounting2 | B41: Material Accounting data view 2 for a standard SAP ECC 6.0 system | C41: TRUE | D41: Tax price 2 | E41: SAP.MBEW.BWPS1 | F41: BWPS1 | G41: Valuation price based on tax law: level 2 | H41: decimal | J41: 11 | K41: 2 | P41: SAP.MAKT.SPRAS = 'E'
A42: ZB_G13_MATNR_Accounting2 | B42: Material Accounting data view 2 for a standard SAP ECC 6.0 system | C42: TRUE | D42: Tax price 3 | E42: SAP.MBEW.VJBWS | F42: VJBWS | G42: Valuation price based on tax law: level 3 | H42: decimal | J42: 11 | K42: 2 | P42: SAP.MAKT.SPRAS = 'E'
A43: ZB_G13_MATNR_Accounting2 | B43: Material Accounting data view 2 for a standard SAP ECC 6.0 system | C43: TRUE | D43: Commercial price 1 | E43: SAP.MBEW.BWPRH | F43: BWPRH | G43: Valuation price based on commercial law: level 1 | H43: decimal | J43: 11 | K43: 2 | P43: SAP.MAKT.SPRAS = 'E'
A44: ZB_G13_MATNR_Accounting2 | B44: Material Accounting data view 2 for a standard SAP ECC 6.0 system | C44: TRUE | D44: Commercial price 2 | E44: SAP.MBEW.BWPH1 | F44: BWPH1 | G44: Valuation price based on commercial law: level 2 | H44: decimal | J44: 11 | K44: 2 | P44: SAP.MAKT.SPRAS = 'E'
A45: ZB_G13_MATNR_Accounting2 | B45: Material Accounting data view 2 for a standard SAP ECC 6.0 system | C45: TRUE | D45: Commercial price 3 | E45: SAP.MBEW.VJBWH | F45: VJBWH | G45: Valuation price based on commercial law: level 3 | H45: decimal | J45: 11 | K45: 2 | P45: SAP.MAKT.SPRAS = 'E'
A46: ZB_G13_MATNR_Accounting2 | B46: Material Accounting data view 2 for a standard SAP ECC 6.0 system | C46: TRUE | D46: Devaluation ind | E46: SAP.MBEW.ABWKZ | F46: ABWKZ | G46: Lowest value: devaluation indicator | H46: numeric | J46: 2 | K46: 0 | P46: SAP.MAKT.SPRAS = 'E'
A47: ZB_G13_MATNR_Accounting2 | B47: Material Accounting data view 2 for a standard SAP ECC 6.0 system | C47: TRUE | D47: Price unit | E47: SAP.MBEW.BWPEI | F47: BWPEI | G47: Price unit for valuation prices based on tax/commercial law | H47: decimal | J47: 5 | K47: 0 | P47: SAP.MAKT.SPRAS = 'E'
A48: ZB_G13_MATNR_Accounting2 | B48: Material Accounting data view 2 for a standard SAP ECC 6.0 system | C48: TRUE | D48: LIFO FIFO relevant | E48: SAP.MBEW.XLIFO | F48: XLIFO | G48: LIFO/FIFO-Relevant | H48: varchar | I48: 1 | P48: SAP.MAKT.SPRAS = 'E'
A49: ZB_G13_MATNR_Accounting2 | B49: Material Accounting data view 2 for a standard SAP ECC 6.0 system | C49: TRUE | D49: LIFO pool | E49: SAP.MBEW.MYPOL | F49: MYPOL | G49: Pool number for LIFO valuation | H49: varchar | I49: 4 | P49: SAP.MAKT.SPRAS = 'E'
A50: ZB_G13_MATNR_Accounting2 | B50: Material Accounting data view 2 for a standard SAP ECC 6.0 system | L50: SAP | M50: MAKT | P50: SAP.MAKT.SPRAS = 'E'
A51: ZB_G13_MATNR_Accounting2 | B51: Material Accounting data view 2 for a standard SAP ECC 6.0 system | L51: SAP | M51: MARA | P51: SAP.MAKT.SPRAS = 'E'
A52: ZB_G13_MATNR_Accounting2 | B52: Material Accounting data view 2 for a standard SAP ECC 6.0 system | L52: SAP | M52: MARC | P52: SAP.MAKT.SPRAS = 'E'
A53: ZB_G13_MATNR_Accounting2 | B53: Material Accounting data view 2 for a standard SAP ECC 6.0 system | L53: SAP | M53: MBEW | P53: SAP.MAKT.SPRAS = 'E'
A54: ZB_G13_MATNR_Accounting2 | B54: Material Accounting data view 2 for a standard SAP ECC 6.0 system | N54: inner | O54: SAP.MAKT.MATNR = SAP.MARA.MATNR | P54: SAP.MAKT.SPRAS = 'E'
A55: ZB_G13_MATNR_Accounting2 | B55: Material Accounting data view 2 for a standard SAP ECC 6.0 system | N55: inner | O55: SAP.MAKT.MATNR = SAP.MARA.MATNR | P55: SAP.MAKT.SPRAS = 'E'
A56: ZB_G13_MATNR_Accounting2 | B56: Material Accounting data view 2 for a standard SAP ECC 6.0 system | N56: inner | O56: SAP.MAKT.MATNR = SAP.MARC.MATNR AND SAP.MARA.MATNR = SAP.MARC.MATNR | P56: SAP.MAKT.SPRAS = 'E'
A57: ZB_G13_MATNR_Accounting2 | B57: Material Accounting data view 2 for a standard SAP ECC 6.0 system | N57: inner | O57: SAP.MAKT.MATNR = SAP.MARC.MATNR AND SAP.MARA.MATNR = SAP.MARC.MATNR | P57: SAP.MAKT.SPRAS = 'E'
A58: ZB_G13_MATNR_Accounting2 | B58: Material Accounting data view 2 for a standard SAP ECC 6.0 system | N58: inner | O58: SAP.MAKT.MATNR = SAP.MARC.MATNR AND SAP.MARA.MATNR = SAP.MARC.MATNR | P58: SAP.MAKT.SPRAS = 'E'
A59: ZB_G13_MATNR_Accounting2 | B59: Material Accounting data view 2 for a standard SAP ECC 6.0 system | N59: inner | O59: SAP.MAKT.MATNR = SAP.MBEW.MATNR AND SAP.MARA.MATNR = SAP.MBEW.MATNR AND SAP.MARC.MATNR = SAP.MBEW.MATNR | P59: SAP.MAKT.SPRAS = 'E'
A60: ZB_G13_MATNR_Accounting2 | B60: Material Accounting data view 2 for a standard SAP ECC 6.0 system | N60: inner | O60: SAP.MAKT.MATNR = SAP.MBEW.MATNR AND SAP.MARA.MATNR = SAP.MBEW.MATNR AND SAP.MARC.MATNR = SAP.MBEW.MATNR | P60: SAP.MAKT.SPRAS = 'E'
A61: ZB_G13_MATNR_Accounting2 | B61: Material Accounting data view 2 for a standard SAP ECC 6.0 system | N61: inner | O61: SAP.MAKT.MATNR = SAP.MBEW.MATNR AND SAP.MARA.MATNR = SAP.MBEW.MATNR AND SAP.MARC.MATNR = SAP.MBEW.MATNR | P61: SAP.MAKT.SPRAS = 'E'
A62: ZB_G13_MATNR_Accounting2 | B62: Material Accounting data view 2 for a standard SAP ECC 6.0 system | N62: inner | O62: SAP.MAKT.MATNR = SAP.MBEW.MATNR AND SAP.MARA.MATNR = SAP.MBEW.MATNR AND SAP.MARC.MATNR = SAP.MBEW.MATNR | P62: SAP.MAKT.SPRAS = 'E'
A63: ZB_G13_MATNR_BasicData1 | B63: Material Master Basic Data View 1 for a standard SAP ECC 6.0 system. | C63: FALSE | D63: Material | E63: SAP.MARA.MATNR | F63: MATNR | G63: Material Number | H63: varchar | I63: 18 | P63: SAP.MAKT.SPRAS = 'E'
A64: ZB_G13_MATNR_BasicData1 | B64: Material Master Basic Data View 1 for a standard SAP ECC 6.0 system. | C64: TRUE | D64: Description | E64: SAP.MAKT.MAKTX | F64: MAKTX | G64: Material Description (Short Text) | H64: varchar | I64: 40 | P64: SAP.MAKT.SPRAS = 'E'
A65: ZB_G13_MATNR_BasicData1 | B65: Material Master Basic Data View 1 for a standard SAP ECC 6.0 system. | C65: TRUE | D65: Industry Sector | E65: SAP.MARA.MBRSH | F65: MBRSH | G65: Industry sector | H65: varchar | I65: 1 | P65: SAP.MAKT.SPRAS = 'E'
A66: ZB_G13_MATNR_BasicData1 | B66: Material Master Basic Data View 1 for a standard SAP ECC 6.0 system. | C66: TRUE | D66: Material Type | E66: SAP.MARA.MTART | F66: MTART | G66: Material Type | H66: varchar | I66: 4 | P66: SAP.MAKT.SPRAS = 'E'
A67: ZB_G13_MATNR_BasicData1 | B67: Material Master Basic Data View 1 for a standard SAP ECC 6.0 system. | C67: TRUE | D67: Base Unit of Measure | E67: SAP.MARA.MEINS | F67: MEINS | G67: Base Unit of Measure | H67: varchar | I67: 3 | P67: SAP.MAKT.SPRAS = 'E'
A68: ZB_G13_MATNR_BasicData1 | B68: Material Master Basic Data View 1 for a standard SAP ECC 6.0 system. | C68: TRUE | D68: Old Material Number | E68: SAP.MARA.BISMT | F68: BISMT | G68: Old material number | H68: varchar | I68: 18 | P68: SAP.MAKT.SPRAS = 'E'
A69: ZB_G13_MATNR_BasicData1 | B69: Material Master Basic Data View 1 for a standard SAP ECC 6.0 system. | C69: TRUE | D69: Division | E69: SAP.MARA.SPART | F69: SPART | G69: Division | H69: varchar | I69: 2 | P69: SAP.MAKT.SPRAS = 'E'
A70: ZB_G13_MATNR_BasicData1 | B70: Material Master Basic Data View 1 for a standard SAP ECC 6.0 system. | C70: TRUE | D70: Product Allocation | E70: SAP.MARA.KOSCH | F70: KOSCH | G70: Product allocation determination procedure | H70: varchar | I70: 18 | P70: SAP.MAKT.SPRAS = 'E'
A71: ZB_G13_MATNR_BasicData1 | B71: Material Master Basic Data View 1 for a standard SAP ECC 6.0 system. | C71: TRUE | D71: X Plant matl status | E71: SAP.MARA.MSTAE | F71: MSTAE | G71: Cross-Plant Material Status | H71: varchar | I71: 2 | P71: SAP.MAKT.SPRAS = 'E'
A72: ZB_G13_MATNR_BasicData1 | B72: Material Master Basic Data View 1 for a standard SAP ECC 6.0 system. | C72: TRUE | D72: Assign effect vals | E72: SAP.MARA.KZEFF | F72: KZEFF | G72: Assign effectivity parameter values/ override change numbers | H72: varchar | I72: 1 | P72: SAP.MAKT.SPRAS = 'E'
A73: ZB_G13_MATNR_BasicData1 | B73: Material Master Basic Data View 1 for a standard SAP ECC 6.0 system. | C73: TRUE | D73: Material Group | E73: SAP.MARA.MATKL | F73: MATKL | G73: Material Group | H73: varchar | I73: 9 | P73: SAP.MAKT.SPRAS = 'E'
A74: ZB_G13_MATNR_BasicData1 | B74: Material Master Basic Data View 1 for a standard SAP ECC 6.0 system. | C74: TRUE | D74: Ext Matl Group | E74: SAP.MARA.EXTWG | F74: EXTWG | G74: External Material Group | H74: varchar | I74: 18 | P74: SAP.MAKT.SPRAS = 'E'
... A76: ZB_G13_MATNR_BasicData1 | B76: Material Master Basic Data View 1 for a standard SAP ECC 6.0 system. | C76: TRUE | D76: Prod hierarchy | E76: SAP.MARA.PRDHA | F76: PRDHA | G76: Product hierarchy | H76: varchar | I76: 18 | P76: SAP.MAKT.SPRAS = 'E'
A77: ZB_G13_MATNR_BasicData1 | B77: Material Master Basic Data View 1 for a standard SAP ECC 6.0 system. | C77: TRUE | D77: Valid From | E77: SAP.MARA.MSTDE | F77: MSTDE | G77: Date from which the cross-plant material status is valid | H77: date | P77: SAP.MAKT.SPRAS = 'E'
A78: ZB_G13_MATNR_BasicData1 | B78: Material Master Basic Data View 1 for a standard SAP ECC 6.0 system. | C78: TRUE | D78: GenItemCatGroup | E78: SAP.MARA.MTPOS_MARA | F78: MTPOS_MARA | G78: General item category group | H78: varchar | I78: 4 | P78: SAP.MAKT.SPRAS = 'E'
A79: ZB_G13_MATNR_BasicData1 | B79: Material Master Basic Data View 1 for a standard SAP ECC 6.0 system. | C79: TRUE | D79: Gross Weight | E79: SAP.MARA.BRGEW | F79: BRGEW | G79: Gross Weight | H79: decimal | J79: 13 | K79: 3 | P79: SAP.MAKT.SPRAS = 'E'
A80: ZB_G13_MATNR_BasicData1 | B80: Material Master Basic Data View 1 for a standard SAP ECC 6.0 system. | C80: TRUE | D80: Net Weight | E80: SAP.MARA.NTGEW | F80: NTGEW | G80: Net Weight | H80: decimal | J80: 13 | K80: 3 | P80: SAP.MAKT.SPRAS = 'E'
A81: ZB_G13_MATNR_BasicData1 | B81: Material Master Basic Data View 1 for a standard SAP ECC 6.0 system. | C81: TRUE | D81: Weight Unit | E81: SAP.MARA.GEWEI | F81: GEWEI | G81: Weight Unit | H81: varchar | I81: 3 | P81: SAP.MAKT.SPRAS = 'E'
A82: ZB_G13_MATNR_BasicData1 | B82: Material Master Basic Data View 1 for a standard SAP ECC 6.0 system. | C82: TRUE | D82: Volume | E82: SAP.MARA.VOLUM | F82: VOLUM | G82: Volume | H82: decimal | J82: 13 | K82: 3 | P82: SAP.MAKT.SPRAS = 'E'
A83: ZB_G13_MATNR_BasicData1 | B83: Material Master Basic Data View 1 for a standard SAP ECC 6.0 system. | C83: TRUE | D83: Volume Unit | E83: SAP.MARA.VOLEH | F83: VOLEH | G83: Volume unit | H83: varchar | I83: 3 | P83: SAP.MAKT.SPRAS = 'E'
A84: ZB_G13_MATNR_BasicData1 | B84: Material Master Basic Data View 1 for a standard SAP ECC 6.0 system. | C84: TRUE | D84: Size dimensions | E84: SAP.MARA.GROES | F84: GROES | G84: Size/dimensions | H84: varchar | I84: 32 | P84: SAP.MAKT.SPRAS = 'E'
A85: ZB_G13_MATNR_BasicData1 | B85: Material Master Basic Data View 1 for a standard SAP ECC 6.0 system. | C85: TRUE | D85: EAN UPC | E85: SAP.MARA.EAN11 | F85: EAN11 | G85: International Article Number (EAN/UPC) | H85: varchar | I85: 18 | P85: SAP.MAKT.SPRAS = 'E'
A86: ZB_G13_MATNR_BasicData1 | B86: Material Master Basic Data View 1 for a standard SAP ECC 6.0 system. | C86: TRUE | D86: Ean Category | E86: SAP.MARA.NUMTP | F86: NUMTP | G86: Category of International Article Number (EAN) | H86: varchar | I86: 2 | P86: SAP.MAKT.SPRAS = 'E'
A87: ZB_G13_MATNR_BasicData1 | B87: Material Master Basic Data View 1 for a standard SAP ECC 6.0 system. | C87: TRUE | D87: Matl Grp Pack Matls | E87: SAP.MARA.MAGRV | F87: MAGRV | G87: Material Group: Packaging Materials | H87: varchar | I87: 4 | P87: SAP.MAKT.SPRAS = 'E'
A88: ZB_G13_MATNR_BasicData1 | B88: Material Master Basic Data View 1 for a standard SAP ECC 6.0 system. | C88: TRUE | D88: Ref mat for pckg | E88: SAP.MARA.RMATP | F88: RMATP | G88: Reference material for materials packed in same way | H88: varchar | I88: 18 | P88: SAP.MAKT.SPRAS = 'E'
A89: ZB_G13_MATNR_BasicData1 | B89: Material Master Basic Data View 1 for a standard SAP ECC 6.0 system. | L89: SAP | M89: MAKT | P89: SAP.MAKT.SPRAS = 'E'
A90: ZB_G13_MATNR_BasicData1 | B90: Material Master Basic Data View 1 for a standard SAP ECC 6.0 system. | L90: SAP | M90: MARA | P90: SAP.MAKT.SPRAS = 'E'
A91: ZB_G13_MATNR_BasicData1 | B91: Material Master Basic Data View 1 for a standard SAP ECC 6.0 system. | N91: inner | O91: SAP.MAKT.MATNR = SAP.MARA.MATNR | P91: SAP.MAKT.SPRAS = 'E'
A92: ZB_G13_MATNR_BasicData1 | B92: Material Master Basic Data View 1 for a standard SAP ECC 6.0 system. | N92: inner | O92: SAP.MAKT.MATNR = SAP.MARA.MATNR | P92: SAP.MAKT.SPRAS = 'E'
A93: ZB_G13_MATNR_BasicData2 | B93: Material Master Basic data view 2 for a standard SAP ECC 6.0 system | C93: FALSE | D93: Material | E93: SAP.MARA.MATNR | F93: MATNR | G93: Material Number | H93: varchar | I93: 18 | P93: SAP.MAKT.SPRAS = 'E'
A94: ZB_G13_MATNR_BasicData2 | B94: Material Master Basic data view 2 for a standard SAP ECC 6.0 system | C94: TRUE | D94: Description | E94: SAP.MAKT.MAKTX | F94: MAKTX | G94: Material Description (Short Text) | H94: varchar | I94: 40 | P94: SAP.MAKT.SPRAS = 'E'
A95: ZB_G13_MATNR_BasicData2 | B95: Material Master Basic data view 2 for a standard SAP ECC 6.0 system | C95: TRUE | D95: Material Type | E95: SAP.MARA.MTART | F95: MTART | G95: Material Type | H95: varchar | I95: 4 | P95: SAP.MAKT.SPRAS = 'E'
A96: ZB_G13_MATNR_BasicData2 | B96: Material Master Basic data view 2 for a standard SAP ECC 6.0 system | C96: TRUE | D96: Prod insp Memo | E96: SAP.MARA.FERTH | F96: FERTH | G96: Production/inspection memo | H96: varchar | I96: 18 | P96: SAP.MAKT.SPRAS = 'E'
A97: ZB_G13_MATNR_BasicData2 | B97: Material Master Basic data view 2 for a standard SAP ECC 6.0 system | C97: TRUE | D97: Ind Std Desc | E97: SAP.MARA.NORMT | F97: NORMT | G97: Industry Standard Description (such as ANSI or ISO) | H97: varchar | I97: 18 | P97: SAP.MAKT.SPRAS = 'E'
A98: ZB_G13_MATNR_BasicData2 | B98: Material Master Basic data view 2 for a standard SAP ECC 6.0 system | C98: TRUE | D98: Page Format | E98: SAP.MARA.FORMT | F98: FORMT | G98: Page Format of Production Memo | H98: varchar | I98: 4 | P98: SAP.MAKT.SPRAS = 'E'
A99: ZB_G13_MATNR_BasicData2 | B99: Material Master Basic data view 2 for a standard SAP ECC 6.0 system | C99: TRUE | D99: CAD Indicator | E99: SAP.MARA.CADKZ | F99: CADKZ | G99: CAD Indicator | H99: varchar | I99: 1 | P99: SAP.MAKT.SPRAS = 'E'
A100: ZB_G13_MATNR_BasicData2 | B100: Material Master Basic data view 2 for a standard SAP ECC 6.0 system | C100: TRUE | D100: Basic Material | E100: SAP.MARA.WRKST | F100: WRKST | G100: Basic Material | H100: varchar | I100: 48 | P100: SAP.MAKT.SPRAS = 'E'
A101: ZB_G13_MATNR_BasicData2 | B101: Material Master Basic data view 2 for a standard SAP ECC 6.0 system | C101: TRUE | D101: DG Indicator Profile | E101: SAP.MARA.PROFL | F101: PROFL | G101: Dangerous Goods Indicator Profile | H101: varchar | I101: 3 | P101: SAP.MAKT.SPRAS = 'E'
...

Sheet Consolidated
A1: num | B1: source | C1: entity | D1: new_brg1 | E1: new_brg2 | F1: new_brg3 | G1: brg1_old | H1: brg2_old | I1: brg3_old | J1: brg1 | K1: brg2 | L1: brg3 | M1: inerror | N1: inactive | O1: inactive_reason | P1: objname | Q1: new_objname | R1: rule_doc | S1: dimension | T1: old_dim | U1: parameter | V1: tabname | W1: fieldname | X1: fielddesc | Y1: lookup_tabname | Z1: lookup_fieldname | AA1: ISrule | AB1: ISfilter | AC1: QUACrule | AD1: where | AE1: resultfields | AF1: viewname | AG1: tableviewcode | AH1: notes
A2: Rule # | B2: Src | C2: Entity | D2: NEW_BRG1 | E2: NEW_BRG2 | F2: NEW_BRG3 | G2: BRG1 | H2: BRG2 | I2: BRG3 | J2: BRG33 | K2: BRG32 | L2: BRG4 | M2: In error state | N2: Inactive | O2: Inactive Reason | P2: Rule Name | Q2: New Rule Name | R2: Rule Desciption | S2: Rule Dimanesion | T2: old_dimension | U2: IS Parameter | V2: Table | W2: Field | X2: Field Description | Y2: Lookup Table | Z2: Lookup Field | AA2: Rule Expression | AB2: Filter Expression | AC2: QUAC rule | AD2: Where clause | AE2: Fields to Include in Result | AF2: View Name | AG2: Table View Code | AH2: Notes | AI2: RelatedRules | AJ2: PotentialRule | AK2: Rule # by Entity | AL2: Old Rule #
A3: 1 | B3: IS_RDS | C3: Material | D3: Logistics | E3: Material Master | F3: Plant Data for Material | G3: QualityManagement | J3: =VLOOKUP(V3,Table_to_BRG!A:D,3,FALSE) -> Plant data | K3: =VLOOKUP(V3,Table_to_BRG!A:D,2,FALSE) -> Plant | P3: ZB_G13_MATL_TargetQMSystemRef | Q3: =UPPER(LEFT(Table362[[#This Row],[Entity]],3))&RIGHT("00"&Table362[[#This Row],[Rule '# by Entity]],3)&"0_"&MID(SUBSTITUTE(Table362[[#This Row],[Rule Name]],"_","|",3),SEARCH("|",SUBSTITUTE(Table362[[#This Row],[Rule Name]],"_","|",3))+1,LEN(Table362[[#This Row],[Rule Name]])) -> MAT0780_TargetQMSystemRef | R3: Verify the Target QM System value exists in the QM system definition table. | S3: Consistency | U3: $P_I_TargetQMSystem | V3: MARC | W3: QSSYS | X3: Required QM System for Vendor | Y3: TQ02 | Z3: QSSYS | AA3: ="BEGIN RETURN exists('DS_IS_RDS', '"&Table362[[#This Row],[Lookup Table]]&"', '"&Table362[[#This Row],[Lookup Field]]&"', "&Table362[[#This Row],[IS Parameter]]&"); END" -> BEGIN RETURN exists('DS_IS_RDS', 'TQ02', 'QSSYS', $P_I_TargetQMSystem); END | AB3: =Table362[[#This Row],[IS Parameter]]&" IS NOT NULL AND rtrim("&Table362[[#This Row],[IS Parameter]]&", ' ') != ''" -> $P_I_TargetQMSystem IS NOT NULL AND rtrim($P_I_TargetQMSystem, ' ') != '' | AC3: QUAC.checkValueExists('{$lookuptabname}','{$lookupfieldname}') | AE3: =IF(Table362[[#This Row],[Entity]]="Customer","KUNNR",IF(Table362[[#This Row],[Entity]]="Vendor","LIFNR","MATNR"))&",WERKS"&","&Table362[[#This Row],[Field]] -> MATNR,WERKS,QSSYS | AF3: ="VW_"&Table362[[#This Row],[New Rule Name]] -> VW_MAT0780_TargetQMSystemRef | AG3: ="create view "&Table362[[#This Row],[View Name]]&" ( "&IF(Table362[[#This Row],[Entity]]="Customer","KUNNR",IF(Table362[[#This Row],[Entity]]="Vendor","LIFNR","MATNR"))&", WERKS, "&Table362[[#This Row],[Field]]&" ) as select "&IF(Table362[[#This Row],[Entity]]="Customer","KUNNR",IF(Table362[[#This Row],[Entity]]="Vendor","LIFNR","MATNR"))&", WERKS, "&Table362[[#This Row],[Field]]&" from "&Table362[[#This Row],[Table]] -> create view VW_MAT0780_TargetQMSystemRef ( MATNR, WERKS, QSSYS ) as select MATNR, WERKS, QSSYS from MARC | AH3: ="Potential rule: Verify that each "&Table362[[#This Row],[Lookup Table]]&"-"&Table362[[#This Row],[Lookup Field]]&" exists in "&Table362[[#This Row],[Table]]&"." -> Potential rule: Verify that each TQ02-QSSYS exists in MARC. | AI3: qms | AK3: 78 | AL3: 1 | AN3: Old view name formula1: "VW_"&MID(SUBSTITUTE([@[Rule Name]],"_","|",3),SEARCH("|",SUBSTITUTE([@[Rule Name]],"_","|",3))+1,LEN([@[Rule Name]]))
A4: 2 | B4: IS_RDS | C4: Customer | D4: Logistics | E4: Customer Master | F4: General Data in Customer Master | G4: GeneralData | H4: ExportData | J4: =VLOOKUP(V4,Table_to_BRG!A:D,3,FALSE) -> General data | K4: =VLOOKUP(V4,Table_to_BRG!A:D,2,FALSE) -> General | P4: ZB_G14_CUST_NuclearNonprolifIndicatorIsValid | Q4: =UPPER(LEFT(Table362[[#This Row],[Entity]],3))&RIGHT("00"&Table362[[#This Row],[Rule '# by Entity]],3)&"0_"&MID(SUBSTITUTE(Table362[[#This Row],[Rule Name]],"_","|",3),SEARCH("|",SUBSTITUTE(Table362[[#This Row],[Rule Name]],"_","|",3))+1,LEN(Table362[[#This Row],[Rule Name]])) -> CUS0360_NuclearNonprolifIndicatorIsValid | R4: Verify the nuclear nonproliferation indicator value is valid according to the appropriate reference domain or value range. | S4: Accuracy | T4: Consistency | U4: $P_I_NuclearNonProliferation | V4: KNA1 | W4: CCC02 | X4: Indicator for nuclear nonproliferation for legal control | AA4: BEGIN RETURN $P_I_NuclearNonProliferation = 'X'; END | AB4: =Table362[[#This Row],[IS Parameter]]&" IS NOT NULL AND "& Table362[[#This Row],[IS Parameter]]&" != ''" -> $P_I_NuclearNonProliferation IS NOT NULL AND $P_I_NuclearNonProliferation != '' | AC4: QUAC.checkValueIsDomainFixedValue() | AE4: =IF(Table362[[#This Row],[Entity]]="Customer","KUNNR",IF(Table362[[#This Row],[Entity]]="Vendor","LIFNR","MATNR"))&","&Table362[[#This Row],[Field]] -> KUNNR,CCC02 | AF4: ="VW_"&Table362[[#This Row],[New Rule Name]] -> VW_CUS0360_NuclearNonprolifIndicatorIsValid | AG4: ="create view "&Table362[[#This Row],[View Name]]&" ( "&IF(Table362[[#This Row],[Entity]]="Customer","KUNNR",IF(Table362[[#This Row],[Entity]]="Vendor","LIFNR","MATNR"))&", "&Table362[[#This Row],[Field]]&" ) as select "&IF(Table362[[#This Row],[Entity]]="Customer","KUNNR",IF(Table362[[#This Row],[Entity]]="Vendor","LIFNR","MATNR"))&", "&Table362[[#This Row],[Field]]&" from "&Table362[[#This Row],[Table]] -> create view VW_CUS0360_NuclearNonprolifIndicatorIsValid ( KUNNR, CCC02 ) as select KUNNR, CCC02 from KNA1 | AI4: expctrl | AK4: 36 | AN4: Old view name formula2: =RIGHT("00"&[@[Rule '#]],3)&"_"&IF([@Entity]="Material","MATL",LEFT(UPPER([@Entity]),4))&"_"&MID(SUBSTITUTE([@[Rule Name]],"_","|",3),SEARCH("|",SUBSTITUTE([@[Rule Name]],"_","|",3))+1,LEN([@[Rule Name]]))
A5: 2 | B5: IS_RDS | C5: Material | D5: Logistics | E5: Material Master | F5: Plant Data for Material | G5: GeneralData | J5: =VLOOKUP(V5,Table_to_BRG!A:D,3,FALSE) -> Plant data | K5: =VLOOKUP(V5,Table_to_BRG!A:D,2,FALSE) -> Plant | P5: ZB_G13_MATL_FairShareRuleIsValid | Q5: =UPPER(LEFT(Table362[[#This Row],[Entity]],3))&RIGHT("00"&Table362[[#This Row],[Rule '# by Entity]],3)&"0_"&MID(SUBSTITUTE(Table362[[#This Row],[Rule Name]],"_","|",3),SEARCH("|",SUBSTITUTE(Table362[[#This Row],[Rule Name]],"_","|",3))+1,LEN(Table362[[#This Row],[Rule Name]])) -> MAT0920_FairShareRuleIsValid | R5: Verify the fair share rule value is valid according to the appropriate reference domain or value range. | S5: Accuracy | T5: Consistency | U5: $P_I_FairShare_Rule | V5: MARC | W5: DPLFS | X5: Fair share rule | AA5: BEGIN RETURN $P_I_FairShare_Rule IN ('A', 'B', 'X'); END | AB5: =Table362[[#This Row],[IS Parameter]]&" IS NOT NULL AND rtrim("&Table362[[#This Row],[IS Parameter]]&", ' ') != ''" -> $P_I_FairShare_Rule IS NOT NULL AND rtrim($P_I_FairShare_Rule, ' ') != '' | AC5: QUAC.checkValueIsDomainFixedValue() | AE5: =IF(Table362[[#This Row],[Entity]]="Customer","KUNNR",IF(Table362[[#This Row],[Entity]]="Vendor","LIFNR","MATNR"))&",WERKS"&","&Table362[[#This Row],[Field]] -> MATNR,WERKS,DPLFS | AF5: ="VW_"&Table362[[#This Row],[New Rule Name]] -> VW_MAT0920_FairShareRuleIsValid | AG5: ="create view "&Table362[[#This Row],[View Name]]&" ( "&IF(Table362[[#This Row],[Entity]]="Customer","KUNNR",IF(Table362[[#This Row],[Entity]]="Vendor","LIFNR","MATNR"))&", WERKS, "&Table362[[#This Row],[Field]]&" ) as select "&IF(Table362[[#This Row],[Entity]]="Customer","KUNNR",IF(Table362[[#This Row],[Entity]]="Vendor","LIFNR","MATNR"))&", WERKS, "&Table362[[#This Row],[Field]]&" from "&Table362[[#This Row],[Table]] -> create view VW_MAT0920_FairShareRuleIsValid ( MATNR, WERKS, DPLFS ) as select MATNR, WERKS, DPLFS from MARC | AK5: 92
A6: 3 | B6: IS_RDS | C6: Material | D6: Logistics | E6: Material Master | F6: Plant Data for Material | G6: Costing1 | J6: =VLOOKUP(V6,Table_to_BRG!A:D,3,FALSE) -> Plant data | K6: =VLOOKUP(V6,Table_to_BRG!A:D,2,FALSE) -> Plant | P6: ZB_G13_MATL_TaskListTypeRef | Q6: =UPPER(LEFT(Table362[[#This Row],[Entity]],3))&RIGHT("00"&Table362[[#This Row],[Rule '# by Entity]],3)&"0_"&MID(SUBSTITUTE(Table362[[#This Row],[Rule Name]],"_","|",3),SEARCH("|",SUBSTITUTE(Table362[[#This Row],[Rule Name]],"_","|",3))+1,LEN(Table362[[#This Row],[Rule Name]])) -> MAT0820_TaskListTypeRef | R6: Verify the task list type value exists in the Task List Types table. | S6: Consistency | U6: $P_I_TaskListType | V6: MARC | W6: PLNTY | X6: Task List Type | Y6: TCA01 | Z6: PLNTY | AA6: ="BEGIN RETURN exists('DS_IS_RDS', '"&Table362[[#This Row],[Lookup Table]]&"', '"&Table362[[#This Row],[Lookup Field]]&"', "&Table362[[#This Row],[IS Parameter]]&"); END" -> BEGIN RETURN exists('DS_IS_RDS', 'TCA01', 'PLNTY', $P_I_TaskListType); END | AB6: =Table362[[#This Row],[IS Parameter]]&" IS NOT NULL AND rtrim("&Table362[[#This Row],[IS Parameter]]&", ' ') != ''" -> $P_I_TaskListType IS NOT NULL AND rtrim($P_I_TaskListType, ' ') != '' | AC6: QUAC.checkValueExists('{$lookuptabname}','{$lookupfieldname}') | AE6: =IF(Table362[[#This Row],[Entity]]="Customer","KUNNR",IF(Table362[[#This Row],[Entity]]="Vendor","LIFNR","MATNR"))&",WERKS"&","&Table362[[#This Row],[Field]] -> MATNR,WERKS,PLNTY | AF6: ="VW_"&Table362[[#This Row],[New Rule Name]] -> VW_MAT0820_TaskListTypeRef | AG6: ="create view "&Table362[[#This Row],[View Name]]&" ( "&IF(Table362[[#This Row],[Entity]]="Customer","KUNNR",IF(Table362[[#This Row],[Entity]]="Vendor","LIFNR","MATNR"))&", WERKS, "&Table362[[#This Row],[Field]]&" ) as select "&IF(Table362[[#This Row],[Entity]]="Customer","KUNNR",IF(Table362[[#This Row],[Entity]]="Vendor","LIFNR","MATNR"))&", WERKS, "&Table362[[#This Row],[Field]]&" from "&Table362[[#This Row],[Table]] -> create view VW_MAT0820_TaskListTypeRef ( MATNR, WERKS, PLNTY ) as select MATNR, WERKS, PLNTY from MARC | AH6: ="Potential rule: Verify that each "&Table362[[#This Row],[Lookup Table]]&"-"&Table362[[#This Row],[Lookup Field]]&" exists in "&Table362[[#This Row],[Table]]&"." -> Potential rule: Verify that each TCA01-PLNTY exists in MARC. | AI6: tasklist | AK6: 82
A7: 4 | B7: IS_RDS | C7: Customer | D7: Logistics | E7: Customer Master | F7: General Data in Customer Master | G7: GeneralData | H7: Control | J7: =VLOOKUP(V7,Table_to_BRG!A:D,3,FALSE) -> General data | K7: =VLOOKUP(V7,Table_to_BRG!A:D,2,FALSE) -> General | P7: ZB_G14_CUST_TradingPartnerRef | Q7: =UPPER(LEFT(Table362[[#This Row],[Entity]],3))&RIGHT("00"&Table362[[#This Row],[Rule '# by Entity]],3)&"0_"&MID(SUBSTITUTE(Table362[[#This Row],[Rule Name]],"_","|",3),SEARCH("|",SUBSTITUTE(Table362[[#This Row],[Rule Name]],"_","|",3))+1,LEN(Table362[[#This Row],[Rule Name]])) -> CUS0250_TradingPartnerRef | R7: Verify the customer trading partner value exists in the Global Company Data (for KONS Ledger) table. | S7: Completeness | T7: Consistency | U7: $P_I_TradingPartner | V7: KNA1 | W7: VBUND | X7: Company ID of trading partner | Y7: T880 | Z7: RCOMP | AA7: ="BEGIN RETURN exists('DS_IS_RDS', '"&Table362[[#This Row],[Lookup Table]]&"', '"&Table362[[#This Row],[Lookup Field]]&"', "&Table362[[#This Row],[IS Parameter]]&"); END" -> BEGIN RETURN exists('DS_IS_RDS', 'T880', 'RCOMP', $P_I_TradingPartner); END | AB7: =Table362[[#This Row],[IS Parameter]]&" IS NOT NULL AND "& Table362[[#This Row],[IS Parameter]]&" != ''" -> $P_I_TradingPartner IS NOT NULL AND $P_I_TradingPartner != '' | AC7: QUAC.checkValueExists('{$lookuptabname}','{$lookupfieldname}') | AE7: =IF(Table362[[#This Row],[Entity]]="Customer","KUNNR",IF(Table362[[#This Row],[Entity]]="Vendor","LIFNR","MATNR"))&","&Table362[[#This Row],[Field]] -> KUNNR,VBUND | AF7: ="VW_"&Table362[[#This Row],[New Rule Name]] -> VW_CUS0250_TradingPartnerRef | AG7: ="create view "&Table362[[#This Row],[View Name]]&" ( "&IF(Table362[[#This Row],[Entity]]="Customer","KUNNR",IF(Table362[[#This Row],[Entity]]="Vendor","LIFNR","MATNR"))&", "&Table362[[#This Row],[Field]]&" ) as select "&IF(Table362[[#This Row],[Entity]]="Customer","KUNNR",IF(Table362[[#This Row],[Entity]]="Vendor","LIFNR","MATNR"))&", "&Table362[[#This Row],[Field]]&" from "&Table362[[#This Row],[Table]] -> create view VW_CUS0250_TradingPartnerRef ( KUNNR, VBUND ) as select KUNNR, VBUND from KNA1 | AH7: ="Potential rule: Verify that each "&Table362[[#This Row],[Lookup Table]]&"-"&Table362[[#This Row],[Lookup Field]]&" exists in "&Table362[[#This Row],[Table]]&"." -> Potential rule: Verify that each T880-RCOMP exists in KNA1. | AI7: tradpart4c | AK7: 25
A8: 6 | B8: IS_RDS | C8: Vendor | D8: SalesAndDistribution | E8: Billing | F8: Customer Master Licenses | G8: Master Licenses | I8: License | J8: =VLOOKUP(V8,Table_to_BRG!A:D,3,FALSE) -> #N/A | K8: =VLOOKUP(V8,Table_to_BRG!A:D,2,FALSE) -> #N/A | N8: x | O8: Vendor master data license table not found | P8: ZB_G15_VNDR_LicensevalidToDatePopulated | R8: Rule to check if the License valid to date for Business Partner / Customer / Vendor exists | S8: Completeness | U8: $P_I_LicenseValidToDate | W8: DATBI | X8: Valid To Date | AA8: BEGIN RETURN $P_I_LicenseValidToDate IS NOT NULL AND $P_I_LicenseValidToDate != to_date('', 'yyyy.mm.dd'); END | AC8: QUAC.checkValueIsNotEmpty() | AH8: There does not appear to be a vendor master license table in ECC, but CRM has a table OIHL with fields for both customer and vendor numbers. | AI8: license03v
A9: 5 | B9: IS_RDS | C9: Customer | D9: Logistics | E9: Customer Master | F9: General Data in Customer Master | G9: GeneralData | H9: SalesInformation | J9: =VLOOKUP(V9,Table_to_BRG!A:D,3,FALSE) -> General data | K9: =VLOOKUP(V9,Table_to_BRG!A:D,2,FALSE) -> General | P9: ZB_G14_CUST_SalesCurrencyPopulated | Q9: =UPPER(LEFT(Table362[[#This Row],[Entity]],3))&RIGHT("00"&Table362[[#This Row],[Rule '# by Entity]],3)&"0_"&MID(SUBSTITUTE(Table362[[#This Row],[Rule Name]],"_","|",3),SEARCH("|",SUBSTITUTE(Table362[[#This Row],[Rule Name]],"_","|",3))+1,LEN(Table362[[#This Row],[Rule Name]])) -> CUS0290_SalesCurrencyPopulated | R9: Verify the customer sales currency field is not empty. | S9: Completeness | U9: $P_I_Currency | V9: KNA1 | W9: UWAER | X9: Currency of sales figure | AA9: BEGIN RETURN $P_I_Currency IS NOT NULL AND $P_I_Currency != ''; END | AC9: QUAC.checkValueIsNotEmpty() | AE9: =IF(Table362[[#This Row],[Entity]]="Customer","KUNNR",IF(Table362[[#This Row],[Entity]]="Vendor","LIFNR","MATNR"))&","&Table362[[#This Row],[Field]] -> KUNNR,UWAER | AF9: ="VW_"&Table362[[#This Row],[New Rule Name]] -> VW_CUS0290_SalesCurrencyPopulated | AG9: ="create view "&Table362[[#This Row],[View Name]]&" ( "&IF(Table362[[#This Row],[Entity]]="Customer","KUNNR",IF(Table362[[#This Row],[Entity]]="Vendor","LIFNR","MATNR"))&", "&Table362[[#This Row],[Field]]&" ) as select "&IF(Table362[[#This Row],[Entity]]="Customer","KUNNR",IF(Table362[[#This Row],[Entity]]="Vendor","LIFNR","MATNR"))&", "&Table362[[#This Row],[Field]]&" from "&Table362[[#This Row],[Table]] -> create view VW_CUS0290_SalesCurrencyPopulated ( KUNNR, UWAER ) as select KUNNR, UWAER from KNA1 | AI9: salescurr | AK9: 29
A10: 7 | B10: IS_RDS | C10: Material | D10: Logistics | E10: Material Master | F10: Plant Data for Material | G10: SalesGeneral | H10: PlantData | J10: =VLOOKUP(V10,Table_to_BRG!A:D,3,FALSE) -> Plant data | K10: =VLOOKUP(V10,Table_to_BRG!A:D,2,FALSE) -> Plant | P10: ZB_G13_MATL_AvailabilityCheckPopulated | Q10: =UPPER(LEFT(Table362[[#This Row],[Entity]],3))&RIGHT("00"&Table362[[#This Row],[Rule '# by Entity]],3)&"0_"&MID(SUBSTITUTE(Table362[[#This Row],[Rule Name]],"_","|",3),SEARCH("|",SUBSTITUTE(Table362[[#This Row],[Rule Name]],"_","|",3))+1,LEN(Table362[[#This Row],[Rule Name]])) -> MAT0600_AvailabilityCheckPopulated | R10: Verify the availability check field is not empty. | S10: Completeness | U10: $P_I_AvailabilityCheck | V10: MARC | W10: MTVFP | X10: Checking group for availability check | AA10: BEGIN RETURN $P_I_AvailabilityCheck IS NOT NULL AND $P_I_AvailabilityCheck != ''; END | AC10: QUAC.checkValueIsNotEmpty() | AE10: =IF(Table362[[#This Row],[Entity]]="Customer","KUNNR",IF(Table362[[#This Row],[Entity]]="Vendor","LIFNR","MATNR"))&",WERKS"&","&Table362[[#This Row],[Field]] -> MATNR,WERKS,MTVFP | AF10: ="VW_"&Table362[[#This Row],[New Rule Name]] -> VW_MAT0600_AvailabilityCheckPopulated | AG10: ="create view "&Table362[[#This Row],[View Name]]&" ( "&IF(Table362[[#This Row],[Entity]]="Customer","KUNNR",IF(Table362[[#This Row],[Entity]]="Vendor","LIFNR","MATNR"))&", WERKS, "&Table362[[#This Row],[Field]]&" ) as select "&IF(Table362[[#This Row],[Entity]]="Customer","KUNNR",IF(Table362[[#This Row],[Entity]]="Vendor","LIFNR","MATNR"))&", WERKS, "&Table362[[#This Row],[Field]]&" from "&Table362[[#This Row],[Table]] -> create view VW_MAT0600_AvailabilityCheckPopulated ( MATNR, WERKS, MTVFP ) as select MATNR, WERKS, MTVFP from MARC | AI10: availcheck | AK10: 60 | AL10: 3
A11: 9 | B11: IS_RDS | C11: Vendor | J11: =VLOOKUP(V11,Table_to_BRG!A:D,3,FALSE) -> Customer sales data | K11: =VLOOKUP(V11,Table_to_BRG!A:D,2,FALSE) -> Sales | N11: x | O11: Vendor master data statistics group table not found | P11: ZB_G15_VNDR_StatisticeGroupRef | R11: Verify the vendor Statistics Group exists. | S11: Consistency | U11: $P_I_StatisticsGroup | V11: KNVV | W11: VERSG | X11: Customer Statistics Group | Y11: TVSD | Z11: STGKU | AA11: ="BEGIN RETURN exists('DS_IS_RDS', '"&Table362[[#This Row],[Lookup Table]]&"', '"&Table362[[#This Row],[Lookup Field]]&"', "&Table362[[#This Row],[IS Parameter]]&"); END" -> BEGIN RETURN exists('DS_IS_RDS', 'TVSD', 'STGKU', $P_I_StatisticsGroup); END | AC11: QUAC.checkValueExists('{$lookuptabname}','{$lookupfieldname}') | AE11: =IF(Table362[[#This Row],[Entity]]="Customer","KUNNR",IF(Table362[[#This Row],[Entity]]="Vendor","LIFNR","MATNR"))&","&Table362[[#This Row],[Field]] -> LIFNR,VERSG | AG11: ="create view "&Table362[[#This Row],[View Name]]&" as select "&IF(Table362[[#This Row],[Entity]]="Customer","KUNNR",IF(Table362[[#This Row],[Entity]]="Vendor","LIFNR","MATNR"))&", "&Table362[[#This Row],[Field]]&" from "&Table362[[#This Row],[Table]] -> create view as select LIFNR, VERSG from KNVV | AI11: statgrp9v
A12: 10 | B12: IS_RDS | C12: Vendor | D12: Finance | E12: Financial Accounting | F12: Vendor Master (General Section) | G12: GeneralData | H12: Control | I12: Tax | J12: =VLOOKUP(V12,Table_to_BRG!A:D,3,FALSE) -> General data | K12: =VLOOKUP(V12,Table_to_BRG!A:D,2,FALSE) -> General | N12: x | O12: LFA1-STCD1 does not have a lookup table reference | P12: See Note ZB_G15_VNDR_TaxNumberRef | R12: Verify the tax Number value exists in the | S12: Consistency | U12: $P_I_TaxNumber | V12: LFA1 | W12: STCD1 | X12: Tax Number 1 | Y12: M_KREDA | Z12: LIFNR | AA12: ="BEGIN RETURN exists('DS_IS_RDS', '"&Table362[[#This Row],[Lookup Table]]&"', '"&Table362[[#This Row],[Lookup Field]]&"', "&Table362[[#This Row],[IS Parameter]]&"); END" -> BEGIN RETURN exists('DS_IS_RDS', 'M_KREDA', 'LIFNR', $P_I_TaxNumber); END | AC12: QUAC.checkValueExists('{$lookuptabname}','{$lookupfieldname}') | AI12: taxnumber
A13: 8 | B13: IS_RDS | C13: Customer | D13: Finance | E13: Financial Accounting | F13: Customer Master (Company Code) | G13: CompanyCodeData | H13: CompanyCode | J13: =VLOOKUP(V13,Table_to_BRG!A:D,3,FALSE) -> Company Code data | K13: =VLOOKUP(V13,Table_to_BRG!A:D,2,FALSE) -> Company Code | P13: ZB_G14_CUST_CompanyCodePopulated | Q13: =UPPER(LEFT(Table362[[#This Row],[Entity]],3))&RIGHT("00"&Table362[[#This Row],[Rule '# by Entity]],3)&"0_"&MID(SUBSTITUTE(Table362[[#This Row],[Rule Name]],"_","|",3),SEARCH("|",SUBSTITUTE(Table362[[#This Row],[Rule Name]],"_","|",3))+1,LEN(Table362[[#This Row],[Rule Name]])) -> CUS0390_CompanyCodePopulated | R13: Verify the company code field is not empty. | S13: Completeness | U13: $P_I_CompanyCode | V13: KNB1 | W13: BUKRS | X13: Company Code | AA13: BEGIN RETURN $P_I_CompanyCode IS NOT NULL AND $P_I_CompanyCode != ''; END | AC13: QUAC.checkValueIsNotEmpty() | AE13: =IF(Table362[[#This Row],[Entity]]="Customer","KUNNR",IF(Table362[[#This Row],[Entity]]="Vendor","LIFNR","MATNR"))&","&Table362[[#This Row],[Field]] -> KUNNR,BUKRS | AF13: ="VW_"&Table362[[#This Row],[New Rule Name]] -> VW_CUS0390_CompanyCodePopulated | AG13: ="create view "&Table362[[#This Row],[View Name]]&" ( "&IF(Table362[[#This Row],[Entity]]="Customer","KUNNR",IF(Table362[[#This Row],[Entity]]="Vendor","LIFNR","MATNR"))&", "&Table362[[#This Row],[Field]]&" ) as select "&IF(Table362[[#This Row],[Entity]]="Customer","KUNNR",IF(Table362[[#This Row],[Entity]]="Vendor","LIFNR","MATNR"))&", "&Table362[[#This Row],[Field]]&" from "&Table362[[#This Row],[Table]] -> create view VW_CUS0390_CompanyCodePopulated ( KUNNR, BUKRS ) as select KUNNR, BUKRS from KNB1 | AI13: compcode8c | AK13: 39
A14: 11 | B14: IS_RDS | C14: Material | D14: Logistics | E14: Material Master | F14: Plant Data for Material | G14: MatlReqPlanning | H14: MRP1 | J14: =VLOOKUP(V14,Table_to_BRG!A:D,3,FALSE) -> Plant data | K14: =VLOOKUP(V14,Table_to_BRG!A:D,2,FALSE) -> Plant | P14: ZB_G13_MATL_MRPTypeRef | Q14: =UPPER(LEFT(Table362[[#This Row],[Entity]],3))&RIGHT("00"&Table362[[#This Row],[Rule '# by Entity]],3)&"0_"&MID(SUBSTITUTE(Table362[[#This Row],[Rule Name]],"_","|",3),SEARCH("|",SUBSTITUTE(Table362[[#This Row],[Rule Name]],"_","|",3))+1,LEN(Table362[[#This Row],[Rule Name]])) -> MAT0410_MRPTypeRef | R14: Verify the MRP Type value exists in the MRP Type table. | S14: Consistency | U14: $P_I_MRPType | V14: MARC | W14: DISMM | X14: MRP Type | Y14: T438A | Z14: DISMM | AA14: ="BEGIN RETURN exists('DS_IS_RDS', '"&Table362[[#This Row],[Lookup Table]]&"', '"&Table362[[#This Row],[Lookup Field]]&"', "&Table362[[#This Row],[IS Parameter]]&"); END" -> BEGIN RETURN exists('DS_IS_RDS', 'T438A', 'DISMM', $P_I_MRPType); END | AB14: =Table362[[#This Row],[IS Parameter]]&" IS NOT NULL AND rtrim("&Table362[[#This Row],[IS Parameter]]&", ' ') != ''" -> $P_I_MRPType IS NOT NULL AND rtrim($P_I_MRPType, ' ') != '' | AC14: QUAC.checkValueExists('{$lookuptabname}','{$lookupfieldname}') | AE14: =IF(Table362[[#This Row],[Entity]]="Customer","KUNNR",IF(Table362[[#This Row],[Entity]]="Vendor","LIFNR","MATNR"))&",WERKS"&","&Table362[[#This Row],[Field]] -> MATNR,WERKS,DISMM | AF14: ="VW_"&Table362[[#This Row],[New Rule Name]] -> VW_MAT0410_MRPTypeRef | AG14: ="create view "&Table362[[#This Row],[View Name]]&" ( "&IF(Table362[[#This Row],[Entity]]="Customer","KUNNR",IF(Table362[[#This Row],[Entity]]="Vendor","LIFNR","MATNR"))&", WERKS, "&Table362[[#This Row],[Field]]&" ) as select "&IF(Table362[[#This Row],[Entity]]="Customer","KUNNR",IF(Table362[[#This Row],[Entity]]="Vendor","LIFNR","MATNR"))&", WERKS, "&Table362[[#This Row],[Field]]&" from "&Table362[[#This Row],[Table]] -> create view VW_MAT0410_MRPTypeRef ( MATNR, WERKS, DISMM ) as select MATNR, WERKS, DISMM from MARC | AI14: mrpttype | AK14: 41
A15: 12 | B15: IS_RDS | C15: Customer | D15: SalesAndDistribution | E15: Billing | F15: Customer Master Tax Indicator | G15: SalesAreaData | H15: BillingDocuments | I15: Tax | J15: =VLOOKUP(V15,Table_to_BRG!A:D,3,FALSE) -> Tax data | K15: =VLOOKUP(V15,Table_to_BRG!A:D,2,FALSE) -> Tax indicator | P15: ZB_G14_CUST_TaxClassificationPopulated | Q15: =UPPER(LEFT(Table362[[#This Row],[Entity]],3))&RIGHT("00"&Table362[[#This Row],[Rule '# by Entity]],3)&"0_"&MID(SUBSTITUTE(Table362[[#This Row],[Rule Name]],"_","|",3),SEARCH("|",SUBSTITUTE(Table362[[#This Row],[Rule Name]],"_","|",3))+1,LEN(Table362[[#This Row],[Rule Name]])) -> CUS0740_TaxClassificationPopulated | R15: Verify the tax classification field is not empty. | S15: Completeness | U15: $P_I_TaxClassification | V15: KNVI | W15: TAXKD | X15: Tax classification for customer | AA15: BEGIN RETURN $P_I_TaxClassification IS NOT NULL AND $P_I_TaxClassification != ''; END | AC15: QUAC.checkValueIsNotEmpty() | AE15: =IF(Table362[[#This Row],[Entity]]="Customer","KUNNR",IF(Table362[[#This Row],[Entity]]="Vendor","LIFNR","MATNR"))&",ALAND,TATYP"&","&Table362[[#This Row],[Field]] -> KUNNR,ALAND,TATYP,TAXKD | AF15: ="VW_"&Table362[[#This Row],[New Rule Name]] -> VW_CUS0740_TaxClassificationPopulated | AG15: ="create view "&Table362[[#This Row],[View Name]]&" ( "&IF(Table362[[#This Row],[Entity]]="Customer","KUNNR",IF(Table362[[#This Row],[Entity]]="Vendor","LIFNR","MATNR"))&", ALAND, TATYP, "&Table362[[#This Row],[Field]]&" ) as select "&IF(Table362[[#This Row],[Entity]]="Customer","KUNNR",IF(Table362[[#This Row],[Entity]]="Vendor","LIFNR","MATNR"))&", ALAND, TATYP, "&Table362[[#This Row],[Field]]&" from "&Table362[[#This Row],[Table]] -> create view VW_CUS0740_TaxClassificationPopulated ( KUNNR, ALAND, TATYP, TAXKD ) as select KUNNR, ALAND, TATYP, TAXKD from KNVI | AI15: taxclass12c | AK15: 74
A16: 13 | B16: IS_RDS | C16: Customer | D16: Logistics | E16: Customer Master | F16: Customer Master Sales Data | G16: SalesAreaData | H16: Sales | J16: =VLOOKUP(V16,Table_to_BRG!A:D,3,FALSE) -> Customer sales data | K16: =VLOOKUP(V16,Table_to_BRG!A:D,2,FALSE) -> Sales | P16: ZB_G14_CUST_DivisionPopulated | Q16: =UPPER(LEFT(Table362[[#This Row],[Entity]],3))&RIGHT("00"&Table362[[#This Row],[Rule '# by Entity]],3)&"0_"&MID(SUBSTITUTE(Table362[[#This Row],[Rule Name]],"_","|",3),SEARCH("|",SUBSTITUTE(Table362[[#This Row],[Rule Name]],"_","|",3))+1,LEN(Table362[[#This Row],[Rule Name]])) -> CUS0910_DivisionPopulated | R16: Verify the division field is not empty. | S16: Completeness | U16: $P_I_Division | V16: KNVV | W16: SPART | X16: Division | AA16: BEGIN RETURN $P_I_Division IS NOT NULL AND $P_I_Division != ''; END | AC16: QUAC.checkValueIsNotEmpty() | AE16: KUNNR,VKORG,VTWEG,SPART | AF16: ="VW_"&Table362[[#This Row],[New Rule Name]] -> VW_CUS0910_DivisionPopulated | AG16: ="create view "&Table362[[#This Row],[View Name]]&" ( "&IF(Table362[[#This Row],[Entity]]="Customer","KUNNR",IF(Table362[[#This Row],[Entity]]="Vendor","LIFNR","MATNR"))&", VKORG, VTWEG, "&Table362[[#This Row],[Field]]&" ) as select "&IF(Table362[[#This Row],[Entity]]="Customer","KUNNR",IF(Table362[[#This Row],[Entity]]="Vendor","LIFNR","MATNR"))&", VKORG, VTWEG, "&Table362[[#This Row],[Field]]&" from "&Table362[[#This Row],[Table]] -> create view VW_CUS0910_DivisionPopulated ( KUNNR, VKORG, VTWEG, SPART ) as select KUNNR, VKORG, VTWEG, SPART from KNVV | AI16: division | AK16: 91
A17: 14 | B17: IS_RDS | C17: Material | D17: Logistics | E17: Material Master | F17: General Material Data | G17: SalesGeneral | H17: PlantData | J17: =VLOOKUP(V17,Table_to_BRG!A:D,3,FALSE) -> General data | K17: =VLOOKUP(V17,Table_to_BRG!A:D,2,FALSE) -> General | P17: ZB_G13_MATL_TransportationGroupPopulated | Q17: =UPPER(LEFT(Table362[[#This Row],[Entity]],3))&RIGHT("00"&Table362[[#This Row],[Rule '# by Entity]],3)&"0_"&MID(SUBSTITUTE(Table362[[#This Row],[Rule Name]],"_","|",3),SEARCH("|",SUBSTITUTE(Table362[[#This Row],[Rule Name]],"_","|",3))+1,LEN(Table362[[#This Row],[Rule Name]])) -> MAT0160_TransportationGroupPopulated | R17: Verify the transportation group field Is not empty. | S17: Completeness | U17: $P_I_TransportationGroup | V17: MARA | W17: TRAGR | X17: Transportation group | AA17: BEGIN RETURN $P_I_TransportationGroup IS NOT NULL AND $P_I_TransportationGroup != ''; END | AC17: QUAC.checkValueIsNotEmpty() | AE17: =IF(Table362[[#This Row],[Entity]]="Customer","KUNNR",IF(Table362[[#This Row],[Entity]]="Vendor","LIFNR","MATNR"))&","&Table362[[#This Row],[Field]] -> MATNR,TRAGR | AF17: ="VW_"&Table362[[#This Row],[New Rule Name]] -> VW_MAT0160_TransportationGroupPopulated | AG17: ="create view "&Table362[[#This Row],[View Name]]&" ( "&IF(Table362[[#This Row],[Entity]]="Customer","KUNNR",IF(Table362[[#This Row],[Entity]]="Vendor","LIFNR","MATNR"))&", "&Table362[[#This Row],[Field]]&" ) as select "&IF(Table362[[#This Row],[Entity]]="Customer","KUNNR",IF(Table362[[#This Row],[Entity]]="Vendor","LIFNR","MATNR"))&", "&Table362[[#This Row],[Field]]&" from "&Table362[[#This Row],[Table]] -> create view VW_MAT0160_TransportationGroupPopulated ( MATNR, TRAGR ) as select MATNR, TRAGR from MARA | AI17: transgrp | AK17: 16
A18: 15 | B18: IS_RDS | C18: Material | D18: Logistics | E18: Material Master | F18: Plant Data for Material | G18: MatlReqPlanning | H18: MRP2 | J18: =VLOOKUP(V18,Table_to_BRG!A:D,3,FALSE) -> Plant data | K18: =VLOOKUP(V18,Table_to_BRG!A:D,2,FALSE) -> Plant | P18: ZB_G13_MATL_SchedulingMarginKeyRef | Q18: =UPPER(LEFT(Table362[[#This Row],[Entity]],3))&RIGHT("00"&Table362[[#This Row],[Rule '# by Entity]],3)&"0_"&MID(SUBSTITUTE(Table362[[#This Row],[Rule Name]],"_","|",3),SEARCH("|",SUBSTITUTE(Table362[[#This Row],[Rule Name]],"_","|",3))+1,LEN(Table362[[#This Row],[Rule Name]])) -> MAT0540_SchedulingMarginKeyRef | R18: Verify the scheduling margin key value exists in the Floats for Scheduling table. | S18: Consistency | U18: $P_I_SchedulingMarginKey | V18: MARC | W18: FHORI | X18: Scheduling Margin Key for Floats | Y18: T436A | Z18: FHORI | AA18: ="BEGIN RETURN exists('DS_IS_RDS', '"&Table362[[#This Row],[Lookup Table]]&"', '"&Table362[[#This Row],[Lookup Field]]&"', "&Table362[[#This Row],[IS Parameter]]&"); END" -> BEGIN RETURN exists('DS_IS_RDS', 'T436A', 'FHORI', $P_I_SchedulingMarginKey); END | AB18: =Table362[[#This Row],[IS Parameter]]&" IS NOT NULL AND rtrim("&Table362[[#This Row],[IS Parameter]]&", ' ') != ''" -> $P_I_SchedulingMarginKey IS NOT NULL AND rtrim($P_I_SchedulingMarginKey, ' ') != '' | AC18: QUAC.checkValueExists('{$lookuptabname}','{$lookupfieldname}') | AE18: =IF(Table362[[#This Row],[Entity]]="Customer","KUNNR",IF(Table362[[#This Row],[Entity]]="Vendor","LIFNR","MATNR"))&",WERKS"&","&Table362[[#This Row],[Field]] -> MATNR,WERKS,FHORI | AF18: ="VW_"&Table362[[#This Row],[New Rule Name]] -> VW_MAT0540_SchedulingMarginKeyRef | AG18: ="create view "&Table362[[#This Row],[View Name]]&" ( "&IF(Table362[[#This Row],[Entity]]="Customer","KUNNR",IF(Table362[[#This Row],[Entity]]="Vendor","LIFNR","MATNR"))&", WERKS, "&Table362[[#This Row],[Field]]&" ) as select "&IF(Table362[[#This Row],[Entity]]="Customer","KUNNR",IF(Table362[[#This Row],[Entity]]="Vendor","LIFNR","MATNR"))&", WERKS, "&Table362[[#This Row],[Field]]&" from "&Table362[[#This Row],[Table]] -> create view VW_MAT0540_SchedulingMarginKeyRef ( MATNR, WERKS, FHORI ) as select MATNR, WERKS, FHORI from MARC | AI18: scheduling | AK18: 54
A19: 16 | B19: IS_RDS | C19: Material | D19: Logistics | E19: Material Master | F19: Plant Data for Material | G19: SalesGeneral | H19: PlantData | J19: =VLOOKUP(V19,Table_to_BRG!A:D,3,FALSE) -> Plant data | K19: =VLOOKUP(V19,Table_to_BRG!A:D,2,FALSE) -> Plant | P19: ZB_G13_MATL_LoadingGroupPopulated | Q19: =UPPER(LEFT(Table362[[#This Row],[Entity]],3))&RIGHT("00"&Table362[[#This Row],[Rule '# by Entity]],3)&"0_"&MID(SUBSTITUTE(Table362[[#This Row],[Rule Name]],"_","|",3),SEARCH("|",SUBSTITUTE(Table362[[#This Row],[Rule Name]],"_","|",3))+1,LEN(Table362[[#This Row],[Rule Name]])) -> MAT0570_LoadingGroupPopulated | R19: Verify the loading group field is not empty. | S19: Completeness | U19: $P_I_LoadingGroup | V19: MARC | W19: LADGR | X19: Loading group | AA19: BEGIN RETURN $P_I_LoadingGroup IS NOT NULL AND $P_I_LoadingGroup != ''; END | AC19: QUAC.checkValueIsNotEmpty() | AE19: =IF(Table362[[#This Row],[Entity]]="Customer","KUNNR",IF(Table362[[#This Row],[Entity]]="Vendor","LIFNR","MATNR"))&",WERKS"&","&Table362[[#This Row],[Field]] -> MATNR,WERKS,LADGR | AF19: ="VW_"&Table362[[#This Row],[New Rule Name]] -> VW_MAT0570_LoadingGroupPopulated | AG19: ="create view "&Table362[[#This Row],[View Name]]&" ( "&IF(Table362[[#This Row],[Entity]]="Customer","KUNNR",IF(Table362[[#This Row],[Entity]]="Vendor","LIFNR","MATNR"))&", WERKS, "&Table362[[#This Row],[Field]]&" ) as select "&IF(Table362[[#This Row],[Entity]]="Customer","KUNNR",IF(Table362[[#This Row],[Entity]]="Vendor","LIFNR","MATNR"))&", WERKS, "&Table362[[#This Row],[Field]]&" from "&Table362[[#This Row],[Table]] -> create view VW_MAT0570_LoadingGroupPopulated ( MATNR, WERKS, LADGR ) as select MATNR, WERKS, LADGR from MARC | AI19: loadgrp | AK19: 57
A20: 17 | B20: IS_RDS | C20: Customer | D20: Logistics | E20: Customer Master | F20: General Data in Customer Master | G20: GeneralData | H20: ExportData | J20: =VLOOKUP(V20,Table_to_BRG!A:D,3,FALSE) -> General data | K20: =VLOOKUP(V20,Table_to_BRG!A:D,2,FALSE) -> General | P20: ZB_G14_CUST_NationalSecurityIndicatorIsValid | Q20: =UPPER(LEFT(Table362[[#This Row],[Entity]],3))&RIGHT("00"&Table362[[#This Row],[Rule '# by Entity]],3)&"0_"&MID(SUBSTITUTE(Table362[[#This Row],[Rule Name]],"_","|",3),SEARCH("|",SUBSTITUTE(Table362[[#This Row],[Rule Name]],"_","|",3))+1,LEN(Table362[[#This Row],[Rule Name]])) -> CUS0370_NationalSecurityIndicatorIsValid | R20: Verify the national security indicator value is valid according to the appropriate reference domain or value range. | S20: Accuracy | T20: Consistency | U20: $P_I_NationalSecurityInd | V20: KNA1 | W20: CCC03 | X20: Indicator for national security for legal control | AA20: BEGIN RETURN $P_I_NationalSecurityInd = 'X'; END | AB20: =Table362[[#This Row],[IS Parameter]]&" IS NOT NULL AND "& Table362[[#This Row],[IS Parameter]]&" != ''" -> $P_I_NationalSecurityInd IS NOT NULL AND $P_I_NationalSecurityInd != '' | AC20: QUAC.checkValueIsDomainFixedValue() | AE20: =IF(Table362[[#This Row],[Entity]]="Customer","KUNNR",IF(Table362[[#This Row],[Entity]]="Vendor","LIFNR","MATNR"))&","&Table362[[#This Row],[Field]] -> KUNNR,CCC03 | AF20: ="VW_"&Table362[[#This Row],[New Rule Name]] -> VW_CUS0370_NationalSecurityIndicatorIsValid | AG20: ="create view "&Table362[[#This Row],[View Name]]&" ( "&IF(Table362[[#This Row],[Entity]]="Customer","KUNNR",IF(Table362[[#This Row],[Entity]]="Vendor","LIFNR","MATNR"))&", "&Table362[[#This Row],[Field]]&" ) as select "&IF(Table362[[#This Row],[Entity]]="Customer","KUNNR",IF(Table362[[#This Row],[Entity]]="Vendor","LIFNR","MATNR"))&", "&Table362[[#This Row],[Field]]&" from "&Table362[[#This Row],[Table]] -> create view VW_CUS0370_NationalSecurityIndicatorIsValid ( KUNNR, CCC03 ) as select KUNNR, CCC03 from KNA1 | AI20: expctrl | AK20: 37
A21: 17 | B21: IS_RDS | C21: Customer | D21: Finance | E21: Financial Accounting | F21: Customer Master (Company Code) | G21: CompanyCodeData | H21: AccountManagement | J21: =VLOOKUP(V21,Table_to_BRG!A:D,3,FALSE) -> Company Code data | K21: =VLOOKUP(V21,Table_to_BRG!A:D,2,FALSE) -> Company Code | P21: ZB_G14_CUST_InterestCycleIsValid | Q21: =UPPER(LEFT(Table362[[#This Row],[Entity]],3))&RIGHT("00"&Table362[[#This Row],[Rule '# by Entity]],3)&"0_"&MID(SUBSTITUTE(Table362[[#This Row],[Rule Name]],"_","|",3),SEARCH("|",SUBSTITUTE(Table362[[#This Row],[Rule Name]],"_","|",3))+1,LEN(Table362[[#This Row],[Rule Name]])) -> CUS0490_InterestCycleIsValid | R21: Verify the interest cycle value is valid according to the appropriate reference domain or value range. | S21: Accuracy | T21: Consistency | U21: $P_I_InterestCycle | V21: KNB1 | W21: ZINRT | X21: Interest calculation frequency in months | AA21: BEGIN RETURN $P_I_InterestCycle IN ('01', '02', '03', '04', '05', '06', '07', '08', '09', '10', '11', '12'); END | AB21: =Table362[[#This Row],[IS Parameter]]&" IS NOT NULL AND "& Table362[[#This Row],[IS Parameter]]&" != ''" -> $P_I_InterestCycle IS NOT NULL AND $P_I_InterestCycle != '' | AC21: QUAC.checkValueIsDomainFixedValue() | AE21: =IF(Table362[[#This Row],[Entity]]="Customer","KUNNR",IF(Table362[[#This Row],[Entity]]="Vendor","LIFNR","MATNR"))&",BUKRS"&","&Table362[[#This Row],[Field]] -> KUNNR,BUKRS,ZINRT | AF21: ="VW_"&Table362[[#This Row],[New Rule Name]] -> VW_CUS0490_InterestCycleIsValid | AG21: ="create view "&Table362[[#This Row],[View Name]]&" as select "&IF(Table362[[#This Row],[Entity]]="Customer","KUNNR",IF(Table362[[#This Row],[Entity]]="Vendor","LIFNR","MATNR"))&", BUKRS, "&Table362[[#This Row],[Field]]&" from "&Table362[[#This Row],[Table]] -> create view VW_CUS0490_InterestCycleIsValid as select KUNNR, BUKRS, ZINRT from KNB1 | AH21: Verify that interest calculation frequency is the same as interest cycle | AI21: intcycle01c | AK21: 49
A22: 18 | B22: IS_RDS | C22: Material | D22: Logistics | E22: Material Master | F22: Plant Data for Material | G22: GeneralData | J22: =VLOOKUP(V22,Table_to_BRG!A:D,3,FALSE) -> Plant data | K22: =VLOOKUP(V22,Table_to_BRG!A:D,2,FALSE) -> Plant | P22: ZB_G13_MATL_BOMUsageRef | Q22: =UPPER(LEFT(Table362[[#This Row],[Entity]],3))&RIGHT("00"&Table362[[#This Row],[Rule '# by Entity]],3)&"0_"&MID(SUBSTITUTE(Table362[[#This Row],[Rule Name]],"_","|",3),SEARCH("|",SUBSTITUTE(Table362[[#This Row],[Rule Name]],"_","|",3))+1,LEN(Table362[[#This Row],[Rule Name]])) -> MAT0690_BOMUsageRef | R22: Verify the BOM usage value exists in the BOM Usage - Item Statuses table. | S22: Consistency | U22: $P_I_BOMUsage | V22: MARC | W22: STLAN | X22: BOM Usage | Y22: T416 | Z22: STLAN | AA22: ="BEGIN RETURN exists('DS_IS_RDS', '"&Table362[[#This Row],[Lookup Table]]&"', '"&Table362[[#This Row],[Lookup Field]]&"', "&Table362[[#This Row],[IS Parameter]]&"); END" -> BEGIN RETURN exists('DS_IS_RDS', 'T416', 'STLAN', $P_I_BOMUsage); END | AB22: =Table362[[#This Row],[IS Parameter]]&" IS NOT NULL AND rtrim("&Table362[[#This Row],[IS Parameter]]&", ' ') != ''" -> $P_I_BOMUsage IS NOT NULL AND rtrim($P_I_BOMUsage, ' ') != '' | AC22: QUAC.checkValueExists('{$lookuptabname}','{$lookupfieldname}') | AE22: =IF(Table362[[#This Row],[Entity]]="Customer","KUNNR",IF(Table362[[#This Row],[Entity]]="Vendor","LIFNR","MATNR"))&",WERKS"&","&Table362[[#This Row],[Field]] -> MATNR,WERKS,STLAN | AF22: ="VW_"&Table362[[#This Row],[New Rule Name]] -> VW_MAT0690_BOMUsageRef | AG22: ="create view "&Table362[[#This Row],[View Name]]&" ( "&IF(Table362[[#This Row],[Entity]]="Customer","KUNNR",IF(Table362[[#This Row],[Entity]]="Vendor","LIFNR","MATNR"))&", WERKS, "&Table362[[#This Row],[Field]]&" ) as select "&IF(Table362[[#This Row],[Entity]]="Customer","KUNNR",IF(Table362[[#This Row],[Entity]]="Vendor","LIFNR","MATNR"))&", WERKS, "&Table362[[#This Row],[Field]]&" from "&Table362[[#This Row],[Table]] -> create view VW_MAT0690_BOMUsageRef ( MATNR, WERKS, STLAN ) as select MATNR, WERKS, STLAN from MARC | AI22: bom | AK22: 69
A23: 19 | B23: IS_RDS | C23: Material | D23: Logistics | E23: Material Master | F23: Plant Data for Material | G23: Forecasting | J23: =VLOOKUP(V23,Table_to_BRG!A:D,3,FALSE) -> Plant data | K23: =VLOOKUP(V23,Table_to_BRG!A:D,2,FALSE) -> Plant | P23: ZB_G13_MATL_FIYearVariantRef | Q23: =UPPER(LEFT(Table362[[#This Row],[Entity]],3))&RIGHT("00"&Table362[[#This Row],[Rule '# by Entity]],3)&"0_"&MID(SUBSTITUTE(Table362[[#This Row],[Rule Name]],"_","|",3),SEARCH("|",SUBSTITUTE(Table362[[#This Row],[Rule Name]],"_","|",3))+1,LEN(Table362[[#This Row],[Rule Name]])) -> MAT0620_FIYearVariantRef | R23: Verify the material fiscal year variant exists in the Fiscal Year Variants table. | S23: Consistency | U23: $P_I_FIYearVariant | V23: MARC | W23: PERIV | X23: Fiscal Year Variant | Y23: T009 | Z23: PERIV | AA23: ="BEGIN RETURN exists('DS_IS_RDS', '"&Table362[[#This Row],[Lookup Table]]&"', '"&Table362[[#This Row],[Lookup Field]]&"', "&Table362[[#This Row],[IS Parameter]]&"); END" -> BEGIN RETURN exists('DS_IS_RDS', 'T009', 'PERIV', $P_I_FIYearVariant); END | AB23: =Table362[[#This Row],[IS Parameter]]&" IS NOT NULL AND rtrim("&Table362[[#This Row],[IS Parameter]]&", ' ') != ''" -> $P_I_FIYearVariant IS NOT NULL AND rtrim($P_I_FIYearVariant, ' ') != '' | AC23: QUAC.checkValueExists('{$lookuptabname}','{$lookupfieldname}') | AE23: =IF(Table362[[#This Row],[Entity]]="Customer","KUNNR",IF(Table362[[#This Row],[Entity]]="Vendor","LIFNR","MATNR"))&",WERKS"&","&Table362[[#This Row],[Field]] -> MATNR,WERKS,PERIV | AF23: ="VW_"&Table362[[#This Row],[New Rule Name]] -> VW_MAT0620_FIYearVariantRef | AG23: ="create view "&Table362[[#This Row],[View Name]]&" ( "&IF(Table362[[#This Row],[Entity]]="Customer","KUNNR",IF(Table362[[#This Row],[Entity]]="Vendor","LIFNR","MATNR"))&", WERKS, "&Table362[[#This Row],[Field]]&" ) as select "&IF(Table362[[#This Row],[Entity]]="Customer","KUNNR",IF(Table362[[#This Row],[Entity]]="Vendor","LIFNR","MATNR"))&", WERKS, "&Table362[[#This Row],[Field]]&" from "&Table362[[#This Row],[Table]] -> create view VW_MAT0620_FIYearVariantRef ( MATNR, WERKS, PERIV ) as select MATNR, WERKS, PERIV from MARC | AI23: fiscalyrvarient136m | AK23: 62
A24: 20 | B24: IS_RDS | C24: Customer | D24: Logistics | E24: Customer Master | F24: General Data in Customer Master | G24: GeneralData | H24: Control | J24: =VLOOKUP(V24,Table_to_BRG!A:D,3,FALSE) -> General data | K24: =VLOOKUP(V24,Table_to_BRG!A:D,2,FALSE) -> General | P24: ZB_G14_CUST_IndustryRef | Q24: =UPPER(LEFT(Table362[[#This Row],[Entity]],3))&RIGHT("00"&Table362[[#This Row],[Rule '# by Entity]],3)&"0_"&MID(SUBSTITUTE(Table362[[#This Row],[Rule Name]],"_","|",3),SEARCH("|",SUBSTITUTE(Table362[[#This Row],[Rule Name]],"_","|",3))+1,LEN(Table362[[#This Row],[Rule Name]])) -> CUS0120_IndustryRef | R24: Verify the customer industry key value exists in the Industries table. | S24: Completeness | T24: Consistency | U24: $P_I_Industry | V24: KNA1 | W24: BRSCH | X24: Industry key | Y24: T016 | Z24: BRSCH | AA24: ="BEGIN RETURN exists('DS_IS_RDS', '"&Table362[[#This Row],[Lookup Table]]&"', '"&Table362[[#This Row],[Lookup Field]]&"', "&Table362[[#This Row],[IS Parameter]]&"); END" -> BEGIN RETURN exists('DS_IS_RDS', 'T016', 'BRSCH', $P_I_Industry); END | AB24: =Table362[[#This Row],[IS Parameter]]&" IS NOT NULL AND "& Table362[[#This Row],[IS Parameter]]&" != ''" -> $P_I_Industry IS NOT NULL AND $P_I_Industry != '' | AC24: QUAC.checkValueExists('{$lookuptabname}','{$lookupfieldname}') | AE24: =IF(Table362[[#This Row],[Entity]]="Customer","KUNNR",IF(Table362[[#This Row],[Entity]]="Vendor","LIFNR","MATNR"))&","&Table362[[#This Row],[Field]] -> KUNNR,BRSCH | AF24: ="VW_"&Table362[[#This Row],[New Rule Name]] -> VW_CUS0120_IndustryRef | AG24: ="create view "&Table362[[#This Row],[View Name]]&" as select "&IF(Table362[[#This Row],[Entity]]="Customer","KUNNR",IF(Table362[[#This Row],[Entity]]="Vendor","LIFNR","MATNR"))&", "&Table362[[#This Row],[Field]]&" from "&Table362[[#This Row],[Table]] -> create view VW_CUS0120_IndustryRef as select KUNNR, BRSCH from KNA1 | AI24: indref20c | AK24: 12
A25: 21 | B25: IS_RDS | C25: Customer | D25: Logistics | E25: Customer Master | F25: Customer Master Sales Data | G25: SalesAreaData | H25: Sales | J25: =VLOOKUP(V25,Table_to_BRG!A:D,3,FALSE) -> Customer sales data | K25: =VLOOKUP(V25,Table_to_BRG!A:D,2,FALSE) -> Sales | P25: ZB_G14_CUST_ProductProposalProcedureRef | Q25: =UPPER(LEFT(Table362[[#This Row],[Entity]],3))&RIGHT("00"&Table362[[#This Row],[Rule '# by Entity]],3)&"0_"&MID(SUBSTITUTE(Table362[[#This Row],[Rule Name]],"_","|",3),SEARCH("|",SUBSTITUTE(Table362[[#This Row],[Rule Name]],"_","|",3))+1,LEN(Table362[[#This Row],[Rule Name]])) -> CUS1090_ProductProposalProcedureRef | R25: Verify the customer product proposal procedure value exists in the Product Proposal: Definition of Customer Procedure table. | S25: Consistency | U25: $P_I_ProductProposalProc | V25: KNVV | W25: PVKSM | X25: Customer procedure for product proposal | Y25: TPVD | Z25: PVKSM | AA25: ="BEGIN RETURN exists('DS_IS_RDS', '"&Table362[[#This Row],[Lookup Table]]&"', '"&Table362[[#This Row],[Lookup Field]]&"', "&Table362[[#This Row],[IS Parameter]]&"); END" -> BEGIN RETURN exists('DS_IS_RDS', 'TPVD', 'PVKSM', $P_I_ProductProposalProc); END | AB25: =Table362[[#This Row],[IS Parameter]]&" IS NOT NULL AND "& Table362[[#This Row],[IS Parameter]]&" != ''" -> $P_I_ProductProposalProc IS NOT NULL AND $P_I_ProductProposalProc != '' | AC25: QUAC.checkValueExists('{$lookuptabname}','{$lookupfieldname}') | AE25: =IF(Table362[[#This Row],[Entity]]="Customer","KUNNR",IF(Table362[[#This Row],[Entity]]="Vendor","LIFNR","MATNR"))&",VKORG,VTWEG,SPART,"&Table362[[#This Row],[Field]] -> KUNNR,VKORG,VTWEG,SPART,PVKSM | AF25: ="VW_"&Table362[[#This Row],[New Rule Name]] -> VW_CUS1090_ProductProposalProcedureRef | AG25: ="create view "&Table362[[#This Row],[View Name]]&" as select "&IF(Table362[[#This Row],[Entity]]="Customer","KUNNR",IF(Table362[[#This Row],[Entity]]="Vendor","LIFNR","MATNR"))&", VKORG, VTWEG, SPART, "&Table362[[#This Row],[Field]]&" from "&Table362[[#This Row],[Table]] -> create view VW_CUS1090_ProductProposalProcedureRef as select KUNNR, VKORG, VTWEG, SPART, PVKSM from KNVV | AI25: prodproposal | AJ25: KNVV-KUNNR that does not exist in KNA1 | AK25: 109
A26: 22 | B26: IS_RDS | C26: Customer | D26: Logistics | E26: Customer Master | F26: Customer Master Sales Data | G26: SalesAreaData | H26: Sales | J26: =VLOOKUP(V26,Table_to_BRG!A:D,3,FALSE) -> Customer sales data | K26: =VLOOKUP(V26,Table_to_BRG!A:D,2,FALSE) -> Sales | P26: ZB_G14_CUST_SalesOrgRef | Q26: =UPPER(LEFT(Table362[[#This Row],[Entity]],3))&RIGHT("00"&Table362[[#This Row],[Rule '# by Entity]],3)&"0_"&MID(SUBSTITUTE(Table362[[#This Row],[Rule Name]],"_","|",3),SEARCH("|",SUBSTITUTE(Table362[[#This Row],[Rule Name]],"_","|",3))+1,LEN(Table362[[#This Row],[Rule Name]])) -> CUS0880_SalesOrgRef | R26: Verify the customer sales organization value exists in the Organizational Unit: Sales Organizations table. | S26: Consistency | U26: $P_I_SalesOrg | V26: KNVV | W26: VKORG | X26: Sales Organization | Y26: TVKO | Z26: VKORG | AA26: ="BEGIN RETURN exists('DS_IS_RDS', '"&Table362[[#This Row],[Lookup Table]]&"', '"&Table362[[#This Row],[Lookup Field]]&"', "&Table362[[#This Row],[IS Parameter]]&"); END" -> BEGIN RETURN exists('DS_IS_RDS', 'TVKO', 'VKORG', $P_I_SalesOrg); END | AB26: =Table362[[#This Row],[IS Parameter]]&" IS NOT NULL AND "& Table362[[#This Row],[IS Parameter]]&" != ''" -> $P_I_SalesOrg IS NOT NULL AND $P_I_SalesOrg != '' | AC26: QUAC.checkValueExists('{$lookuptabname}','{$lookupfieldname}') | AE26: =IF(Table362[[#This Row],[Entity]]="Customer","KUNNR",IF(Table362[[#This Row],[Entity]]="Vendor","LIFNR","MATNR"))&","&Table362[[#This Row],[Field]] -> KUNNR,VKORG | AF26: ="VW_"&Table362[[#This Row],[New Rule Name]] -> VW_CUS0880_SalesOrgRef | AG26: ="create view "&Table362[[#This Row],[View Name]]&" as select "&IF(Table362[[#This Row],[Entity]]="Customer","KUNNR",IF(Table362[[#This Row],[Entity]]="Vendor","LIFNR","MATNR"))&", "&Table362[[#This Row],[Field]]&" from "&Table362[[#This Row],[Table]]&" group by "&IF(Table362[[#This Row],[Entity]]="Customer","KUNNR",IF(Table362[[#This Row],[Entity]]="Vendor","LIFNR","MATNR"))&","&Table362[[#This Row],[Field]] -> create view VW_CUS0880_SalesOrgRef as select KUNNR, VKORG from KNVV group by KUNNR,VKORG | AI26: salesorg | AK26: 88
A27: 23 | B27: IS_RDS | C27: Material | D27: Logistics | E27: Material Master | F27: Plant Data for Material | G27: GeneralPlantData | H27: Storage1 | I27: Inventory | J27: =VLOOKUP(V27,Table_to_BRG!A:D,3,FALSE) -> Plant data | K27: =VLOOKUP(V27,Table_to_BRG!A:D,2,FALSE) -> Plant | P27: ZB_G13_MATL_CCPhysicalInventoryIndicatorRef | Q27: =UPPER(LEFT(Table362[[#This Row],[Entity]],3))&RIGHT("00"&Table362[[#This Row],[Rule '# by Entity]],3)&"0_"&MID(SUBSTITUTE(Table362[[#This Row],[Rule Name]],"_","|",3),SEARCH("|",SUBSTITUTE(Table362[[#This Row],[Rule Name]],"_","|",3))+1,LEN(Table362[[#This Row],[Rule Name]])) -> MAT0730_CCPhysicalInventoryIndicatorRef | R27: Verify the physical inventory indicator value for cycle counting exists in reference table T159C. | S27: Consistency | U27: $P_I_CCPhyInvIndicator | V27: MARC | W27: ABCIN | X27: Physical inventory indicator for cycle counting | Y27: T159C | Z27: ABCIN | AA27: ="BEGIN RETURN exists('DS_IS_RDS', '"&Table362[[#This Row],[Lookup Table]]&"', '"&Table362[[#This Row],[Lookup Field]]&"', "&Table362[[#This Row],[IS Parameter]]&"); END" -> BEGIN RETURN exists('DS_IS_RDS', 'T159C', 'ABCIN', $P_I_CCPhyInvIndicator); END | AB27: =Table362[[#This Row],[IS Parameter]]&" IS NOT NULL AND rtrim("&Table362[[#This Row],[IS Parameter]]&", ' ') != ''" -> $P_I_CCPhyInvIndicator IS NOT NULL AND rtrim($P_I_CCPhyInvIndicator, ' ') != '' | AC27: QUAC.checkValueExists('{$lookuptabname}','{$lookupfieldname}') | AE27: =IF(Table362[[#This Row],[Entity]]="Customer","KUNNR",IF(Table362[[#This Row],[Entity]]="Vendor","LIFNR","MATNR"))&",WERKS"&","&Table362[[#This Row],[Field]] -> MATNR,WERKS,ABCIN | AF27: ="VW_"&Table362[[#This Row],[New Rule Name]] -> VW_MAT0730_CCPhysicalInventoryIndicatorRef | AG27: ="create view "&Table362[[#This Row],[View Name]]&" ( "&IF(Table362[[#This Row],[Entity]]="Customer","KUNNR",IF(Table362[[#This Row],[Entity]]="Vendor","LIFNR","MATNR"))&", WERKS, "&Table362[[#This Row],[Field]]&" ) as select "&IF(Table362[[#This Row],[Entity]]="Customer","KUNNR",IF(Table362[[#This Row],[Entity]]="Vendor","LIFNR","MATNR"))&", WERKS, "&Table362[[#This Row],[Field]]&" from "&Table362[[#This Row],[Table]] -> create view VW_MAT0730_CCPhysicalInventoryIndicatorRef ( MATNR, WERKS, ABCIN ) as select MATNR, WERKS, ABCIN from MARC | AI27: inventory | AK27: 73
A28: 24 | B28: IS_RDS | C28: Material | D28: Logistics | E28: Material Master | F28: Plant Data for Material | G28: SalesOrg1 | J28: =VLOOKUP(V28,Table_to_BRG!A:D,3,FALSE) -> Plant data | K28: =VLOOKUP(V28,Table_to_BRG!A:D,2,FALSE) -> Plant | P28: ZB_G13_MATL_UnitofMeasureGroupRef | Q28: =UPPER(LEFT(Table362[[#This Row],[Entity]],3))&RIGHT("00"&Table362[[#This Row],[Rule '# by Entity]],3)&"0_"&MID(SUBSTITUTE(Table362[[#This Row],[Rule Name]],"_","|",3),SEARCH("|",SUBSTITUTE(Table362[[#This Row],[Rule Name]],"_","|",3))+1,LEN(Table362[[#This Row],[Rule Name]])) -> MAT0860_UnitofMeasureGroupRef | R28: Verify the unit of measure group value exists in the Unit of Measure Group table. | S28: Consistency | U28: $P_I_UnitOfMeasureGroup | V28: MARC | W28: MEGRU | X28: Unit of Measure Group | Y28: TWMEG | Z28: MEGRU | AA28: ="BEGIN RETURN exists('DS_IS_RDS', '"&Table362[[#This Row],[Lookup Table]]&"', '"&Table362[[#This Row],[Lookup Field]]&"', "&Table362[[#This Row],[IS Parameter]]&"); END" -> BEGIN RETURN exists('DS_IS_RDS', 'TWMEG', 'MEGRU', $P_I_UnitOfMeasureGroup); END | AB28: =Table362[[#This Row],[IS Parameter]]&" IS NOT NULL AND rtrim("&Table362[[#This Row],[IS Parameter]]&", ' ') != ''" -> $P_I_UnitOfMeasureGroup IS NOT NULL AND rtrim($P_I_UnitOfMeasureGroup, ' ') != '' | AC28: QUAC.checkValueExists('{$lookuptabname}','{$lookupfieldname}') | AE28: =IF(Table362[[#This Row],[Entity]]="Customer","KUNNR",IF(Table362[[#This Row],[Entity]]="Vendor","LIFNR","MATNR"))&",WERKS"&","&Table362[[#This Row],[Field]] -> MATNR,WERKS,MEGRU | AF28: ="VW_"&Table362[[#This Row],[New Rule Name]] -> VW_MAT0860_UnitofMeasureGroupRef | AG28: ="create view "&Table362[[#This Row],[View Name]]&" ( "&IF(Table362[[#This Row],[Entity]]="Customer","KUNNR",IF(Table362[[#This Row],[Entity]]="Vendor","LIFNR","MATNR"))&", WERKS, "&Table362[[#This Row],[Field]]&" ) as select "&IF(Table362[[#This Row],[Entity]]="Customer","KUNNR",IF(Table362[[#This Row],[Entity]]="Vendor","LIFNR","MATNR"))&", WERKS, "&Table362[[#This Row],[Field]]&" from "&Table362[[#This Row],[Table]] -> create view VW_MAT0860_UnitofMeasureGroupRef ( MATNR, WERKS, MEGRU ) as select MATNR, WERKS, MEGRU from MARC | AI28: uomgrp | AK28: 86
A29: 25 | B29: IS_RDS | C29: Material | D29: Logistics | E29: Material Master | F29: General Material Data | G29: WarehouseManagement | H29: Storage | I29: GeneralPlantData | J29: =VLOOKUP(V29,Table_to_BRG!A:D,3,FALSE) -> General data | K29: =VLOOKUP(V29,Table_to_BRG!A:D,2,FALSE) -> General | P29: ZB_G13_MATL_StorageConditionRef | Q29: =UPPER(LEFT(Table362[[#This Row],[Entity]],3))&RIGHT("00"&Table362[[#This Row],[Rule '# by Entity]],3)&"0_"&MID(SUBSTITUTE(Table362[[#This Row],[Rule Name]],"_","|",3),SEARCH("|",SUBSTITUTE(Table362[[#This Row],[Rule Name]],"_","|",3))+1,LEN(Table362[[#This Row],[Rule Name]])) -> MAT0140_StorageConditionRef | R29: Verify the storage condition value exists in the Storage Conditions for Materials table. | S29: Consistency | U29: $P_I_StorageCondition | V29: MARA | W29: RAUBE | X29: Storage conditions | Y29: T142 | Z29: RAUBE | AA29: ="BEGIN RETURN exists('DS_IS_RDS', '"&Table362[[#This Row],[Lookup Table]]&"', '"&Table362[[#This Row],[Lookup Field]]&"', "&Table362[[#This Row],[IS Parameter]]&"); END" -> BEGIN RETURN exists('DS_IS_RDS', 'T142', 'RAUBE', $P_I_StorageCondition); END | AB29: =Table362[[#This Row],[IS Parameter]]&" IS NOT NULL AND rtrim("&Table362[[#This Row],[IS Parameter]]&", ' ') != ''" -> $P_I_StorageCondition IS NOT NULL AND rtrim($P_I_StorageCondition, ' ') != '' | AC29: QUAC.checkValueExists('{$lookuptabname}','{$lookupfieldname}') | AE29: =IF(Table362[[#This Row],[Entity]]="Customer","KUNNR",IF(Table362[[#This Row],[Entity]]="Vendor","LIFNR","MATNR"))&","&Table362[[#This Row],[Field]] -> MATNR,RAUBE | AF29: ="VW_"&Table362[[#This Row],[New Rule Name]] -> VW_MAT0140_StorageConditionRef | AG29: ="create view "&Table362[[#This Row],[View Name]]&" as select "&IF(Table362[[#This Row],[Entity]]="Customer","KUNNR",IF(Table362[[#This Row],[Entity]]="Vendor","LIFNR","MATNR"))&", "&Table362[[#This Row],[Field]]&" from "&Table362[[#This Row],[Table]] -> create view VW_MAT0140_StorageConditionRef as select MATNR, RAUBE from MARA | AI29: storage | AK29: 14
A30: 26 | B30: IS_RDS | C30: Material | D30: Logistics | E30: Material Master | F30: Plant Data for Material | G30: SalesGeneral | H30: PlantData | J30: =VLOOKUP(V30,Table_to_BRG!A:D,3,FALSE) -> Plant data | K30: =VLOOKUP(V30,Table_to_BRG!A:D,2,FALSE) -> Plant | P30: ZB_G13_MATL_AvailabilityCheckRef | Q30: =UPPER(LEFT(Table362[[#This Row],[Entity]],3))&RIGHT("00"&Table362[[#This Row],[Rule '# by Entity]],3)&"0_"&MID(SUBSTITUTE(Table362[[#This Row],[Rule Name]],"_","|",3),SEARCH("|",SUBSTITUTE(Table362[[#This Row],[Rule Name]],"_","|",3))+1,LEN(Table362[[#This Row],[Rule Name]])) -> MAT0610_AvailabilityCheckRef | R30: Verify the availability check value exists in the Availability Check Control table. | S30: Consistency | U30: $P_I_AvailabilityCheck | V30: MARC | W30: MTVFP | X30: Checking group for availability check | Y30: TMVF | Z30: MTVFP | AA30: ="BEGIN RETURN exists('DS_IS_RDS', '"&Table362[[#This Row],[Lookup Table]]&"', '"&Table362[[#This Row],[Lookup Field]]&"', "&Table362[[#This Row],[IS Parameter]]&"); END" -> BEGIN RETURN exists('DS_IS_RDS', 'TMVF', 'MTVFP', $P_I_AvailabilityCheck); END | AB30: =Table362[[#This Row],[IS Parameter]]&" IS NOT NULL AND rtrim("&Table362[[#This Row],[IS Parameter]]&", ' ') != ''" -> $P_I_AvailabilityCheck IS NOT NULL AND rtrim($P_I_AvailabilityCheck, ' ') != '' | AC30: QUAC.checkValueExists('{$lookuptabname}','{$lookupfieldname}') | AE30: =IF(Table362[[#This Row],[Entity]]="Customer","KUNNR",IF(Table362[[#This Row],[Entity]]="Vendor","LIFNR","MATNR"))&",WERKS"&","&Table362[[#This Row],[Field]] -> MATNR,WERKS,MTVFP | AF30: ="VW_"&Table362[[#This Row],[New Rule Name]] -> VW_MAT0610_AvailabilityCheckRef | AG30: ="create view "&Table362[[#This Row],[View Name]]&" ( "&IF(Table362[[#This Row],[Entity]]="Customer","KUNNR",IF(Table362[[#This Row],[Entity]]="Vendor","LIFNR","MATNR"))&", WERKS, "&Table362[[#This Row],[Field]]&" ) as select "&IF(Table362[[#This Row],[Entity]]="Customer","KUNNR",IF(Table362[[#This Row],[Entity]]="Vendor","LIFNR","MATNR"))&", WERKS, "&Table362[[#This Row],[Field]]&" from "&Table362[[#This Row],[Table]] -> create view VW_MAT0610_AvailabilityCheckRef ( MATNR, WERKS, MTVFP ) as select MATNR, WERKS, MTVFP from MARC | AI30: availcheck | AK30: 61 | AL30: 4
A31: 27 | B31: IS_RDS | C31: Material | D31: Logistics | E31: Material Master | F31: General Material Data | G31: QualityManagement | J31: =VLOOKUP(V31,Table_to_BRG!A:D,3,FALSE) -> General data | K31: =VLOOKUP(V31,Table_to_BRG!A:D,2,FALSE) -> General | P31: ZB_G13_MATL_CatalogProfileRef | Q31: =UPPER(LEFT(Table362[[#This Row],[Entity]],3))&RIGHT("00"&Table362[[#This Row],[Rule '# by Entity]],3)&"0_"&MID(SUBSTITUTE(Table362[[#This Row],[Rule Name]],"_","|",3),SEARCH("|",SUBSTITUTE(Table362[[#This Row],[Rule Name]],"_","|",3))+1,LEN(Table362[[#This Row],[Rule Name]])) -> MAT0240_CatalogProfileRef | R31: Verify the catalog profile value exists in the Technical Report table. | S31: Consistency | U31: $P_I_CatalogProfile | V31: MARA | W31: RBNRM | X31: Catalog Profile | Y31: T352B | Z31: RBNR | AA31: ="BEGIN RETURN exists('DS_IS_RDS', '"&Table362[[#This Row],[Lookup Table]]&"', '"&Table362[[#This Row],[Lookup Field]]&"', "&Table362[[#This Row],[IS Parameter]]&"); END" -> BEGIN RETURN exists('DS_IS_RDS', 'T352B', 'RBNR', $P_I_CatalogProfile); END | AB31: =Table362[[#This Row],[IS Parameter]]&" IS NOT NULL AND rtrim("&Table362[[#This Row],[IS Parameter]]&", ' ') != ''" -> $P_I_CatalogProfile IS NOT NULL AND rtrim($P_I_CatalogProfile, ' ') != '' | AC31: QUAC.checkValueExists('{$lookuptabname}','{$lookupfieldname}') | AE31: =IF(Table362[[#This Row],[Entity]]="Customer","KUNNR",IF(Table362[[#This Row],[Entity]]="Vendor","LIFNR","MATNR"))&","&Table362[[#This Row],[Field]] -> MATNR,RBNRM | AF31: ="VW_"&Table362[[#This Row],[New Rule Name]] -> VW_MAT0240_CatalogProfileRef | AG31: ="create view "&Table362[[#This Row],[View Name]]&" as select "&IF(Table362[[#This Row],[Entity]]="Customer","KUNNR",IF(Table362[[#This Row],[Entity]]="Vendor","LIFNR","MATNR"))&", "&Table362[[#This Row],[Field]]&" from "&Table362[[#This Row],[Table]] -> create view VW_MAT0240_CatalogProfileRef as select MATNR, RBNRM from MARA | AI31: catalog | AK31: 24
A32: 28 | B32: IS_RDS | C32: Vendor | D32: Finance | E32: Financial Accounting | F32: Vendor Master (General Section) | G32: GeneralData | H32: PaymentTransactions | J32: =VLOOKUP(V32,Table_to_BRG!A:D,3,FALSE) -> General data | K32: =VLOOKUP(V32,Table_to_BRG!A:D,2,FALSE) -> General | P32: ZB_G15_VNDR_DMEIndicatorIsValid | Q32: =UPPER(LEFT(Table362[[#This Row],[Entity]],3))&RIGHT("00"&Table362[[#This Row],[Rule '# by Entity]],3)&"0_"&MID(SUBSTITUTE(Table362[[#This Row],[Rule Name]],"_","|",3),SEARCH("|",SUBSTITUTE(Table362[[#This Row],[Rule Name]],"_","|",3))+1,LEN(Table362[[#This Row],[Rule Name]])) -> VEN0140_DMEIndicatorIsValid | R32: Verify the DME indicator value is valid according to the appropriate refeence domain or value range. | S32: Consistency | U32: $P_I_DMEIndicator | V32: LFA1 | W32: DTAMS | X32: Indicator for Data Medium Exchange | AA32: BEGIN RETURN $P_I_DMEIndicator IS NULL OR length($P_I_DMEIndicator) = 0 OR $P_I_DMEIndicator IN ('0', '1'); END | AC32: QUAC.checkValueIsDomainFixedValue() | AE32: =IF(Table362[[#This Row],[Entity]]="Customer","KUNNR",IF(Table362[[#This Row],[Entity]]="Vendor","LIFNR","MATNR"))&","&Table362[[#This Row],[Field]] -> LIFNR,DTAMS | AF32: ="VW_"&Table362[[#This Row],[New Rule Name]] -> VW_VEN0140_DMEIndicatorIsValid | AG32: ="create view "&Table362[[#This Row],[View Name]]&" as select "&IF(Table362[[#This Row],[Entity]]="Customer","KUNNR",IF(Table362[[#This Row],[Entity]]="Vendor","LIFNR","MATNR"))&", "&Table362[[#This Row],[Field]]&" from "&Table362[[#This Row],[Table]] -> create view VW_VEN0140_DMEIndicatorIsValid as select LIFNR, DTAMS from LFA1 | AK32: 14
A33: 29 | B33: IS_RDS | C33: Customer | D33: Logistics | E33: Customer Master | F33: Customer Master Sales Data | G33: SalesAreaData | H33: Sales | J33: =VLOOKUP(V33,Table_to_BRG!A:D,3,FALSE) -> Customer sales data | K33: =VLOOKUP(V33,Table_to_BRG!A:D,2,FALSE) -> Sales | P33: ZB_G14_CUST_StatisticsGroupRef | Q33: =UPPER(LEFT(Table362[[#This Row],[Entity]],3))&RIGHT("00"&Table362[[#This Row],[Rule '# by Entity]],3)&"0_"&MID(SUBSTITUTE(Table362[[#This Row],[Rule Name]],"_","|",3),SEARCH("|",SUBSTITUTE(Table362[[#This Row],[Rule Name]],"_","|",3))+1,LEN(Table362[[#This Row],[Rule Name]])) -> CUS0930_StatisticsGroupRef | R33: Verify the customer statistics group value exists in the Customers: Statistics Groups table. | S33: Consistency | U33: $P_I_StatisticsGroup | V33: KNVV | W33: VERSG | X33: Customer Statistics Group | Y33: TVSD | Z33: STGKU | AA33: ="BEGIN RETURN exists('DS_IS_RDS', '"&Table362[[#This Row],[Lookup Table]]&"', '"&Table362[[#This Row],[Lookup Field]]&"', "&Table362[[#This Row],[IS Parameter]]&"); END" -> BEGIN RETURN exists('DS_IS_RDS', 'TVSD', 'STGKU', $P_I_StatisticsGroup); END | AB33: =Table362[[#This Row],[IS Parameter]]&" IS NOT NULL AND "& Table362[[#This Row],[IS Parameter]]&" != ''" -> $P_I_StatisticsGroup IS NOT NULL AND $P_I_StatisticsGroup != '' | AC33: QUAC.checkValueExists('{$lookuptabname}','{$lookupfieldname}') | AE33: =IF(Table362[[#This Row],[Entity]]="Customer","KUNNR",IF(Table362[[#This Row],[Entity]]="Vendor","LIFNR","MATNR"))&",VKORG,VTWEG,SPART,"&Table362[[#This Row],[Field]] -> KUNNR,VKORG,VTWEG,SPART,VERSG | AF33: ="VW_"&Table362[[#This Row],[New Rule Name]] -> VW_CUS0930_StatisticsGroupRef | AG33: ="create view "&Table362[[#This Row],[View Name]]&" as select "&IF(Table362[[#This Row],[Entity]]="Customer","KUNNR",IF(Table362[[#This Row],[Entity]]="Vendor","LIFNR","MATNR"))&", VKORG, VTWEG, SPART, "&Table362[[#This Row],[Field]]&" from "&Table362[[#This Row],[Table]] -> create view VW_CUS0930_StatisticsGroupRef as select KUNNR, VKORG, VTWEG, SPART, VERSG from KNVV | AI33: statgrp9c | AK33: 93
A34: 30 | B34: IS_RDS | C34: Customer | D34: SalesAndDistribution | E34: Payment Cards | F34: Credit card master | G34: Credit Card | H34: Credit Card | I34: Credit Card | J34: =VLOOKUP(V34,Table_to_BRG!A:D,3,FALSE) -> Billing | K34: =VLOOKUP(V34,Table_to_BRG!A:D,2,FALSE) -> Credit Card Master | P34: ZB_G14_CUST_PaymentCardCategoryRef | Q34: =UPPER(LEFT(Table362[[#This Row],[Entity]],3))&RIGHT("00"&Table362[[#This Row],[Rule '# by Entity]],3)&"0_"&MID(SUBSTITUTE(Table362[[#This Row],[Rule Name]],"_","|",3),SEARCH("|",SUBSTITUTE(Table362[[#This Row],[Rule Name]],"_","|",3))+1,LEN(Table362[[#This Row],[Rule Name]])) -> CUS1130_PaymentCardCategoryRef | R34: Verify the customer payment card category value exists in the Payment Card Category table. | S34: Consistency | U34: $P_I_PaymentCardCategory | V34: VCNUM | W34: CCTYP | X34: Payment cards: Card category | Y34: TVCTY | Z34: CCTYP | AA34: ="BEGIN RETURN exists('DS_IS_RDS', '"&Table362[[#This Row],[Lookup Table]]&"', '"&Table362[[#This Row],[Lookup Field]]&"', "&Table362[[#This Row],[IS Parameter]]&"); END" -> BEGIN RETURN exists('DS_IS_RDS', 'TVCTY', 'CCTYP', $P_I_PaymentCardCategory); END | AB34: =Table362[[#This Row],[IS Parameter]]&" IS NOT NULL AND "& Table362[[#This Row],[IS Parameter]]&" != ''" -> $P_I_PaymentCardCategory IS NOT NULL AND $P_I_PaymentCardCategory != '' | AC34: QUAC.checkValueExists('{$lookuptabname}','{$lookupfieldname}') | AE34: ="CCINS,CCNUM,"&Table362[[#This Row],[Field]] -> CCINS,CCNUM,CCTYP | AF34: ="VW_"&Table362[[#This Row],[New Rule Name]] -> VW_CUS1130_PaymentCardCategoryRef | AG34: ="create view "&Table362[[#This Row],[View Name]]&" as select CCINS, CCNUM, "&Table362[[#This Row],[Field]]&" from "&Table362[[#This Row],[Table]] -> create view VW_CUS1130_PaymentCardCategoryRef as select CCINS, CCNUM, CCTYP from VCNUM | AI34: paymentcard | AK34: 113
A35: 31 | B35: IS_RDS | C35: Customer | D35: SalesAndDistribution | E35: Sales | F35: Sales Document: Business Data | G35: CompanyCodeData | H35: PaymentTransactions | J35: =VLOOKUP(V35,Table_to_BRG!A:D,3,FALSE) -> Sales document | K35: =VLOOKUP(V35,Table_to_BRG!A:D,2,FALSE) -> Sales Document: Business Data | P35: ZB_G14_CUST_PaymentMethodRef | Q35: =UPPER(LEFT(Table362[[#This Row],[Entity]],3))&RIGHT("00"&Table362[[#This Row],[Rule '# by Entity]],3)&"0_"&MID(SUBSTITUTE(Table362[[#This Row],[Rule Name]],"_","|",3),SEARCH("|",SUBSTITUTE(Table362[[#This Row],[Rule Name]],"_","|",3))+1,LEN(Table362[[#This Row],[Rule Name]])) -> CUS1110_PaymentMethodRef | R35: Verify the customer payment method value exists in the Payment Methods for Automatic Payment table. | S35: Consistency | U35: $P_I_PaymentMethod | V35: VBKD | W35: ZLSCH | X35: Payment method | Y35: T042Z | Z35: ZLSCH | AA35: ="BEGIN RETURN exists('DS_IS_RDS', '"&Table362[[#This Row],[Lookup Table]]&"', '"&Table362[[#This Row],[Lookup Field]]&"', "&Table362[[#This Row],[IS Parameter]]&"); END" -> BEGIN RETURN exists('DS_IS_RDS', 'T042Z', 'ZLSCH', $P_I_PaymentMethod); END | AB35: =Table362[[#This Row],[IS Parameter]]&" IS NOT NULL AND "& Table362[[#This Row],[IS Parameter]]&" != ''" -> $P_I_PaymentMethod IS NOT NULL AND $P_I_PaymentMethod != '' | AC35: QUAC.checkValueExists('{$lookuptabname}','{$lookupfieldname}') | AE35: ="VBELN,POSNR,"&Table362[[#This Row],[Field]] -> VBELN,POSNR,ZLSCH | AF35: ="VW_"&Table362[[#This Row],[New Rule Name]] -> VW_CUS1110_PaymentMethodRef | AG35: ="create view "&Table362[[#This Row],[View Name]]&" as select VBELN, POSNR, "&Table362[[#This Row],[Field]]&" from "&Table362[[#This Row],[Table]] -> create view VW_CUS1110_PaymentMethodRef as select VBELN, POSNR, ZLSCH from VBKD | AI35: pmtmeth31c | AK35: 111
A36: 32 | B36: IS_RDS | C36: Material | D36: Logistics | E36: Material Master | F36: Sales Data for Material | G36: SalesOrg2 | J36: =VLOOKUP(V36,Table_to_BRG!A:D,3,FALSE) -> Sales data | K36: =VLOOKUP(V36,Table_to_BRG!A:D,2,FALSE) -> Sales | P36: ZB_G13_MATL_CommissionGroupRef | Q36: =UPPER(LEFT(Table362[[#This Row],[Entity]],3))&RIGHT("00"&Table362[[#This Row],[Rule '# by Entity]],3)&"0_"&MID(SUBSTITUTE(Table362[[#This Row],[Rule Name]],"_","|",3),SEARCH("|",SUBSTITUTE(Table362[[#This Row],[Rule Name]],"_","|",3))+1,LEN(Table362[[#This Row],[Rule Name]])) -> MAT1270_CommissionGroupRef | R36: Verify the commission group value exists in the Commission Groups table. | S36: Consistency | U36: $P_I_CommissionGroup | V36: MVKE | W36: PROVG | X36: Commission group | Y36: TVPR | Z36: PROVG | AA36: ="BEGIN RETURN exists('DS_IS_RDS', '"&Table362[[#This Row],[Lookup Table]]&"', '"&Table362[[#This Row],[Lookup Field]]&"', "&Table362[[#This Row],[IS Parameter]]&"); END" -> BEGIN RETURN exists('DS_IS_RDS', 'TVPR', 'PROVG', $P_I_CommissionGroup); END | AB36: =Table362[[#This Row],[IS Parameter]]&" IS NOT NULL AND rtrim("&Table362[[#This Row],[IS Parameter]]&", ' ') != ''" -> $P_I_CommissionGroup IS NOT NULL AND rtrim($P_I_CommissionGroup, ' ') != '' | AC36: QUAC.checkValueExists('{$lookuptabname}','{$lookupfieldname}') | AE36: =IF(Table362[[#This Row],[Entity]]="Customer","KUNNR",IF(Table362[[#This Row],[Entity]]="Vendor","LIFNR","MATNR"))&",VKORG,VTWEG,"&Table362[[#This Row],[Field]] -> MATNR,VKORG,VTWEG,PROVG | AF36: ="VW_"&Table362[[#This Row],[New Rule Name]] -> VW_MAT1270_CommissionGroupRef | AG36: ="create view "&Table362[[#This Row],[View Name]]&" as select "&IF(Table362[[#This Row],[Entity]]="Customer","KUNNR",IF(Table362[[#This Row],[Entity]]="Vendor","LIFNR","MATNR"))&", VKORG, VTWEG, "&Table362[[#This Row],[Field]]&" from "&Table362[[#This Row],[Table]] -> create view VW_MAT1270_CommissionGroupRef as select MATNR, VKORG, VTWEG, PROVG from MVKE | AK36: 127
A37: 35 | B37: IS_RDS | C37: Customer | D37: Logistics | E37: Customer Master | F37: General Data in Customer Master | G37: GeneralData | H37: Phone | I37: Phone | J37: =VLOOKUP(V37,Table_to_BRG!A:D,3,FALSE) -> General data | K37: =VLOOKUP(V37,Table_to_BRG!A:D,2,FALSE) -> General | N37: x | O37: ="Superceded by rule "&A1004 -> Superceded by rule 384 | P37: ZB_G14_CUST_USPhoneNumberFormat | R37: Rule to check if a US phone or fax number is in the valid format if it exists. | S37: Conformity | U37: $P_I_PhoneNumber | V37: KNA1 | W37: TELF1 TELF2 | X37: First telephone number Second telephone number | AA37: BEGIN RETURN match_pattern($P_I_PhoneNumber, '9999999999') OR match_pattern($P_I_PhoneNumber, '999-999-9999') OR match_pattern($P_I_PhoneNumber, '(999)-999-9999') OR match_pattern($P_I_PhoneNumber, '1-999-999-9999') OR match_pattern($P_I_PhoneNumber, '1-(999)-999-9999') OR match_pattern($P_I_PhoneNumber, '19999999999') OR match_pattern($P_I_PhoneNumber, '+1-999-999-9999') OR match_pattern($P_I_PhoneNumber, '+1-(999)-999-9999') OR match_pattern($P_I_PhoneNumber, '+19999999999'); END | AC37: matchPattern(pattern) or matchRegex(regexpattern) | AH37: In order to standardize phone numbers, and maintain phone data quality, only one format can be correct. Also, phone country codes and phone extensions should be stored in separate fields. The most common US formats are (999) 999-9999 and 999-999-9999, so this rule should fail for any other format 21 countries use the same phone number system as the US. Nine of those countries are US territoties and posessions: AS, FM, GU, MH, MP, PR, PW, UM, VI match_regex( $P_I_PhoneNumber, ( '^+?(1-?)?([0-9]{3}-?[0-9]{3}-?[0-9]{4}$' ) ), NULL ); | AI37: phoneus01c
A38: 33 | B38: IS_RDS | C38: Material | D38: Logistics | E38: Material Master | F38: Plant Data for Material | G38: Purchasing | J38: =VLOOKUP(V38,Table_to_BRG!A:D,3,FALSE) -> Plant data | K38: =VLOOKUP(V38,Table_to_BRG!A:D,2,FALSE) -> Plant | P38: ZB_G13_MATL_PurchasingGroupPopulated | Q38: =UPPER(LEFT(Table362[[#This Row],[Entity]],3))&RIGHT("00"&Table362[[#This Row],[Rule '# by Entity]],3)&"0_"&MID(SUBSTITUTE(Table362[[#This Row],[Rule Name]],"_","|",3),SEARCH("|",SUBSTITUTE(Table362[[#This Row],[Rule Name]],"_","|",3))+1,LEN(Table362[[#This Row],[Rule Name]])) -> MAT0380_PurchasingGroupPopulated | R38: Verify the purchasing group field is not empty. | S38: Completeness | U38: $P_I_PurchasingGroup | V38: MARC | W38: EKGRP | X38: Purchasing group | AA38: BEGIN RETURN $P_I_PurchasingGroup IS NOT NULL AND $P_I_PurchasingGroup != ''; END | AC38: QUAC.checkValueIsNotEmpty() | AE38: =IF(Table362[[#This Row],[Entity]]="Customer","KUNNR",IF(Table362[[#This Row],[Entity]]="Vendor","LIFNR","MATNR"))&",WERKS"&","&Table362[[#This Row],[Field]] -> MATNR,WERKS,EKGRP | AF38: ="VW_"&Table362[[#This Row],[New Rule Name]] -> VW_MAT0380_PurchasingGroupPopulated | AG38: ="create view "&Table362[[#This Row],[View Name]]&" ( "&IF(Table362[[#This Row],[Entity]]="Customer","KUNNR",IF(Table362[[#This Row],[Entity]]="Vendor","LIFNR","MATNR"))&", WERKS, "&Table362[[#This Row],[Field]]&" ) as select "&IF(Table362[[#This Row],[Entity]]="Customer","KUNNR",IF(Table362[[#This Row],[Entity]]="Vendor","LIFNR","MATNR"))&", WERKS, "&Table362[[#This Row],[Field]]&" from "&Table362[[#This Row],[Table]] -> create view VW_MAT0380_PurchasingGroupPopulated ( MATNR, WERKS, EKGRP ) as select MATNR, WERKS, EKGRP from MARC | AI38: purchgrpmatl | AK38: 38
A39: 34 | B39: IS_RDS | C39: Material | D39: Logistics | E39: Material Master | F39: Material Data for Each Warehouse Number | G39: WarehouseManagement | J39: =VLOOKUP(V39,Table_to_BRG!A:D,3,FALSE) -> Warehouse data | K39: =VLOOKUP(V39,Table_to_BRG!A:D,2,FALSE) -> Material Data for Each Warehouse Number | P39: ZB_G13_MATL_WarehouseNumberPopulated | Q39: =UPPER(LEFT(Table362[[#This Row],[Entity]],3))&RIGHT("00"&Table362[[#This Row],[Rule '# by Entity]],3)&"0_"&MID(SUBSTITUTE(Table362[[#This Row],[Rule Name]],"_","|",3),SEARCH("|",SUBSTITUTE(Table362[[#This Row],[Rule Name]],"_","|",3))+1,LEN(Table362[[#This Row],[Rule Name]])) -> MAT1100_WarehouseNumberPopulated | R39: Verify the warehouse number field is not empty. | S39: Completeness | U39: $P_I_WarehouseNumber | V39: MLGN | W39: LGNUM | X39: Warehouse number / Warehouse complex | AA39: BEGIN RETURN $P_I_WarehouseNumber IS NOT NULL AND $P_I_WarehouseNumber != ''; END | AC39: QUAC.checkValueIsNotEmpty() | AE39: =IF(Table362[[#This Row],[Entity]]="Customer","KUNNR",IF(Table362[[#This Row],[Entity]]="Vendor","LIFNR","MATNR"))&","&Table362[[#This Row],[Field]] -> MATNR,LGNUM | AF39: ="VW_"&Table362[[#This Row],[New Rule Name]] -> VW_MAT1100_WarehouseNumberPopulated | AG39: ="create view "&Table362[[#This Row],[View Name]]&" as select "&IF(Table362[[#This Row],[Entity]]="Customer","KUNNR",IF(Table362[[#This Row],[Entity]]="Vendor","LIFNR","MATNR"))&", "&Table362[[#This Row],[Field]]&" from "&Table362[[#This Row],[Table]] -> create view VW_MAT1100_WarehouseNumberPopulated as select MATNR, LGNUM from MLGN | AK39: 110
A40: 36 | B40: IS_RDS | C40: Vendor | D40: Finance | E40: Financial Accounting | F40: Vendor Master (Dunning Data) | G40: CompanyCodeData | H40: Correspondence | I40: Dunning | J40: =VLOOKUP(V40,Table_to_BRG!A:D,3,FALSE) -> Dunning data | K40: =VLOOKUP(V40,Table_to_BRG!A:D,2,FALSE) -> Dunning | P40: ZB_G15_VNDR_DunningClerkRef | Q40: =UPPER(LEFT(Table362[[#This Row],[Entity]],3))&RIGHT("00"&Table362[[#This Row],[Rule '# by Entity]],3)&"0_"&MID(SUBSTITUTE(Table362[[#This Row],[Rule Name]],"_","|",3),SEARCH("|",SUBSTITUTE(Table362[[#This Row],[Rule Name]],"_","|",3))+1,LEN(Table362[[#This Row],[Rule Name]])) -> VEN0530_DunningClerkRef | R40: Verify the vendor dunning clerk exists in the Vendor Master Dunning Data table. | S40: Consistency | U40: $P_I_DunningClerk | V40: LFB5 | W40: BUSAB | X40: Dunning clerk | Y40: T001S | Z40: BUSAB | AA40: ="BEGIN RETURN exists('DS_IS_RDS', '"&Table362[[#This Row],[Lookup Table]]&"', '"&Table362[[#This Row],[Lookup Field]]&"', "&Table362[[#This Row],[IS Parameter]]&"); END" -> BEGIN RETURN exists('DS_IS_RDS', 'T001S', 'BUSAB', $P_I_DunningClerk); END | AC40: QUAC.checkValueExists('{$lookuptabname}','{$lookupfieldname}') | AE40: =IF(Table362[[#This Row],[Entity]]="Customer","KUNNR",IF(Table362[[#This Row],[Entity]]="Vendor","LIFNR","MATNR"))&",BUKRS,MABERS,"&Table362[[#This Row],[Field]] -> LIFNR,BUKRS,MABERS,BUSAB | AF40: ="VW_"&Table362[[#This Row],[New Rule Name]] -> VW_VEN0530_DunningClerkRef | AG40: ="create view "&Table362[[#This Row],[View Name]]&" as select "&IF(Table362[[#This Row],[Entity]]="Customer","KUNNR",IF(Table362[[#This Row],[Entity]]="Vendor","LIFNR","MATNR"))&", BUKRS, MABER, "&Table362[[#This Row],[Field]]&" from "&Table362[[#This Row],[Table]] -> create view VW_VEN0530_DunningClerkRef as select LIFNR, BUKRS, MABER, BUSAB from LFB5 | AI40: dunning01v | AK40: 53
A41: 37 | B41: IS_RDS | C41: Material | D41: Logistics | E41: Material Master | F41: Plant Data for Material | G41: Plant Data | J41: =VLOOKUP(V41,Table_to_BRG!A:D,3,FALSE) -> Plant data | K41: =VLOOKUP(V41,Table_to_BRG!A:D,2,FALSE) -> Plant | P41: ZB_G13_MATL_SchedulingMarginKeyPopulated | Q41: =UPPER(LEFT(Table362[[#This Row],[Entity]],3))&RIGHT("00"&Table362[[#This Row],[Rule '# by Entity]],3)&"0_"&MID(SUBSTITUTE(Table362[[#This Row],[Rule Name]],"_","|",3),SEARCH("|",SUBSTITUTE(Table362[[#This Row],[Rule Name]],"_","|",3))+1,LEN(Table362[[#This Row],[Rule Name]])) -> MAT0530_SchedulingMarginKeyPopulated | R41: Verify the scheduling margin key for floats field is not empty. | S41: Completeness | U41: $P_I_SchedKey | V41: MARC | W41: FHORI | X41: Scheduling margin key for floats | AA41: BEGIN RETURN $P_I_SchedKey IS NOT NULL AND $P_I_SchedKey != ''; END | AC41: QUAC.checkValueIsNotEmpty() | AE41: =IF(Table362[[#This Row],[Entity]]="Customer","KUNNR",IF(Table362[[#This Row],[Entity]]="Vendor","LIFNR","MATNR"))&",WERKS"&","&Table362[[#This Row],[Field]] -> MATNR,WERKS,FHORI | AF41: ="VW_"&Table362[[#This Row],[New Rule Name]] -> VW_MAT0530_SchedulingMarginKeyPopulated | AG41: ="create view "&Table362[[#This Row],[View Name]]&" ( "&IF(Table362[[#This Row],[Entity]]="Customer","KUNNR",IF(Table362[[#This Row],[Entity]]="Vendor","LIFNR","MATNR"))&", WERKS, "&Table362[[#This Row],[Field]]&" ) as select "&IF(Table362[[#This Row],[Entity]]="Customer","KUNNR",IF(Table362[[#This Row],[Entity]]="Vendor","LIFNR","MATNR"))&", WERKS, "&Table362[[#This Row],[Field]]&" from "&Table362[[#This Row],[Table]] -> create view VW_MAT0530_SchedulingMarginKeyPopulated ( MATNR, WERKS, FHORI ) as select MATNR, WERKS, FHORI from MARC | AK41: 53
A42: 38 | B42: IS_RDS | C42: Customer | D42: Finance | E42: Financial Accounting | F42: Customer Master (Company Code) | G42: CompanyCodeData | H42: Correspondence | J42: =VLOOKUP(V42,Table_to_BRG!A:D,3,FALSE) -> Company Code data | K42: =VLOOKUP(V42,Table_to_BRG!A:D,2,FALSE) -> Company Code | P42: ZB_G14_CUST_AccountingClerkRef | Q42: =UPPER(LEFT(Table362[[#This Row],[Entity]],3))&RIGHT("00"&Table362[[#This Row],[Rule '# by Entity]],3)&"0_"&MID(SUBSTITUTE(Table362[[#This Row],[Rule Name]],"_","|",3),SEARCH("|",SUBSTITUTE(Table362[[#This Row],[Rule Name]],"_","|",3))+1,LEN(Table362[[#This Row],[Rule Name]])) -> CUS0420_AccountingClerkRef | R42: Verify the customer accounting clerk value exists in the Accounting Clerks table. | S42: Consistency | U42: $P_I_AccountingClerk | V42: KNB1 | W42: BUSAB | X42: Accounting Clerk | Y42: T001S | Z42: BUSAB | AA42: ="BEGIN RETURN exists('DS_IS_RDS', '"&Table362[[#This Row],[Lookup Table]]&"', '"&Table362[[#This Row],[Lookup Field]]&"', "&Table362[[#This Row],[IS Parameter]]&"); END" -> BEGIN RETURN exists('DS_IS_RDS', 'T001S', 'BUSAB', $P_I_AccountingClerk); END | AB42: =Table362[[#This Row],[IS Parameter]]&" IS NOT NULL AND "& Table362[[#This Row],[IS Parameter]]&" != ''" -> $P_I_AccountingClerk IS NOT NULL AND $P_I_AccountingClerk != '' | AC42: QUAC.checkValueExists('{$lookuptabname}','{$lookupfieldname}') | AE42: =IF(Table362[[#This Row],[Entity]]="Customer","KUNNR",IF(Table362[[#This Row],[Entity]]="Vendor","LIFNR","MATNR"))&",BUKRS"&","&Table362[[#This Row],[Field]] -> KUNNR,BUKRS,BUSAB | AF42: ="VW_"&Table362[[#This Row],[New Rule Name]] -> VW_CUS0420_AccountingClerkRef | AG42: ="create view "&Table362[[#This Row],[View Name]]&" as select "&IF(Table362[[#This Row],[Entity]]="Customer","KUNNR",IF(Table362[[#This Row],[Entity]]="Vendor","LIFNR","MATNR"))&", BUKRS, "&Table362[[#This Row],[Field]]&" from "&Table362[[#This Row],[Table]] -> create view VW_CUS0420_AccountingClerkRef as select KUNNR, BUKRS, BUSAB from KNB1 | AI42: acctclerk38c | AK42: 42 | AL42: 5
A43: 39 | B43: IS_RDS | C43: Customer | D43: Logistics | E43: Customer Master | F43: General Data in Customer Master | G43: GeneralData | H43: Marketing | J43: =VLOOKUP(V43,Table_to_BRG!A:D,3,FALSE) -> General data | K43: =VLOOKUP(V43,Table_to_BRG!A:D,2,FALSE) -> General | P43: ZB_G14_CUST_IndustryCodeRef | Q43: =UPPER(LEFT(Table362[[#This Row],[Entity]],3))&RIGHT("00"&Table362[[#This Row],[Rule '# by Entity]],3)&"0_"&MID(SUBSTITUTE(Table362[[#This Row],[Rule Name]],"_","|",3),SEARCH("|",SUBSTITUTE(Table362[[#This Row],[Rule Name]],"_","|",3))+1,LEN(Table362[[#This Row],[Rule Name]])) -> CUS0280_IndustryCodeRef | R43: Verify the customer industry code value exists in the Industry Code (Customer Master) table. | S43: Completeness | T43: Consistency | U43: $P_I_IndustryCode | V43: KNA1 | W43: BRAN1 | X43: Industry code 1 | Y43: TBRC | Z43: BRACO | AA43: ="BEGIN RETURN exists('DS_IS_RDS', '"&Table362[[#This Row],[Lookup Table]]&"', '"&Table362[[#This Row],[Lookup Field]]&"', "&Table362[[#This Row],[IS Parameter]]&"); END" -> BEGIN RETURN exists('DS_IS_RDS', 'TBRC', 'BRACO', $P_I_IndustryCode); END | AB43: =Table362[[#This Row],[IS Parameter]]&" IS NOT NULL AND "& Table362[[#This Row],[IS Parameter]]&" != ''" -> $P_I_IndustryCode IS NOT NULL AND $P_I_IndustryCode != '' | AC43: QUAC.checkValueExists('{$lookuptabname}','{$lookupfieldname}') | AE43: =IF(Table362[[#This Row],[Entity]]="Customer","KUNNR",IF(Table362[[#This Row],[Entity]]="Vendor","LIFNR","MATNR"))&","&Table362[[#This Row],[Field]] -> KUNNR,BRAN1 | AF43: ="VW_"&Table362[[#This Row],[New Rule Name]] -> VW_CUS0280_IndustryCodeRef | AG43: ="create view "&Table362[[#This Row],[View Name]]&" as select "&IF(Table362[[#This Row],[Entity]]="Customer","KUNNR",IF(Table362[[#This Row],[Entity]]="Vendor","LIFNR","MATNR"))&", "&Table362[[#This Row],[Field]]&" from "&Table362[[#This Row],[Table]] -> create view VW_CUS0280_IndustryCodeRef as select KUNNR, BRAN1 from KNA1 | AI43: indcode39c | AK43: 28
A44: 40 | B44: IS_RDS | C44: Customer | D44: Logistics | E44: Customer Master | F44: Customer Master Sales Data | G44: SalesAreaData | H44: Sales | J44: =VLOOKUP(V44,Table_to_BRG!A:D,3,FALSE) -> Customer sales data | K44: =VLOOKUP(V44,Table_to_BRG!A:D,2,FALSE) -> Sales | P44: ZB_G14_CUST_SalesOfficeRef | Q44: =UPPER(LEFT(Table362[[#This Row],[Entity]],3))&RIGHT("00"&Table362[[#This Row],[Rule '# by Entity]],3)&"0_"&MID(SUBSTITUTE(Table362[[#This Row],[Rule Name]],"_","|",3),SEARCH("|",SUBSTITUTE(Table362[[#This Row],[Rule Name]],"_","|",3))+1,LEN(Table362[[#This Row],[Rule Name]])) -> CUS1060_SalesOfficeRef | R44: Verify the customer sales office value exists in the Organizational Unit: Sales Offices: Texts table. | S44: Consistency | U44: $P_I_SalesOffice | V44: KNVV | W44: VKBUR | X44: Sales Office | Y44: TVKBT | Z44: VKBUR | AA44: ="BEGIN RETURN exists('DS_IS_RDS', '"&Table362[[#This Row],[Lookup Table]]&"', '"&Table362[[#This Row],[Lookup Field]]&"', "&Table362[[#This Row],[IS Parameter]]&"); END" -> BEGIN RETURN exists('DS_IS_RDS', 'TVKBT', 'VKBUR', $P_I_SalesOffice); END | AB44: =Table362[[#This Row],[IS Parameter]]&" IS NOT NULL AND "& Table362[[#This Row],[IS Parameter]]&" != ''" -> $P_I_SalesOffice IS NOT NULL AND $P_I_SalesOffice != '' | AC44: QUAC.checkValueExists('{$lookuptabname}','{$lookupfieldname}') | AE44: =IF(Table362[[#This Row],[Entity]]="Customer","KUNNR",IF(Table362[[#This Row],[Entity]]="Vendor","LIFNR","MATNR"))&",VKORG,VTWEG,SPART,"&Table362[[#This Row],[Field]] -> KUNNR,VKORG,VTWEG,SPART,VKBUR | AF44: ="VW_"&Table362[[#This Row],[New Rule Name]] -> VW_CUS1060_SalesOfficeRef | AG44: ="create view "&Table362[[#This Row],[View Name]]&" as select "&IF(Table362[[#This Row],[Entity]]="Customer","KUNNR",IF(Table362[[#This Row],[Entity]]="Vendor","LIFNR","MATNR"))&", VKORG, VTWEG, SPART, "&Table362[[#This Row],[Field]]&" from "&Table362[[#This Row],[Table]] -> create view VW_CUS1060_SalesOfficeRef as select KUNNR, VKORG, VTWEG, SPART, VKBUR from KNVV | AI44: salesoffice | AK44: 106
A45: 41 | B45: IS_RDS | C45: Material | D45: Logistics | E45: Material Master | F45: General Material Data | G45: GeneralPlantData | H45: Storage2 | J45: =VLOOKUP(V45,Table_to_BRG!A:D,3,FALSE) -> General data | K45: =VLOOKUP(V45,Table_to_BRG!A:D,2,FALSE) -> General | P45: ZB_G13_MATL_SerialNumberLevelIsValid | Q45: =UPPER(LEFT(Table362[[#This Row],[Entity]],3))&RIGHT("00"&Table362[[#This Row],[Rule '# by Entity]],3)&"0_"&MID(SUBSTITUTE(Table362[[#This Row],[Rule Name]],"_","|",3),SEARCH("|",SUBSTITUTE(Table362[[#This Row],[Rule Name]],"_","|",3))+1,LEN(Table362[[#This Row],[Rule Name]])) -> MAT0280_SerialNumberLevelIsValid | R45: Verify the serial number level value is valid according to the appropriate reference domain or value range. | S45: Accuracy | T45: Consistency | U45: $P_I_SerialNoDomain | V45: MARA | W45: SERLV | X45: Level of Explicitness for Serial Number | AA45: BEGIN RETURN $P_I_SerialNoDomain IN ('1'); END | AB45: =Table362[[#This Row],[IS Parameter]]&" IS NOT NULL AND rtrim("&Table362[[#This Row],[IS Parameter]]&", ' ') != ''" -> $P_I_SerialNoDomain IS NOT NULL AND rtrim($P_I_SerialNoDomain, ' ') != '' | AC45: QUAC.checkValueIsDomainFixedValue() | AE45: =IF(Table362[[#This Row],[Entity]]="Customer","KUNNR",IF(Table362[[#This Row],[Entity]]="Vendor","LIFNR","MATNR"))&","&Table362[[#This Row],[Field]] -> MATNR,SERLV | AF45: ="VW_"&Table362[[#This Row],[New Rule Name]] -> VW_MAT0280_SerialNumberLevelIsValid | AG45: ="create view "&Table362[[#This Row],[View Name]]&" as select "&IF(Table362[[#This Row],[Entity]]="Customer","KUNNR",IF(Table362[[#This Row],[Entity]]="Vendor","LIFNR","MATNR"))&", "&Table362[[#This Row],[Field]]&" from "&Table362[[#This Row],[Table]] -> create view VW_MAT0280_SerialNumberLevelIsValid as select MATNR, SERLV from MARA | AK45: 28
A46: 42 | B46: IS_RDS | C46: Vendor | D46: Finance | E46: Financial Accounting | F46: Vendor Master (Company Code) | G46: CompanyCodeData | H46: Correspondence | I46: Bank | J46: =VLOOKUP(V46,Table_to_BRG!A:D,3,FALSE) -> Company Code data | K46: =VLOOKUP(V46,Table_to_BRG!A:D,2,FALSE) -> Company Code | P46: ZB_G15_VNDR_BankStatementIndicatorRef | Q46: =UPPER(LEFT(Table362[[#This Row],[Entity]],3))&RIGHT("00"&Table362[[#This Row],[Rule '# by Entity]],3)&"0_"&MID(SUBSTITUTE(Table362[[#This Row],[Rule Name]],"_","|",3),SEARCH("|",SUBSTITUTE(Table362[[#This Row],[Rule Name]],"_","|",3))+1,LEN(Table362[[#This Row],[Rule Name]])) -> VEN0500_BankStatementIndicatorRef | R46: Verify the vendor bank statement indicator value exists in the Indicator for Periodic Account Statements table. | S46: Consistency | U46: $P_I_BankStmtInd | V46: LFB1 | W46: XAUSZ | X46: Indicator for periodic account statements | Y46: T048K | Z46: XAUSZ | AA46: ="BEGIN RETURN exists('DS_IS_RDS', '"&Table362[[#This Row],[Lookup Table]]&"', '"&Table362[[#This Row],[Lookup Field]]&"', "&Table362[[#This Row],[IS Parameter]]&"); END" -> BEGIN RETURN exists('DS_IS_RDS', 'T048K', 'XAUSZ', $P_I_BankStmtInd); END | AC46: QUAC.checkValueExists('{$lookuptabname}','{$lookupfieldname}') | AE46: =IF(Table362[[#This Row],[Entity]]="Customer","KUNNR",IF(Table362[[#This Row],[Entity]]="Vendor","LIFNR","MATNR"))&",BUKRS,"&Table362[[#This Row],[Field]] -> LIFNR,BUKRS,XAUSZ | AF46: ="VW_"&Table362[[#This Row],[New Rule Name]] -> VW_VEN0500_BankStatementIndicatorRef | AG46: ="create view "&Table362[[#This Row],[View Name]]&" as select "&IF(Table362[[#This Row],[Entity]]="Customer","KUNNR",IF(Table362[[#This Row],[Entity]]="Vendor","LIFNR","MATNR"))&", BUKRS, "&Table362[[#This Row],[Field]]&" from "&Table362[[#This Row],[Table]] -> create view VW_VEN0500_BankStatementIndicatorRef as select LIFNR, BUKRS, XAUSZ from LFB1 | AI46: bank42v | AK46: 50
A47: 43 | B47: IS_RDS | C47: Material | D47: Logistics | E47: Material Master | F47: Material Data for Each Warehouse Number | G47: WarehouseManagement | J47: =VLOOKUP(V47,Table_to_BRG!A:D,3,FALSE) -> Warehouse data | K47: =VLOOKUP(V47,Table_to_BRG!A:D,2,FALSE) -> Material Data for Each Warehouse Number | P47: ZB_G13_MATL_ProposedUOMfromMatIsValid | Q47: =UPPER(LEFT(Table362[[#This Row],[Entity]],3))&RIGHT("00"&Table362[[#This Row],[Rule '# by Entity]],3)&"0_"&MID(SUBSTITUTE(Table362[[#This Row],[Rule Name]],"_","|",3),SEARCH("|",SUBSTITUTE(Table362[[#This Row],[Rule Name]],"_","|",3))+1,LEN(Table362[[#This Row],[Rule Name]])) -> MAT1110_ProposedUOMfromMatIsValid | R47: Verify the proposed UoM from material value is valid according to the appropriate reference domain or value range. | S47: Accuracy | T47: Consistency | U47: $P_I_ProposedUOM | V47: MLGN | W47: VOMEM | X47: Default for unit of measure from material master record | AA47: BEGIN RETURN $P_I_ProposedUOM IN ('A','B', 'K', 'L', 'M', 'N'); END | AB47: =Table362[[#This Row],[IS Parameter]]&" IS NOT NULL AND rtrim("&Table362[[#This Row],[IS Parameter]]&", ' ') != ''" -> $P_I_ProposedUOM IS NOT NULL AND rtrim($P_I_ProposedUOM, ' ') != '' | AC47: QUAC.checkValueIsDomainFixedValue() | AE47: =IF(Table362[[#This Row],[Entity]]="Customer","KUNNR",IF(Table362[[#This Row],[Entity]]="Vendor","LIFNR","MATNR"))&",LGNUM,"&Table362[[#This Row],[Field]] -> MATNR,LGNUM,VOMEM | AF47: ="VW_"&Table362[[#This Row],[New Rule Name]] -> VW_MAT1110_ProposedUOMfromMatIsValid | AG47: ="create view "&Table362[[#This Row],[View Name]]&" as select "&IF(Table362[[#This Row],[Entity]]="Customer","KUNNR",IF(Table362[[#This Row],[Entity]]="Vendor","LIFNR","MATNR"))&", LGNUM, "&Table362[[#This Row],[Field]]&" from "&Table362[[#This Row],[Table]] -> create view VW_MAT1110_ProposedUOMfromMatIsValid as select MATNR, LGNUM, VOMEM from MLGN | AI47: uom | AK47: 111
A48: 44 | B48: IS_RDS | C48: Material | G48: WarehouseManagement | H48: Movement | J48: =VLOOKUP(V48,Table_to_BRG!A:D,3,FALSE) -> Warehouse data | K48: =VLOOKUP(V48,Table_to_BRG!A:D,2,FALSE) -> Material Data for Each Warehouse Number | P48: ZB_G13_MATL_SpecialMovementRef | Q48: =UPPER(LEFT(Table362[[#This Row],[Entity]],3))&RIGHT("00"&Table362[[#This Row],[Rule '# by Entity]],3)&"0_"&MID(SUBSTITUTE(Table362[[#This Row],[Rule Name]],"_","|",3),SEARCH("|",SUBSTITUTE(Table362[[#This Row],[Rule Name]],"_","|",3))+1,LEN(Table362[[#This Row],[Rule Name]])) -> MAT1180_SpecialMovementRef | R48: Verify the special movement value exists in the Special Movement Indicators table. | S48: Consistency | U48: $P_I_SpecialMovement | V48: MLGN | W48: BSSKZ | X48: Special movement indicator for warehouse mgmt. | Y48: T306 | Z48: BSSKZ | AA48: ="BEGIN RETURN exists('DS_IS_RDS', '"&Table362[[#This Row],[Lookup Table]]&"', '"&Table362[[#This Row],[Lookup Field]]&"', "&Table362[[#This Row],[IS Parameter]]&"); END" -> BEGIN RETURN exists('DS_IS_RDS', 'T306', 'BSSKZ', $P_I_SpecialMovement); END | AB48: =Table362[[#This Row],[IS Parameter]]&" IS NOT NULL AND rtrim("&Table362[[#This Row],[IS Parameter]]&", ' ') != ''" -> $P_I_SpecialMovement IS NOT NULL AND rtrim($P_I_SpecialMovement, ' ') != '' | AC48: QUAC.checkValueExists('{$lookuptabname}','{$lookupfieldname}') | AE48: =IF(Table362[[#This Row],[Entity]]="Customer","KUNNR",IF(Table362[[#This Row],[Entity]]="Vendor","LIFNR","MATNR"))&",LGNUM,"&Table362[[#This Row],[Field]] -> MATNR,LGNUM,BSSKZ | AF48: ="VW_"&Table362[[#This Row],[New Rule Name]] -> VW_MAT1180_SpecialMovementRef | AG48: ="create view "&Table362[[#This Row],[View Name]]&" as select "&IF(Table362[[#This Row],[Entity]]="Customer","KUNNR",IF(Table362[[#This Row],[Entity]]="Vendor","LIFNR","MATNR"))&", LGNUM, "&Table362[[#This Row],[Field]]&" from "&Table362[[#This Row],[Table]] -> create view VW_MAT1180_SpecialMovementRef as select MATNR, LGNUM, BSSKZ from MLGN | AH48: MVGN is used by ECC. MLGN has identical fields, but it is used in CRM. | AK48: 118
A49: 47 | B49: IS_RDS | C49: Vendor | J49: =VLOOKUP(V49,Table_to_BRG!A:D,3,FALSE) -> Customer sales data | K49: =VLOOKUP(V49,Table_to_BRG!A:D,2,FALSE) -> Sales | N49: x | O49: Need table where vendor exchange rate type is stored | P49: ZB_G15_VNDR_ExchangeRateTypeRef | R49: Verify the vendor Exchange Rate Type exists. | S49: Consistency | U49: $P_I_ExchRateType | V49: KNVV | W49: KURST | X49: Exchange Rate Type | Y49: TCURV | Z49: KURST | AA49: ="BEGIN RETURN exists('DS_IS_RDS', '"&Table362[[#This Row],[Lookup Table]]&"', '"&Table362[[#This Row],[Lookup Field]]&"', "&Table362[[#This Row],[IS Parameter]]&"); END" -> BEGIN RETURN exists('DS_IS_RDS', 'TCURV', 'KURST', $P_I_ExchRateType); END | AC49: QUAC.checkValueExists('{$lookuptabname}','{$lookupfieldname}') | AE49: =IF(Table362[[#This Row],[Entity]]="Customer","KUNNR",IF(Table362[[#This Row],[Entity]]="Vendor","LIFNR","MATNR"))&","&Table362[[#This Row],[Field]] -> LIFNR,KURST | AG49: ="create view "&Table362[[#This Row],[View Name]]&" as select "&IF(Table362[[#This Row],[Entity]]="Customer","KUNNR",IF(Table362[[#This Row],[Entity]]="Vendor","LIFNR","MATNR"))&", "&Table362[[#This Row],[Field]]&" from "&Table362[[#This Row],[Table]] -> create view as select LIFNR, KURST from KNVV | AH49: Where is exchange rate type stored in vendor master tables? | AI49: exchrate01v
A50: 45 | B50: IS_RDS | C50: Vendor | D50: Logistics | E50: Vendor Master | F50: Partner Functions | G50: PurchaseOrgData | H50: PartnerFunctions | J50: =VLOOKUP(V50,Table_to_BRG!A:D,3,FALSE) -> Purchasing data | K50: =VLOOKUP(V50,Table_to_BRG!A:D,2,FALSE) -> Partner functions | P50: ZB_G15_VNDR_PartnerFunctionPopulated | Q50: =UPPER(LEFT(Table362[[#This Row],[Entity]],3))&RIGHT("00"&Table362[[#This Row],[Rule '# by Entity]],3)&"0_"&MID(SUBSTITUTE(Table362[[#This Row],[Rule Name]],"_","|",3),SEARCH("|",SUBSTITUTE(Table362[[#This Row],[Rule Name]],"_","|",3))+1,LEN(Table362[[#This Row],[Rule Name]])) -> VEN0700_PartnerFunctionPopulated | R50: Verify the partner function field is not empty. | S50: Completeness | U50: $P_I_PartnerFunction | V50: WYT3 | W50: PARVW | X50: Partner Function | AA50: BEGIN RETURN $P_I_PartnerFunction IS NOT NULL AND $P_I_PartnerFunction != ''; END | AC50: QUAC.checkValueIsNotEmpty() | AE50: LIFNR,EKORG,LTSNR,WERKS,PARVW | AF50: ="VW_"&Table362[[#This Row],[New Rule Name]] -> VW_VEN0700_PartnerFunctionPopulated | AG50: ="create view "&Table362[[#This Row],[View Name]]&" as select "&IF(Table362[[#This Row],[Entity]]="Customer","KUNNR",IF(Table362[[#This Row],[Entity]]="Vendor","LIFNR","MATNR"))&", EKORG, LTSNR, WERKS, "&Table362[[#This Row],[Field]]&" from "&Table362[[#This Row],[Table]]&" group by LIFNR,EKORG,LTSNR,WERKS,PARVW" -> create view VW_VEN0700_PartnerFunctionPopulated as select LIFNR, EKORG, LTSNR, WERKS, PARVW from WYT3 group by LIFNR,EKORG,LTSNR,WERKS,PARVW | AI50: partnerfn01v | AK50: 70
A51: 46 | B51: IS_RDS | C51: Customer | D51: Logistics | E51: Customer Master | F51: General Data in Customer Master | G51: GeneralData | H51: Address | I51: Tax | J51: =VLOOKUP(V51,Table_to_BRG!A:D,3,FALSE) -> General data | K51: =VLOOKUP(V51,Table_to_BRG!A:D,2,FALSE) -> General | P51: ZB_G14_CUST_TaxJurisdictionPopulated | Q51: =UPPER(LEFT(Table362[[#This Row],[Entity]],3))&RIGHT("00"&Table362[[#This Row],[Rule '# by Entity]],3)&"0_"&MID(SUBSTITUTE(Table362[[#This Row],[Rule Name]],"_","|",3),SEARCH("|",SUBSTITUTE(Table362[[#This Row],[Rule Name]],"_","|",3))+1,LEN(Table362[[#This Row],[Rule Name]])) -> CUS0310_TaxJurisdictionPopulated | R51: Verify the customer tax jurisdiction field is not empty. | S51: Completeness | U51: $P_I_TaxJurisdiction | V51: KNA1 | W51: TXJCD | X51: Tax Jurisdiction | AA51: BEGIN RETURN $P_I_TaxJurisdiction IS NOT NULL AND $P_I_TaxJurisdiction != ''; END | AC51: QUAC.checkValueIsNotEmpty() | AE51: =IF(Table362[[#This Row],[Entity]]="Customer","KUNNR",IF(Table362[[#This Row],[Entity]]="Vendor","LIFNR","MATNR"))&","&Table362[[#This Row],[Field]] -> KUNNR,TXJCD | AF51: ="VW_"&Table362[[#This Row],[New Rule Name]] -> VW_CUS0310_TaxJurisdictionPopulated | AG51: ="create view "&Table362[[#This Row],[View Name]]&" as select "&Table362[[#This Row],[Table]]&", "&Table362[[#This Row],[Field]]&" from "&Table362[[#This Row],[Table]] -> create view VW_CUS0310_TaxJurisdictionPopulated as select KNA1, TXJCD from KNA1 | AI51: taxjurisdiction | AK51: 31
A52: 48 | B52: IS_RDS | C52: Material | D52: Logistics | E52: Material Master | F52: Plant Data for Material | G52: ForeignTradeExport | J52: =VLOOKUP(V52,Table_to_BRG!A:D,3,FALSE) -> Plant data | K52: =VLOOKUP(V52,Table_to_BRG!A:D,2,FALSE) -> Plant | P52: ZB_G13_MATL_CommodityorImportCodeRef | Q52: =UPPER(LEFT(Table362[[#This Row],[Entity]],3))&RIGHT("00"&Table362[[#This Row],[Rule '# by Entity]],3)&"0_"&MID(SUBSTITUTE(Table362[[#This Row],[Rule Name]],"_","|",3),SEARCH("|",SUBSTITUTE(Table362[[#This Row],[Rule Name]],"_","|",3))+1,LEN(Table362[[#This Row],[Rule Name]])) -> MAT0630_CommodityorImportCodeRef | R52: Verify the commodity / import code value exists in reference table T604. | S52: Consistency | U52: $P_I_CommImportCode | V52: MARC | W52: STAWN | X52: Commodity Code/Import Code number for foreign trade | Y52: T604 | Z52: STAWN | AA52: ="BEGIN RETURN exists('DS_IS_RDS', '"&Table362[[#This Row],[Lookup Table]]&"', '"&Table362[[#This Row],[Lookup Field]]&"', "&Table362[[#This Row],[IS Parameter]]&"); END" -> BEGIN RETURN exists('DS_IS_RDS', 'T604', 'STAWN', $P_I_CommImportCode); END | AB52: =Table362[[#This Row],[IS Parameter]]&" IS NOT NULL AND rtrim("&Table362[[#This Row],[IS Parameter]]&", ' ') != ''" -> $P_I_CommImportCode IS NOT NULL AND rtrim($P_I_CommImportCode, ' ') != '' | AC52: QUAC.checkValueExists('{$lookuptabname}','{$lookupfieldname}') | AE52: =IF(Table362[[#This Row],[Entity]]="Customer","KUNNR",IF(Table362[[#This Row],[Entity]]="Vendor","LIFNR","MATNR"))&",WERKS"&","&Table362[[#This Row],[Field]] -> MATNR,WERKS,STAWN | AF52: ="VW_"&Table362[[#This Row],[New Rule Name]] -> VW_MAT0630_CommodityorImportCodeRef | AG52: ="create view "&Table362[[#This Row],[View Name]]&" ( "&IF(Table362[[#This Row],[Entity]]="Customer","KUNNR",IF(Table362[[#This Row],[Entity]]="Vendor","LIFNR","MATNR"))&", WERKS, "&Table362[[#This Row],[Field]]&" ) as select "&IF(Table362[[#This Row],[Entity]]="Customer","KUNNR",IF(Table362[[#This Row],[Entity]]="Vendor","LIFNR","MATNR"))&", WERKS, "&Table362[[#This Row],[Field]]&" from "&Table362[[#This Row],[Table]] -> create view VW_MAT0630_CommodityorImportCodeRef ( MATNR, WERKS, STAWN ) as select MATNR, WERKS, STAWN from MARC | AK52: 63
A53: 49 | B53: IS_RDS | C53: Vendor | D53: Finance | E53: Financial Accounting | F53: Vendor Master (General Section) | G53: CompanyCodeData | H53: PaymentTransactions | J53: =VLOOKUP(V53,Table_to_BRG!A:D,3,FALSE) -> General data | K53: =VLOOKUP(V53,Table_to_BRG!A:D,2,FALSE) -> General | P53: ZB_G15_VNDR_GroupingKeyRef | Q53: =UPPER(LEFT(Table362[[#This Row],[Entity]],3))&RIGHT("00"&Table362[[#This Row],[Rule '# by Entity]],3)&"0_"&MID(SUBSTITUTE(Table362[[#This Row],[Rule Name]],"_","|",3),SEARCH("|",SUBSTITUTE(Table362[[#This Row],[Rule Name]],"_","|",3))+1,LEN(Table362[[#This Row],[Rule Name]])) -> VEN0160_GroupingKeyRef | R53: Verify the vendor group key value exists in the Grouping Rules for Automatic Payments table. | S53: Consistency | U53: $P_I_GroupingKey | V53: LFA1 | W53: KONZS | X53: Group key | Y53: TZGR | Z53: ZGRUP | AA53: ="BEGIN RETURN exists('DS_IS_RDS', '"&Table362[[#This Row],[Lookup Table]]&"', '"&Table362[[#This Row],[Lookup Field]]&"', "&Table362[[#This Row],[IS Parameter]]&"); END" -> BEGIN RETURN exists('DS_IS_RDS', 'TZGR', 'ZGRUP', $P_I_GroupingKey); END | AC53: QUAC.checkValueExists('{$lookuptabname}','{$lookupfieldname}') | AE53: =IF(Table362[[#This Row],[Entity]]="Customer","KUNNR",IF(Table362[[#This Row],[Entity]]="Vendor","LIFNR","MATNR"))&","&Table362[[#This Row],[Field]] -> LIFNR,KONZS | AF53: ="VW_"&Table362[[#This Row],[New Rule Name]] -> VW_VEN0160_GroupingKeyRef | AG53: ="create view "&Table362[[#This Row],[View Name]]&" as select "&IF(Table362[[#This Row],[Entity]]="Customer","KUNNR",IF(Table362[[#This Row],[Entity]]="Vendor","LIFNR","MATNR"))&", "&Table362[[#This Row],[Field]]&" from "&Table362[[#This Row],[Table]] -> create view VW_VEN0160_GroupingKeyRef as select LIFNR, KONZS from LFA1 | AI53: grpkey49v | AK53: 16
A54: 50 | B54: IS_RDS | C54: Customer | D54: SalesAndDistribution | E54: Basic Functions | F54: Customer Master: Legal Control - Sanctioned Party List | G54: LegalControl | H54: ExportData | I54: Boycott | J54: =VLOOKUP(V54,Table_to_BRG!A:D,3,FALSE) -> Legal control data | K54: =VLOOKUP(V54,Table_to_BRG!A:D,2,FALSE) -> Legal Control - Sanctioned Party List | P54: ZB_G14_CUST_BoycottDHRListIsValid | Q54: =UPPER(LEFT(Table362[[#This Row],[Entity]],3))&RIGHT("00"&Table362[[#This Row],[Rule '# by Entity]],3)&"0_"&MID(SUBSTITUTE(Table362[[#This Row],[Rule Name]],"_","|",3),SEARCH("|",SUBSTITUTE(Table362[[#This Row],[Rule Name]],"_","|",3))+1,LEN(Table362[[#This Row],[Rule Name]])) -> CUS0710_BoycottDHRListIsValid | R54: Verify the DHR boycott list value is valid according to the appropriate reference domain or value range. | S54: Accuracy | T54: Consistency | U54: $P_I_BoycottList | V54: KNEX | W54: DHRCO | X54: DHR boycott list for export control | AA54: BEGIN RETURN $P_I_BoycottList = 'X'; END | AB54: =Table362[[#This Row],[IS Parameter]]&" IS NOT NULL AND "& Table362[[#This Row],[IS Parameter]]&" != ''" -> $P_I_BoycottList IS NOT NULL AND $P_I_BoycottList != '' | AC54: QUAC.checkValueIsDomainFixedValue() | AE54: =IF(Table362[[#This Row],[Entity]]="Customer","KUNNR",IF(Table362[[#This Row],[Entity]]="Vendor","LIFNR","MATNR"))&",LNDEX,"&Table362[[#This Row],[Field]] -> KUNNR,LNDEX,DHRCO | AF54: ="VW_"&Table362[[#This Row],[New Rule Name]] -> VW_CUS0710_BoycottDHRListIsValid | AG54: ="create view "&Table362[[#This Row],[View Name]]&" as select "&IF(Table362[[#This Row],[Entity]]="Customer","KUNNR",IF(Table362[[#This Row],[Entity]]="Vendor","LIFNR","MATNR"))&", LNDEX, "&Table362[[#This Row],[Field]]&" from "&Table362[[#This Row],[Table]] -> create view VW_CUS0710_BoycottDHRListIsValid as select KUNNR, LNDEX, DHRCO from KNEX | AH54: ="Rule "&Table362[[#This Row],[Rule '#]]&" evaluates DHR boycott list Rule "&A58&" evaluates SDN boycott list Rule "&A68&" evaluates TDO boycott list" -> Rule 50 evaluates DHR boycott list Rule 53 evaluates SDN boycott list Rule 66 evaluates TDO boycott list | AI54: expctrl83c | AK54: 71
A55: 50 | B55: IS_RDS | C55: Material | D55: Logistics | E55: Material Master | F55: Plant Data for Material | G55: MatlReqPlanning | H55: MRP4 | J55: =VLOOKUP(V55,Table_to_BRG!A:D,3,FALSE) -> Storage location | K55: =VLOOKUP(V55,Table_to_BRG!A:D,2,FALSE) -> Storage Location | P55: ZB_G13_MATL_SlocMRPIndicatorIsValid | Q55: =UPPER(LEFT(Table362[[#This Row],[Entity]],3))&RIGHT("00"&Table362[[#This Row],[Rule '# by Entity]],3)&"0_"&MID(SUBSTITUTE(Table362[[#This Row],[Rule Name]],"_","|",3),SEARCH("|",SUBSTITUTE(Table362[[#This Row],[Rule Name]],"_","|",3))+1,LEN(Table362[[#This Row],[Rule Name]])) -> MAT0990_SlocMRPIndicatorIsValid | R55: Verify the storage location MRP indicator value for a Material is valid according to the appropriate reference domain or value range. | S55: Accuracy | T55: Consistency | U55: $P_I_StorageLocMRPInd | V55: MARD | W55: DISKX | X55: Storage location MRP indicator | AA55: BEGIN RETURN $P_I_StorageLocMRP_ind IN ('1', '2'); END | AB55: =Table362[[#This Row],[IS Parameter]]&" IS NOT NULL AND rtrim("&Table362[[#This Row],[IS Parameter]]&", ' ') != ''" -> $P_I_StorageLocMRPInd IS NOT NULL AND rtrim($P_I_StorageLocMRPInd, ' ') != '' | AC55: QUAC.checkValueIsEmpty_OrOneOf(['1'],['2']) | AE55: =IF(Table362[[#This Row],[Entity]]="Customer","KUNNR",IF(Table362[[#This Row],[Entity]]="Vendor","LIFNR","MATNR"))&",WERKS"&","&Table362[[#This Row],[Field]] -> MATNR,WERKS,DISKX | AF55: ="VW_"&Table362[[#This Row],[New Rule Name]] -> VW_MAT0990_SlocMRPIndicatorIsValid | AG55: ="create view "&Table362[[#This Row],[View Name]]&" as select "&IF(Table362[[#This Row],[Entity]]="Customer","KUNNR",IF(Table362[[#This Row],[Entity]]="Vendor","LIFNR","MATNR"))&", WERKS, "&Table362[[#This Row],[Field]]&" from "&Table362[[#This Row],[Table]] -> create view VW_MAT0990_SlocMRPIndicatorIsValid as select MATNR, WERKS, DISKX from MARD | AK55: 99
A56: 51 | B56: IS_RDS | C56: Customer | D56: Logistics | E56: Customer Master | F56: Customer Master Sales Data | G56: SalesAreaData | H56: Sales | J56: =VLOOKUP(V56,Table_to_BRG!A:D,3,FALSE) -> Customer sales data | K56: =VLOOKUP(V56,Table_to_BRG!A:D,2,FALSE) -> Sales | P56: ZB_G14_CUST_PricingProcedurePopulated | Q56: =UPPER(LEFT(Table362[[#This Row],[Entity]],3))&RIGHT("00"&Table362[[#This Row],[Rule '# by Entity]],3)&"0_"&MID(SUBSTITUTE(Table362[[#This Row],[Rule Name]],"_","|",3),SEARCH("|",SUBSTITUTE(Table362[[#This Row],[Rule Name]],"_","|",3))+1,LEN(Table362[[#This Row],[Rule Name]])) -> CUS0940_PricingProcedurePopulated | R56: Verify the pricing procedure field is not empty. | S56: Completeness | U56: $P_I_PricingProcedure | V56: KNVV | W56: KALKS | X56: Pricing procedure assigned to this customer | AA56: BEGIN RETURN $P_I_PricingProcedure IS NOT NULL AND $P_I_PricingProcedure != ''; END | AC56: QUAC.checkValueIsNotEmpty() | AE56: KUNNR,VKORG,VTWEG,SPART,KALKS | AF56: ="VW_"&Table362[[#This Row],[New Rule Name]] -> VW_CUS0940_PricingProcedurePopulated | AG56: ="create view "&Table362[[#This Row],[View Name]]&" as select "&IF(Table362[[#This Row],[Entity]]="Customer","KUNNR",IF(Table362[[#This Row],[Entity]]="Vendor","LIFNR","MATNR"))&", VKORG, VTWEG, SPART, "&Table362[[#This Row],[Field]]&" from "&Table362[[#This Row],[Table]] -> create view VW_CUS0940_PricingProcedurePopulated as select KUNNR, VKORG, VTWEG, SPART, KALKS from KNVV | AK56: 94
A57: 52 | B57: IS_RDS | C57: Material | D57: Logistics | E57: Material Master | F57: Plant Data for Material | G57: Purchasing | J57: =VLOOKUP(V57,Table_to_BRG!A:D,3,FALSE) -> Plant data | K57: =VLOOKUP(V57,Table_to_BRG!A:D,2,FALSE) -> Plant | P57: ZB_G13_MATL_MaterialFreightGroupRef | Q57: =UPPER(LEFT(Table362[[#This Row],[Entity]],3))&RIGHT("00"&Table362[[#This Row],[Rule '# by Entity]],3)&"0_"&MID(SUBSTITUTE(Table362[[#This Row],[Rule Name]],"_","|",3),SEARCH("|",SUBSTITUTE(Table362[[#This Row],[Rule Name]],"_","|",3))+1,LEN(Table362[[#This Row],[Rule Name]])) -> MAT0870_MaterialFreightGroupRef | R57: Verify the material freight group value exists in the Material Freight Groups table. | S57: Consistency | U57: $P_I_FreightGroup | V57: MARC | W57: MFRGR | X57: Material freight group | Y57: TMFG | Z57: MFRGR | AA57: ="BEGIN RETURN exists('DS_IS_RDS', '"&Table362[[#This Row],[Lookup Table]]&"', '"&Table362[[#This Row],[Lookup Field]]&"', "&Table362[[#This Row],[IS Parameter]]&"); END" -> BEGIN RETURN exists('DS_IS_RDS', 'TMFG', 'MFRGR', $P_I_FreightGroup); END | AB57: =Table362[[#This Row],[IS Parameter]]&" IS NOT NULL AND rtrim("&Table362[[#This Row],[IS Parameter]]&", ' ') != ''" -> $P_I_FreightGroup IS NOT NULL AND rtrim($P_I_FreightGroup, ' ') != '' | AC57: QUAC.checkValueExists('{$lookuptabname}','{$lookupfieldname}') | AE57: =IF(Table362[[#This Row],[Entity]]="Customer","KUNNR",IF(Table362[[#This Row],[Entity]]="Vendor","LIFNR","MATNR"))&",WERKS"&","&Table362[[#This Row],[Field]] -> MATNR,WERKS,MFRGR | AF57: ="VW_"&Table362[[#This Row],[New Rule Name]] -> VW_MAT0870_MaterialFreightGroupRef | AG57: ="create view "&Table362[[#This Row],[View Name]]&" ( "&IF(Table362[[#This Row],[Entity]]="Customer","KUNNR",IF(Table362[[#This Row],[Entity]]="Vendor","LIFNR","MATNR"))&", WERKS, "&Table362[[#This Row],[Field]]&" ) as select "&IF(Table362[[#This Row],[Entity]]="Customer","KUNNR",IF(Table362[[#This Row],[Entity]]="Vendor","LIFNR","MATNR"))&", WERKS, "&Table362[[#This Row],[Field]]&" from "&Table362[[#This Row],[Table]] -> create view VW_MAT0870_MaterialFreightGroupRef ( MATNR, WERKS, MFRGR ) as select MATNR, WERKS, MFRGR from MARC | AK57: 87
A58: 53 | B58: IS_RDS | C58: Vendor | D58: Finance | E58: Financial Accounting | F58: Vendor Master (General Section) | G58: GeneralData | H58: Address | I58: Address | J58: =VLOOKUP(V58,Table_to_BRG!A:D,3,FALSE) -> General data | K58: =VLOOKUP(V58,Table_to_BRG!A:D,2,FALSE) -> General | P58: ZB_G15_VNDR_CountryKeyRef | Q58: =UPPER(LEFT(Table362[[#This Row],[Entity]],3))&RIGHT("00"&Table362[[#This Row],[Rule '# by Entity]],3)&"0_"&MID(SUBSTITUTE(Table362[[#This Row],[Rule Name]],"_","|",3),SEARCH("|",SUBSTITUTE(Table362[[#This Row],[Rule Name]],"_","|",3))+1,LEN(Table362[[#This Row],[Rule Name]])) -> VEN0030_CountryKeyRef | R58: Verify the vendor country key value exists in the Countries table. | S58: Consistency | U58: $P_I_Country | V58: LFA1 | W58: LAND1 | X58: Country Key | Y58: T005 | Z58: LAND1 | AA58: ="BEGIN RETURN exists('DS_IS_RDS', '"&Table362[[#This Row],[Lookup Table]]&"', '"&Table362[[#This Row],[Lookup Field]]&"', "&Table362[[#This Row],[IS Parameter]]&"); END" -> BEGIN RETURN exists('DS_IS_RDS', 'T005', 'LAND1', $P_I_Country); END | AC58: QUAC.checkValueExists('{$lookuptabname}','{$lookupfieldname}') | AE58: =IF(Table362[[#This Row],[Entity]]="Customer","KUNNR",IF(Table362[[#This Row],[Entity]]="Vendor","LIFNR","MATNR"))&","&Table362[[#This Row],[Field]] -> LIFNR,LAND1 | AF58: ="VW_"&Table362[[#This Row],[New Rule Name]] -> VW_VEN0030_CountryKeyRef | AG58: ="create view "&Table362[[#This Row],[View Name]]&" as select "&IF(Table362[[#This Row],[Entity]]="Customer","KUNNR",IF(Table362[[#This Row],[Entity]]="Vendor","LIFNR","MATNR"))&", "&Table362[[#This Row],[Field]]&" from "&Table362[[#This Row],[Table]] -> create view VW_VEN0030_CountryKeyRef as select LIFNR, LAND1 from LFA1 | AK58: 3
A59: 54 | B59: IS_RDS | C59: Customer | D59: SalesAndDistribution | E59: Basic Functions | F59: Customer Master: Legal Control - Sanctioned Party List | G59: GeneralData | H59: ExportData | I59: Boycott | J59: =VLOOKUP(V59,Table_to_BRG!A:D,3,FALSE) -> Legal control data | K59: =VLOOKUP(V59,Table_to_BRG!A:D,2,FALSE) -> Legal Control - Sanctioned Party List | P59: ZB_G14_CUST_BoycottSDNListIsValid | Q59: =UPPER(LEFT(Table362[[#This Row],[Entity]],3))&RIGHT("00"&Table362[[#This Row],[Rule '# by Entity]],3)&"0_"&MID(SUBSTITUTE(Table362[[#This Row],[Rule Name]],"_","|",3),SEARCH("|",SUBSTITUTE(Table362[[#This Row],[Rule Name]],"_","|",3))+1,LEN(Table362[[#This Row],[Rule Name]])) -> CUS0700_BoycottSDNListIsValid | R59: Verify the SDN boycott list value is valid according to the appropriate reference domain or value range. | S59: Accuracy | T59: Consistency | U59: $P_I_BoycottList | V59: KNEX | W59: SDNCO | X59: SDN boycott list for export control | AA59: BEGIN RETURN $P_I_BoycottList = 'X'; END | AB59: =Table362[[#This Row],[IS Parameter]]&" IS NOT NULL AND "& Table362[[#This Row],[IS Parameter]]&" != ''" -> $P_I_BoycottList IS NOT NULL AND $P_I_BoycottList != '' | AC59: QUAC.checkValueIsDomainFixedValue() | AE59: =IF(Table362[[#This Row],[Entity]]="Customer","KUNNR",IF(Table362[[#This Row],[Entity]]="Vendor","LIFNR","MATNR"))&",LNDEX,"&Table362[[#This Row],[Field]] -> KUNNR,LNDEX,SDNCO | AF59: ="VW_"&Table362[[#This Row],[New Rule Name]] -> VW_CUS0700_BoycottSDNListIsValid | AG59: ="create view "&Table362[[#This Row],[View Name]]&" as select "&IF(Table362[[#This Row],[Entity]]="Customer","KUNNR",IF(Table362[[#This Row],[Entity]]="Vendor","LIFNR","MATNR"))&", LNDEX, "&Table362[[#This Row],[Field]]&" from "&Table362[[#This Row],[Table]] -> create view VW_CUS0700_BoycottSDNListIsValid as select KUNNR, LNDEX, SDNCO from KNEX | AH59: ="Rule "&Table362[[#This Row],[Rule '#]]&" evaluates Customer boycott list Rule "&A63&" evaluates SDN boycott list Rule "&A73&" evaluates TDO boycott list" -> Rule 54 evaluates Customer boycott list Rule 57 evaluates SDN boycott list Rule 65 evaluates TDO boycott list | AI59: expctrl83v | AK59: 70
A60: 54 | B60: IS_RDS | C60: Material | D60: Logistics | E60: Material Master | F60: Plant Data for Material | G60: MatlReqPlanning | H60: MRP2 | J60: =VLOOKUP(V60,Table_to_BRG!A:D,3,FALSE) -> Plant data | K60: =VLOOKUP(V60,Table_to_BRG!A:D,2,FALSE) -> Plant | P60: ZB_G13_MATL_SafetyTimeIndicatorIsValid | Q60: =UPPER(LEFT(Table362[[#This Row],[Entity]],3))&RIGHT("00"&Table362[[#This Row],[Rule '# by Entity]],3)&"0_"&MID(SUBSTITUTE(Table362[[#This Row],[Rule Name]],"_","|",3),SEARCH("|",SUBSTITUTE(Table362[[#This Row],[Rule Name]],"_","|",3))+1,LEN(Table362[[#This Row],[Rule Name]])) -> MAT0830_SafetyTimeIndicatorIsValid | R60: Verify the safety time indicator value is valid according to the appropriate reference domain or value range. | S60: Accuracy | T60: Consistency | U60: $P_I_SafetyTimeInd | V60: MARC | W60: SHFLG | X60: Safety time indicator (with or without safety time) | AA60: BEGIN RETURN $P_I_SafetyTimeInd IN ('1','2'); END | AB60: =Table362[[#This Row],[IS Parameter]]&" IS NOT NULL AND rtrim("&Table362[[#This Row],[IS Parameter]]&", ' ') != ''" -> $P_I_SafetyTimeInd IS NOT NULL AND rtrim($P_I_SafetyTimeInd, ' ') != '' | AC60: QUAC.checkValueIsDomainFixedValue() | AE60: =IF(Table362[[#This Row],[Entity]]="Customer","KUNNR",IF(Table362[[#This Row],[Entity]]="Vendor","LIFNR","MATNR"))&",WERKS"&","&Table362[[#This Row],[Field]] -> MATNR,WERKS,SHFLG | AF60: ="VW_"&Table362[[#This Row],[New Rule Name]] -> VW_MAT0830_SafetyTimeIndicatorIsValid | AG60: ="create view "&Table362[[#This Row],[View Name]]&" ( "&IF(Table362[[#This Row],[Entity]]="Customer","KUNNR",IF(Table362[[#This Row],[Entity]]="Vendor","LIFNR","MATNR"))&", WERKS, "&Table362[[#This Row],[Field]]&" ) as select "&IF(Table362[[#This Row],[Entity]]="Customer","KUNNR",IF(Table362[[#This Row],[Entity]]="Vendor","LIFNR","MATNR"))&", WERKS, "&Table362[[#This Row],[Field]]&" from "&Table362[[#This Row],[Table]] -> create view VW_MAT0830_SafetyTimeIndicatorIsValid ( MATNR, WERKS, SHFLG ) as select MATNR, WERKS, SHFLG from MARC | AK60: 83
A61: 55 | B61: IS_RDS | C61: Customer | D61: Finance | E61: Financial Accounting | F61: Customer Master (Company Code) | G61: CompanyCodeData | H61: PaymentTransactions | J61: =VLOOKUP(V61,Table_to_BRG!A:D,3,FALSE) -> Company Code data | K61: =VLOOKUP(V61,Table_to_BRG!A:D,2,FALSE) -> Company Code | P61: ZB_G14_CUST_TermsOfPaymentRef | Q61: =UPPER(LEFT(Table362[[#This Row],[Entity]],3))&RIGHT("00"&Table362[[#This Row],[Rule '# by Entity]],3)&"0_"&MID(SUBSTITUTE(Table362[[#This Row],[Rule Name]],"_","|",3),SEARCH("|",SUBSTITUTE(Table362[[#This Row],[Rule Name]],"_","|",3))+1,LEN(Table362[[#This Row],[Rule Name]])) -> CUS0460_TermsOfPaymentRef | R61: Verify the customer terms of payment key value exists in the Terms of Payment table. | S61: Consistency | U61: $P_I_TermsOfPayment | V61: KNB1 | W61: ZTERM | X61: Terms of Payment Key | Y61: T052 | Z61: ZTERM | AA61: ="BEGIN RETURN exists('DS_IS_RDS', '"&Table362[[#This Row],[Lookup Table]]&"', '"&Table362[[#This Row],[Lookup Field]]&"', "&Table362[[#This Row],[IS Parameter]]&"); END" -> BEGIN RETURN exists('DS_IS_RDS', 'T052', 'ZTERM', $P_I_TermsOfPayment); END | AB61: =Table362[[#This Row],[IS Parameter]]&" IS NOT NULL AND "& Table362[[#This Row],[IS Parameter]]&" != ''" -> $P_I_TermsOfPayment IS NOT NULL AND $P_I_TermsOfPayment != '' | AC61: QUAC.checkValueExists('{$lookuptabname}','{$lookupfieldname}') | AE61: =IF(Table362[[#This Row],[Entity]]="Customer","KUNNR",IF(Table362[[#This Row],[Entity]]="Vendor","LIFNR","MATNR"))&",BUKRS"&","&Table362[[#This Row],[Field]] -> KUNNR,BUKRS,ZTERM | AF61: ="VW_"&Table362[[#This Row],[New Rule Name]] -> VW_CUS0460_TermsOfPaymentRef | AG61: ="create view "&Table362[[#This Row],[View Name]]&" as select "&IF(Table362[[#This Row],[Entity]]="Customer","KUNNR",IF(Table362[[#This Row],[Entity]]="Vendor","LIFNR","MATNR"))&", BUKRS, "&Table362[[#This Row],[Field]]&" from "&Table362[[#This Row],[Table]] -> create view VW_CUS0460_TermsOfPaymentRef as select KUNNR, BUKRS, ZTERM from KNB1 | AI61: top01c | AK61: 46
A62: 56 | B62: IS_RDS | C62: Material | D62: Logistics | E62: Material Master | F62: Sales Data for Material | G62: SalesOrg2 | J62: =VLOOKUP(V62,Table_to_BRG!A:D,3,FALSE) -> Sales data | K62: =VLOOKUP(V62,Table_to_BRG!A:D,2,FALSE) -> Sales | P62: ZB_G13_MATL_MaterialGroup3Ref | Q62: =UPPER(LEFT(Table362[[#This Row],[Entity]],3))&RIGHT("00"&Table362[[#This Row],[Rule '# by Entity]],3)&"0_"&MID(SUBSTITUTE(Table362[[#This Row],[Rule Name]],"_","|",3),SEARCH("|",SUBSTITUTE(Table362[[#This Row],[Rule Name]],"_","|",3))+1,LEN(Table362[[#This Row],[Rule Name]])) -> MAT1340_MaterialGroup3Ref | R62: Verify the material group 3 value exists in the Material Pricing Group 3 table. | S62: Consistency | U62: $P_I_MatGroup3 | V62: MVKE | W62: MVGR3 | X62: Material group 3 | Y62: TVM3 | Z62: MVGR3 | AA62: ="BEGIN RETURN exists('DS_IS_RDS', '"&Table362[[#This Row],[Lookup Table]]&"', '"&Table362[[#This Row],[Lookup Field]]&"', "&Table362[[#This Row],[IS Parameter]]&"); END" -> BEGIN RETURN exists('DS_IS_RDS', 'TVM3', 'MVGR3', $P_I_MatGroup3); END | AB62: =Table362[[#This Row],[IS Parameter]]&" IS NOT NULL AND rtrim("&Table362[[#This Row],[IS Parameter]]&", ' ') != ''" -> $P_I_MatGroup3 IS NOT NULL AND rtrim($P_I_MatGroup3, ' ') != '' | AC62: QUAC.checkValueExists('{$lookuptabname}','{$lookupfieldname}') | AE62: =IF(Table362[[#This Row],[Entity]]="Customer","KUNNR",IF(Table362[[#This Row],[Entity]]="Vendor","LIFNR","MATNR"))&",VKORG,VTWEG,"&Table362[[#This Row],[Field]] -> MATNR,VKORG,VTWEG,MVGR3 | AF62: ="VW_"&Table362[[#This Row],[New Rule Name]] -> VW_MAT1340_MaterialGroup3Ref | AG62: ="create view "&Table362[[#This Row],[View Name]]&" as select "&IF(Table362[[#This Row],[Entity]]="Customer","KUNNR",IF(Table362[[#This Row],[Entity]]="Vendor","LIFNR","MATNR"))&", VKORG, VTWEG, "&Table362[[#This Row],[Field]]&" from "&Table362[[#This Row],[Table]] -> create view VW_MAT1340_MaterialGroup3Ref as select MATNR, VKORG, VTWEG, MVGR3 from MVKE | AI62: matgrp03 | AK62: 134
A63: 57 | B63: IS_RDS | C63: Customer | D63: Logistics | E63: Customer Master | F63: General Data in Customer Master | G63: GeneralData | H63: PaymentTransactions | J63: =VLOOKUP(V63,Table_to_BRG!A:D,3,FALSE) -> Company Code data | K63: =VLOOKUP(V63,Table_to_BRG!A:D,2,FALSE) -> Company Code | P63: ZB_G14_CUST_NextPayeeRef | Q63: =UPPER(LEFT(Table362[[#This Row],[Entity]],3))&RIGHT("00"&Table362[[#This Row],[Rule '# by Entity]],3)&"0_"&MID(SUBSTITUTE(Table362[[#This Row],[Rule Name]],"_","|",3),SEARCH("|",SUBSTITUTE(Table362[[#This Row],[Rule Name]],"_","|",3))+1,LEN(Table362[[#This Row],[Rule Name]])) -> CUS0530_NextPayeeRef | R63: Verify the customer next payee value has a corresponding customer number in the General Data in Customer Master table. | S63: Completeness | T63: Consistency | U63: $P_I_NextPayee | V63: KNB1 | W63: REMIT | X63: Account number of an alternative payer | Y63: KNA1 | Z63: KUNNR | AA63: ="BEGIN RETURN exists('DS_IS_RDS', '"&Table362[[#This Row],[Lookup Table]]&"', '"&Table362[[#This Row],[Lookup Field]]&"', "&Table362[[#This Row],[IS Parameter]]&"); END" -> BEGIN RETURN exists('DS_IS_RDS', 'KNA1', 'KUNNR', $P_I_NextPayee); END | AB63: =Table362[[#This Row],[IS Parameter]]&" IS NOT NULL AND "& Table362[[#This Row],[IS Parameter]]&" != ''" -> $P_I_NextPayee IS NOT NULL AND $P_I_NextPayee != '' | AC63: QUAC.checkValueExists('{$lookuptabname}','{$lookupfieldname}') | AE63: =IF(Table362[[#This Row],[Entity]]="Customer","KUNNR",IF(Table362[[#This Row],[Entity]]="Vendor","LIFNR","MATNR"))&","&Table362[[#This Row],[Field]] -> KUNNR,REMIT | AF63: ="VW_"&Table362[[#This Row],[New Rule Name]] -> VW_CUS0530_NextPayeeRef | AG63: ="create view "&Table362[[#This Row],[View Name]]&" as select "&IF(Table362[[#This Row],[Entity]]="Customer","KUNNR",IF(Table362[[#This Row],[Entity]]="Vendor","LIFNR","MATNR"))&", "&Table362[[#This Row],[Field]]&" from "&Table362[[#This Row],[Table]] -> create view VW_CUS0530_NextPayeeRef as select KUNNR, REMIT from KNB1 | AH63: Use KNB1-KNRZB for alt payee by company code. | AI63: next_payee01c | AK63: 53
A64: 58 | B64: IS_RDS | C64: Vendor | D64: Finance | E64: Financial Accounting | F64: Vendor Master (General Section) | G64: GeneralData | H64: Address | J64: =VLOOKUP(V64,Table_to_BRG!A:D,3,FALSE) -> General data | K64: =VLOOKUP(V64,Table_to_BRG!A:D,2,FALSE) -> General | P64: ZB_G15_VNDR_TransportationZoneRef | Q64: =UPPER(LEFT(Table362[[#This Row],[Entity]],3))&RIGHT("00"&Table362[[#This Row],[Rule '# by Entity]],3)&"0_"&MID(SUBSTITUTE(Table362[[#This Row],[Rule Name]],"_","|",3),SEARCH("|",SUBSTITUTE(Table362[[#This Row],[Rule Name]],"_","|",3))+1,LEN(Table362[[#This Row],[Rule Name]])) -> VEN0280_TransportationZoneRef | R64: Verify the vendor transportation zone value exists in the Customers: Regional Zones table. | S64: Consistency | U64: $P_I_TransportationZone | V64: LFA1 | W64: LZONE | X64: Transportation zone to or from which the goods are delivered | Y64: TZONE | Z64: ZONE1 | AA64: ="BEGIN RETURN exists('DS_IS_RDS', '"&Table362[[#This Row],[Lookup Table]]&"', '"&Table362[[#This Row],[Lookup Field]]&"', "&Table362[[#This Row],[IS Parameter]]&"); END" -> BEGIN RETURN exists('DS_IS_RDS', 'TZONE', 'ZONE1', $P_I_TransportationZone); END | AC64: QUAC.checkValueExists('{$lookuptabname}','{$lookupfieldname}') | AE64: =IF(Table362[[#This Row],[Entity]]="Customer","KUNNR",IF(Table362[[#This Row],[Entity]]="Vendor","LIFNR","MATNR"))&","&Table362[[#This Row],[Field]] -> LIFNR,LZONE | AF64: ="VW_"&Table362[[#This Row],[New Rule Name]] -> VW_VEN0280_TransportationZoneRef | AG64: ="create view "&Table362[[#This Row],[View Name]]&" as select "&IF(Table362[[#This Row],[Entity]]="Customer","KUNNR",IF(Table362[[#This Row],[Entity]]="Vendor","LIFNR","MATNR"))&", "&Table362[[#This Row],[Field]]&" from "&Table362[[#This Row],[Table]] -> create view VW_VEN0280_TransportationZoneRef as select LIFNR, LZONE from LFA1 | AI64: transzone58v | AK64: 28
A65: 59 | B65: IS_RDS | C65: Material | D65: Logistics | E65: Material Master | F65: Sales Data for Material | G65: SalesOrg1 | J65: =VLOOKUP(V65,Table_to_BRG!A:D,3,FALSE) -> Sales data | K65: =VLOOKUP(V65,Table_to_BRG!A:D,2,FALSE) -> Sales | P65: ZB_G13_MATL_SalesOrgPopulated | Q65: =UPPER(LEFT(Table362[[#This Row],[Entity]],3))&RIGHT("00"&Table362[[#This Row],[Rule '# by Entity]],3)&"0_"&MID(SUBSTITUTE(Table362[[#This Row],[Rule Name]],"_","|",3),SEARCH("|",SUBSTITUTE(Table362[[#This Row],[Rule Name]],"_","|",3))+1,LEN(Table362[[#This Row],[Rule Name]])) -> MAT1210_SalesOrgPopulated | R65: Verify the sales organization field is not empty. | S65: Completeness | U65: $P_I_SalesOrg | V65: MVKE | W65: VKORG | X65: Sales organization | AA65: BEGIN RETURN $P_I_SalesOrg IS NOT NULL AND $P_I_SalesOrg != ''; END | AC65: QUAC.checkValueIsNotEmpty() | AE65: =IF(Table362[[#This Row],[Entity]]="Customer","KUNNR",IF(Table362[[#This Row],[Entity]]="Vendor","LIFNR","MATNR"))&","&Table362[[#This Row],[Field]] -> MATNR,VKORG | AF65: ="VW_"&Table362[[#This Row],[New Rule Name]] -> VW_MAT1210_SalesOrgPopulated | AG65: ="create view "&Table362[[#This Row],[View Name]]&" as select "&IF(Table362[[#This Row],[Entity]]="Customer","KUNNR",IF(Table362[[#This Row],[Entity]]="Vendor","LIFNR","MATNR"))&", "&Table362[[#This Row],[Field]]&" from "&Table362[[#This Row],[Table]]&" group by MATNR,VKORG" -> create view VW_MAT1210_SalesOrgPopulated as select MATNR, VKORG from MVKE group by MATNR,VKORG | AI65: salesorg01m | AK65: 121
A66: 60 | B66: IS_RDS | C66: Material | D66: Logistics | E66: Material Master | F66: Plant Data for Material | G66: ForeignTradeExport | I66: Address | J66: =VLOOKUP(V66,Table_to_BRG!A:D,3,FALSE) -> Plant data | K66: =VLOOKUP(V66,Table_to_BRG!A:D,2,FALSE) -> Plant | P66: ZB_G13_MATL_CountryRef | Q66: =UPPER(LEFT(Table362[[#This Row],[Entity]],3))&RIGHT("00"&Table362[[#This Row],[Rule '# by Entity]],3)&"0_"&MID(SUBSTITUTE(Table362[[#This Row],[Rule Name]],"_","|",3),SEARCH("|",SUBSTITUTE(Table362[[#This Row],[Rule Name]],"_","|",3))+1,LEN(Table362[[#This Row],[Rule Name]])) -> MAT0640_CountryRef | R66: Verify the material's country of origin exists in the Countries table. | S66: Consistency | U66: $P_I_Country | V66: MARC | W66: HERKL | X66: Country of origin of the material | Y66: T005 | Z66: LAND1 | AA66: ="BEGIN RETURN exists('DS_IS_RDS', '"&Table362[[#This Row],[Lookup Table]]&"', '"&Table362[[#This Row],[Lookup Field]]&"', "&Table362[[#This Row],[IS Parameter]]&"); END" -> BEGIN RETURN exists('DS_IS_RDS', 'T005', 'LAND1', $P_I_Country); END | AB66: =Table362[[#This Row],[IS Parameter]]&" IS NOT NULL AND rtrim("&Table362[[#This Row],[IS Parameter]]&", ' ') != ''" -> $P_I_Country IS NOT NULL AND rtrim($P_I_Country, ' ') != '' | AC66: QUAC.checkValueExists('{$lookuptabname}','{$lookupfieldname}') | AE66: =IF(Table362[[#This Row],[Entity]]="Customer","KUNNR",IF(Table362[[#This Row],[Entity]]="Vendor","LIFNR","MATNR"))&",WERKS"&","&Table362[[#This Row],[Field]] -> MATNR,WERKS,HERKL | AF66: ="VW_"&Table362[[#This Row],[New Rule Name]] -> VW_MAT0640_CountryRef | AG66: ="create view "&Table362[[#This Row],[View Name]]&" ( "&IF(Table362[[#This Row],[Entity]]="Customer","KUNNR",IF(Table362[[#This Row],[Entity]]="Vendor","LIFNR","MATNR"))&", WERKS, "&Table362[[#This Row],[Field]]&" ) as select "&IF(Table362[[#This Row],[Entity]]="Customer","KUNNR",IF(Table362[[#This Row],[Entity]]="Vendor","LIFNR","MATNR"))&", WERKS, "&Table362[[#This Row],[Field]]&" from "&Table362[[#This Row],[Table]] -> create view VW_MAT0640_CountryRef ( MATNR, WERKS, HERKL ) as select MATNR, WERKS, HERKL from MARC | AI66: addrctry60m | AK66: 64
A67: 61 | B67: IS_RDS | C67: Customer | D67: Basis | E67: Address Management/Business Address | F67: E-Mail Addresses (Business Address Services) | G67: GeneralData | H67: Address | I67: Email | J67: =VLOOKUP(V67,Table_to_BRG!A:D,3,FALSE) -> #N/A | K67: =VLOOKUP(V67,Table_to_BRG!A:D,2,FALSE) -> #N/A | P67: ZB_G14_CUST_EmailAddressPopulated | Q67: =UPPER(LEFT(Table362[[#This Row],[Entity]],3))&RIGHT("00"&Table362[[#This Row],[Rule '# by Entity]],3)&"0_"&MID(SUBSTITUTE(Table362[[#This Row],[Rule Name]],"_","|",3),SEARCH("|",SUBSTITUTE(Table362[[#This Row],[Rule Name]],"_","|",3))+1,LEN(Table362[[#This Row],[Rule Name]])) -> CUS1170_EmailAddressPopulated | R67: Verify the customer e-mail address field is not empty. | S67: Completeness | U67: $P_I_EmailAddress | V67: KNA1, ADR6 | W67: KUNNR,ADDRNUMBER,SMTP_ADDR | X67: Vendor Number Address number Email address | AA67: BEGIN RETURN $P_I_EmailAddress IS NOT NULL AND $P_I_EmailAddress != ''; END | AC67: QUAC.checkValueIsNotEmpty() | AE67: KUNNR,ADRNR,SMTP_ADDR | AF67: ="VW_"&Table362[[#This Row],[New Rule Name]] -> VW_CUS1170_EmailAddressPopulated | AG67: create view VW_KNA1_ADR6 as select t1.KUNNR, t1.ADRNR, t2.SMTP_ADDR from KNA1 t1 inner join ADR6 t2 on t2.ADDRNUMBER = t1.ADRNR | AH67: This rule requires a view that joins KNA1/ADR6 | AI67: email01c | AK67: 117
A68: 66 | B68: IS_RDS | C68: Customer | D68: Logistics | E68: Customer Master | F68: General Data in Customer Master | G68: GeneralData | H68: Phone | I68: Phone | J68: =VLOOKUP(V68,Table_to_BRG!A:D,3,FALSE) -> General data | K68: =VLOOKUP(V68,Table_to_BRG!A:D,2,FALSE) -> General | N68: x | O68: ="Superceded by rule "&A1005 -> Superceded by rule 385 | P68: ZB_G14_CUST_USFaxNumberFormat | R68: Rule to check if a US FAX number is in the valid format | S68: Conformity | U68: $P_I_PhoneNumber | V68: KNA1 | W68: TELFX | X68: Fax number | AA68: BEGIN RETURN match_pattern($P_I_PhoneNumber, '9999999999') OR match_pattern($P_I_PhoneNumber, '999-999-9999') OR match_pattern($P_I_PhoneNumber, '(999)-999-9999') OR match_pattern($P_I_PhoneNumber, '1-999-999-9999') OR match_pattern($P_I_PhoneNumber, '1-(999)-999-9999') OR match_pattern($P_I_PhoneNumber, '19999999999') OR match_pattern($P_I_PhoneNumber, '+1-999-999-9999') OR match_pattern($P_I_PhoneNumber, '+1-(999)-999-9999') OR match_pattern($P_I_PhoneNumber, '+19999999999'); END | AH68: 21 countries use the same phone number system as the US. Nine of those countries are US territoties and posessions: AS, FM, GU, MH, MP, PR, PW, UM, VI match_regex( $P_I_PhoneNumber, ( ^+?(1-?)?([0-9]{3}-?[0-9]{3}-?[0-9]{4}$ ) ), NULL ); | AI68: phoneus02c
A69: 62 | B69: IS_RDS | C69: Material | D69: Logistics | E69: Material Master | F69: Sales Data for Material | G69: SalesOrg2 | J69: =VLOOKUP(V69,Table_to_BRG!A:D,3,FALSE) -> Sales data | K69: =VLOOKUP(V69,Table_to_BRG!A:D,2,FALSE) -> Sales | P69: ZB_G13_MATL_MaterialStatisticsGroupRef | Q69: =UPPER(LEFT(Table362[[#This Row],[Entity]],3))&RIGHT("00"&Table362[[#This Row],[Rule '# by Entity]],3)&"0_"&MID(SUBSTITUTE(Table362[[#This Row],[Rule Name]],"_","|",3),SEARCH("|",SUBSTITUTE(Table362[[#This Row],[Rule Name]],"_","|",3))+1,LEN(Table362[[#This Row],[Rule Name]])) -> MAT1250_MaterialStatisticsGroupRef | R69: Verify the material statistics group value exists in the Material Statistics Group table. | S69: Consistency | U69: $P_I_MatStatsGroups | V69: MVKE | W69: VERSG | X69: Material statistics group | Y69: TVSM | Z69: STGMA | AA69: ="BEGIN RETURN exists('DS_IS_RDS', '"&Table362[[#This Row],[Lookup Table]]&"', '"&Table362[[#This Row],[Lookup Field]]&"', "&Table362[[#This Row],[IS Parameter]]&"); END" -> BEGIN RETURN exists('DS_IS_RDS', 'TVSM', 'STGMA', $P_I_MatStatsGroups); END | AB69: =Table362[[#This Row],[IS Parameter]]&" IS NOT NULL AND rtrim("&Table362[[#This Row],[IS Parameter]]&", ' ') != ''" -> $P_I_MatStatsGroups IS NOT NULL AND rtrim($P_I_MatStatsGroups, ' ') != '' | AC69: QUAC.checkValueExists('{$lookuptabname}','{$lookupfieldname}') | AE69: =IF(Table362[[#This Row],[Entity]]="Customer","KUNNR",IF(Table362[[#This Row],[Entity]]="Vendor","LIFNR","MATNR"))&",VKORG,VTWEG,"&Table362[[#This Row],[Field]] -> MATNR,VKORG,VTWEG,VERSG | AF69: ="VW_"&Table362[[#This Row],[New Rule Name]] -> VW_MAT1250_MaterialStatisticsGroupRef | AG69: ="create view "&Table362[[#This Row],[View Name]]&" as select "&IF(Table362[[#This Row],[Entity]]="Customer","KUNNR",IF(Table362[[#This Row],[Entity]]="Vendor","LIFNR","MATNR"))&", VKORG, VTWEG, "&Table362[[#This Row],[Field]]&" from "&Table362[[#This Row],[Table]] -> create view VW_MAT1250_MaterialStatisticsGroupRef as select MATNR, VKORG, VTWEG, VERSG from MVKE | AK69: 125
A70: 63 | B70: IS_RDS | C70: Customer | D70: Logistics | E70: Customer Master | F70: General Data in Customer Master | G70: GeneralData | H70: Control | I70: Address | J70: =VLOOKUP(V70,Table_to_BRG!A:D,3,FALSE) -> General data | K70: =VLOOKUP(V70,Table_to_BRG!A:D,2,FALSE) -> General | P70: ZB_G14_CUST_CountryCodePopulated | Q70: =UPPER(LEFT(Table362[[#This Row],[Entity]],3))&RIGHT("00"&Table362[[#This Row],[Rule '# by Entity]],3)&"0_"&MID(SUBSTITUTE(Table362[[#This Row],[Rule Name]],"_","|",3),SEARCH("|",SUBSTITUTE(Table362[[#This Row],[Rule Name]],"_","|",3))+1,LEN(Table362[[#This Row],[Rule Name]])) -> CUS0020_CountryCodePopulated | R70: Verify the country code field is not empty. | S70: Completeness | U70: $P_I_CountryCode | V70: KNA1 | W70: LAND1 | X70: Country Code | AA70: BEGIN RETURN $P_I_CountryCode IS NOT NULL AND $P_I_CountryCode != ''; END | AC70: QUAC.checkValueIsNotEmpty() | AE70: =IF(Table362[[#This Row],[Entity]]="Customer","KUNNR",IF(Table362[[#This Row],[Entity]]="Vendor","LIFNR","MATNR"))&","&Table362[[#This Row],[Field]] -> KUNNR,LAND1 | AF70: ="VW_"&Table362[[#This Row],[New Rule Name]] -> VW_CUS0020_CountryCodePopulated | AG70: ="create view "&Table362[[#This Row],[View Name]]&" as select "&Table362[[#This Row],[Table]]&", "&Table362[[#This Row],[Field]]&" from "&Table362[[#This Row],[Table]] -> create view VW_CUS0020_CountryCodePopulated as select KNA1, LAND1 from KNA1 | AI70: addrctrycode01c | AK70: 2
A71: 64 | B71: IS_RDS | C71: Customer | D71: SalesAndDistribution | E71: Basic Functions | F71: Customer Master: Legal Control - Sanctioned Party List | G71: LegalControl | H71: ExportData | I71: Boycott | J71: =VLOOKUP(V71,Table_to_BRG!A:D,3,FALSE) -> Legal control data | K71: =VLOOKUP(V71,Table_to_BRG!A:D,2,FALSE) -> Legal Control - Sanctioned Party List | P71: ZB_G14_CUST_BoycottTDOListIsValid | Q71: =UPPER(LEFT(Table362[[#This Row],[Entity]],3))&RIGHT("00"&Table362[[#This Row],[Rule '# by Entity]],3)&"0_"&MID(SUBSTITUTE(Table362[[#This Row],[Rule Name]],"_","|",3),SEARCH("|",SUBSTITUTE(Table362[[#This Row],[Rule Name]],"_","|",3))+1,LEN(Table362[[#This Row],[Rule Name]])) -> CUS0690_BoycottTDOListIsValid | R71: Verify the TDO boycott list value is valid according to the appropriate reference domain or value range. | S71: Accuracy | T71: Consistency | U71: $P_I_BoycottList | V71: KNEX | W71: TDOCO | X71: TDO boycott list for export control | AA71: BEGIN RETURN $P_I_BoycottList = 'X'; END | AB71: =Table362[[#This Row],[IS Parameter]]&" IS NOT NULL AND "& Table362[[#This Row],[IS Parameter]]&" != ''" -> $P_I_BoycottList IS NOT NULL AND $P_I_BoycottList != '' | AC71: QUAC.checkValueIsDomainFixedValue() | AE71: =IF(Table362[[#This Row],[Entity]]="Customer","KUNNR",IF(Table362[[#This Row],[Entity]]="Vendor","LIFNR","MATNR"))&",LNDEX,"&Table362[[#This Row],[Field]] -> KUNNR,LNDEX,TDOCO | AF71: ="VW_"&Table362[[#This Row],[New Rule Name]] -> VW_CUS0690_BoycottTDOListIsValid | AG71: ="create view "&Table362[[#This Row],[View Name]]&" as select "&IF(Table362[[#This Row],[Entity]]="Customer","KUNNR",IF(Table362[[#This Row],[Entity]]="Vendor","LIFNR","MATNR"))&", LNDEX, "&Table362[[#This Row],[Field]]&" from "&Table362[[#This Row],[Table]] -> create view VW_CUS0690_BoycottTDOListIsValid as select KUNNR, LNDEX, TDOCO from KNEX | AH71: ="Rule "&Table362[[#This Row],[Rule '#]]&" evaluates Customer boycott list Rule "&A75&" evaluates SDN boycott list Rule "&A85&" evaluates TDO boycott list" -> Rule 64 evaluates Customer boycott list Rule 67 evaluates SDN boycott list Rule 78 evaluates TDO boycott list | AI71: expctrl02c | AK71: 69
A72: 64 | B72: IS_RDS | C72: Vendor | D72: Finance | E72: Financial Accounting | F72: Vendor Master (Company Code) | G72: CompanyCodeData | H72: AccountingInformation | J72: =VLOOKUP(V72,Table_to_BRG!A:D,3,FALSE) -> Company Code data | K72: =VLOOKUP(V72,Table_to_BRG!A:D,2,FALSE) -> Company Code | P72: ZB_G15_VNDR_ExcemptionAuthorityIsValid | Q72: =UPPER(LEFT(Table362[[#This Row],[Entity]],3))&RIGHT("00"&Table362[[#This Row],[Rule '# by Entity]],3)&"0_"&MID(SUBSTITUTE(Table362[[#This Row],[Rule Name]],"_","|",3),SEARCH("|",SUBSTITUTE(Table362[[#This Row],[Rule Name]],"_","|",3))+1,LEN(Table362[[#This Row],[Rule Name]])) -> VEN0490_ExcemptionAuthorityIsValid | R72: Verify the exemption authority value is valid according to the appropriate reference domain or value range. | S72: Consistency | U72: $P_I_ExcemptionAuthority | V72: LFB1 | W72: QSBGR | X72: Authority for Exemption from Withholding Tax | AA72: BEGIN RETURN $P_I_ExcemptionAuthority IS NULL OR $P_I_ExcemptionAuthority IN ('0','1', '2', '3','4','5'); END | AC72: QUAC.checkValueIsDomainFixedValue() | AE72: =IF(Table362[[#This Row],[Entity]]="Customer","KUNNR",IF(Table362[[#This Row],[Entity]]="Vendor","LIFNR","MATNR"))&",BUKRS,"&Table362[[#This Row],[Field]] -> LIFNR,BUKRS,QSBGR | AF72: ="VW_"&Table362[[#This Row],[New Rule Name]] -> VW_VEN0490_ExcemptionAuthorityIsValid | AG72: ="create view "&Table362[[#This Row],[View Name]]&" as select "&IF(Table362[[#This Row],[Entity]]="Customer","KUNNR",IF(Table362[[#This Row],[Entity]]="Vendor","LIFNR","MATNR"))&", BUKRS, "&Table362[[#This Row],[Field]]&" from "&Table362[[#This Row],[Table]] -> create view VW_VEN0490_ExcemptionAuthorityIsValid as select LIFNR, BUKRS, QSBGR from LFB1 | AK72: 49
A73: 65 | B73: IS_RDS | C73: Vendor | D73: Finance | E73: Financial Accounting | F73: Vendor Master (Company Code) | G73: CompanyCodeData | H73: AccountingInformation | I73: Tax | J73: =VLOOKUP(V73,Table_to_BRG!A:D,3,FALSE) -> Company Code data | K73: =VLOOKUP(V73,Table_to_BRG!A:D,2,FALSE) -> Company Code | P73: ZB_G15_VNDR_WitholdingTaxRef | Q73: =UPPER(LEFT(Table362[[#This Row],[Entity]],3))&RIGHT("00"&Table362[[#This Row],[Rule '# by Entity]],3)&"0_"&MID(SUBSTITUTE(Table362[[#This Row],[Rule Name]],"_","|",3),SEARCH("|",SUBSTITUTE(Table362[[#This Row],[Rule Name]],"_","|",3))+1,LEN(Table362[[#This Row],[Rule Name]])) -> VEN0460_WitholdingTaxRef | R73: Verify the withholding tax code value exists in the Withholding Tax table. | S73: Consistency | U73: $P_I_WithholdingTaxCode | V73: LFB1 | W73: QSSKZ | X73: Withholding Tax Code | Y73: T059Q | Z73: QSSKZ | AA73: ="BEGIN RETURN exists('DS_IS_RDS', '"&Table362[[#This Row],[Lookup Table]]&"', '"&Table362[[#This Row],[Lookup Field]]&"', "&Table362[[#This Row],[IS Parameter]]&"); END" -> BEGIN RETURN exists('DS_IS_RDS', 'T059Q', 'QSSKZ', $P_I_WithholdingTaxCode); END | AC73: QUAC.checkValueExists('{$lookuptabname}','{$lookupfieldname}') | AE73: =IF(Table362[[#This Row],[Entity]]="Customer","KUNNR",IF(Table362[[#This Row],[Entity]]="Vendor","LIFNR","MATNR"))&",BUKRS,"&Table362[[#This Row],[Field]] -> LIFNR,BUKRS,QSSKZ | AF73: ="VW_"&Table362[[#This Row],[New Rule Name]] -> VW_VEN0460_WitholdingTaxRef | AG73: ="create view "&Table362[[#This Row],[View Name]]&" as select "&IF(Table362[[#This Row],[Entity]]="Customer","KUNNR",IF(Table362[[#This Row],[Entity]]="Vendor","LIFNR","MATNR"))&", BUKRS, "&Table362[[#This Row],[Field]]&" from "&Table362[[#This Row],[Table]] -> create view VW_VEN0460_WitholdingTaxRef as select LIFNR, BUKRS, QSSKZ from LFB1 | AI73: taxwithhold | AK73: 46
A74: 72 | B74: IS_RDS | C74: Customer | G74: SalesAreaData | H74: BillingDocuments | I74: Tax | J74: =VLOOKUP(V74,Table_to_BRG!A:D,3,FALSE) -> #N/A | K74: =VLOOKUP(V74,Table_to_BRG!A:D,2,FALSE) -> #N/A | P74: ZB_G14_CUST_TaxDepartureCountryPopulated | Q74: =UPPER(LEFT(Table362[[#This Row],[Entity]],3))&RIGHT("00"&Table362[[#This Row],[Rule '# by Entity]],3)&"0_"&MID(SUBSTITUTE(Table362[[#This Row],[Rule Name]],"_","|",3),SEARCH("|",SUBSTITUTE(Table362[[#This Row],[Rule Name]],"_","|",3))+1,LEN(Table362[[#This Row],[Rule Name]])) -> CUS1160_TaxDepartureCountryPopulated | R74: Verify the tax departure country is not empty. | S74: Completeness | U74: $P_I_Country | V74: VBRK | W74: LANDTX | X74: Tax departure country | AA74: BEGIN RETURN $P_I_Country IS NOT NULL AND $P_I_Country != ''; END | AC74: QUAC.checkValueIsNotEmpty() | AE74: ="VBELN,"&Table362[[#This Row],[Field]] -> VBELN,LANDTX | AF74: ="VW_"&Table362[[#This Row],[New Rule Name]] -> VW_CUS1160_TaxDepartureCountryPopulated | AH74: How is this referenced from a customer record? | AI74: taxctry | AK74: 116
A75: 67 | B75: IS_RDS | C75: Vendor | D75: Finance | E75: Financial Accounting | F75: Vendor Master (General Section) | G75: GeneralData | H75: PaymentTransactions | J75: =VLOOKUP(V75,Table_to_BRG!A:D,3,FALSE) -> General data | K75: =VLOOKUP(V75,Table_to_BRG!A:D,2,FALSE) -> General | P75: ZB_G15_VNDR_DMEInstructionKeyRef | Q75: =UPPER(LEFT(Table362[[#This Row],[Entity]],3))&RIGHT("00"&Table362[[#This Row],[Rule '# by Entity]],3)&"0_"&MID(SUBSTITUTE(Table362[[#This Row],[Rule Name]],"_","|",3),SEARCH("|",SUBSTITUTE(Table362[[#This Row],[Rule Name]],"_","|",3))+1,LEN(Table362[[#This Row],[Rule Name]])) -> VEN0150_DMEInstructionKeyRef | R75: Verify the DME instruction key value exists in the Instruction Key table. | S75: Consistency | U75: $P_I_InstructionKey | V75: LFA1 | W75: DTAWS | X75: Instruction key for data medium exchange | Y75: T015W | Z75: DTAWS | AA75: ="BEGIN RETURN exists('DS_IS_RDS', '"&Table362[[#This Row],[Lookup Table]]&"', '"&Table362[[#This Row],[Lookup Field]]&"', "&Table362[[#This Row],[IS Parameter]]&"); END" -> BEGIN RETURN exists('DS_IS_RDS', 'T015W', 'DTAWS', $P_I_InstructionKey); END | AC75: QUAC.checkValueExists('{$lookuptabname}','{$lookupfieldname}') | AE75: =IF(Table362[[#This Row],[Entity]]="Customer","KUNNR",IF(Table362[[#This Row],[Entity]]="Vendor","LIFNR","MATNR"))&","&Table362[[#This Row],[Field]] -> LIFNR,DTAWS | AF75: ="VW_"&Table362[[#This Row],[New Rule Name]] -> VW_VEN0150_DMEInstructionKeyRef | AG75: ="create view "&Table362[[#This Row],[View Name]]&" as select "&IF(Table362[[#This Row],[Entity]]="Customer","KUNNR",IF(Table362[[#This Row],[Entity]]="Vendor","LIFNR","MATNR"))&", "&Table362[[#This Row],[Field]]&" from "&Table362[[#This Row],[Table]] -> create view VW_VEN0150_DMEInstructionKeyRef as select LIFNR, DTAWS from LFA1 | AK75: 15
A76: 68 | B76: IS_RDS | C76: Material | D76: Logistics | E76: Material Master | F76: Plant Data for Material | G76: ForeignTradeExport | J76: =VLOOKUP(V76,Table_to_BRG!A:D,3,FALSE) -> Plant data | K76: =VLOOKUP(V76,Table_to_BRG!A:D,2,FALSE) -> Plant | P76: ZB_G13_MATL_RegionRef | Q76: =UPPER(LEFT(Table362[[#This Row],[Entity]],3))&RIGHT("00"&Table362[[#This Row],[Rule '# by Entity]],3)&"0_"&MID(SUBSTITUTE(Table362[[#This Row],[Rule Name]],"_","|",3),SEARCH("|",SUBSTITUTE(Table362[[#This Row],[Rule Name]],"_","|",3))+1,LEN(Table362[[#This Row],[Rule Name]])) -> MAT0650_RegionRef | R76: Verify that material's region (state, province, county) exists in the Tax Region table. | S76: Consistency | U76: $P_I_Region | V76: MARC | W76: HERKR | X76: Region of origin of material (non-preferential origin) | Y76: T005S | Z76: BLAND | AA76: ="BEGIN RETURN exists('DS_IS_RDS', '"&Table362[[#This Row],[Lookup Table]]&"', '"&Table362[[#This Row],[Lookup Field]]&"', "&Table362[[#This Row],[IS Parameter]]&"); END" -> BEGIN RETURN exists('DS_IS_RDS', 'T005S', 'BLAND', $P_I_Region); END | AB76: =Table362[[#This Row],[IS Parameter]]&" IS NOT NULL AND rtrim("&Table362[[#This Row],[IS Parameter]]&", ' ') != ''" -> $P_I_Region IS NOT NULL AND rtrim($P_I_Region, ' ') != '' | AC76: QUAC.checkValueExists('{$lookuptabname}','{$lookupfieldname}') | AE76: =IF(Table362[[#This Row],[Entity]]="Customer","KUNNR",IF(Table362[[#This Row],[Entity]]="Vendor","LIFNR","MATNR"))&",WERKS"&","&Table362[[#This Row],[Field]] -> MATNR,WERKS,HERKR | AF76: ="VW_"&Table362[[#This Row],[New Rule Name]] -> VW_MAT0650_RegionRef | AG76: ="create view "&Table362[[#This Row],[View Name]]&" ( "&IF(Table362[[#This Row],[Entity]]="Customer","KUNNR",IF(Table362[[#This Row],[Entity]]="Vendor","LIFNR","MATNR"))&", WERKS, "&Table362[[#This Row],[Field]]&" ) as select "&IF(Table362[[#This Row],[Entity]]="Customer","KUNNR",IF(Table362[[#This Row],[Entity]]="Vendor","LIFNR","MATNR"))&", WERKS, "&Table362[[#This Row],[Field]]&" from "&Table362[[#This Row],[Table]] -> create view VW_MAT0650_RegionRef ( MATNR, WERKS, HERKR ) as select MATNR, WERKS, HERKR from MARC | AI76: addrregion240m | AK76: 65
A77: 69 | B77: IS_RDS | C77: Customer | D77: Logistics | E77: Customer Master | F77: General Data in Customer Master | G77: GeneralData | H77: Marketing | J77: =VLOOKUP(V77,Table_to_BRG!A:D,3,FALSE) -> General data | K77: =VLOOKUP(V77,Table_to_BRG!A:D,2,FALSE) -> General | P77: ZB_G14_CUST_NielsenIDRef | Q77: =UPPER(LEFT(Table362[[#This Row],[Entity]],3))&RIGHT("00"&Table362[[#This Row],[Rule '# by Entity]],3)&"0_"&MID(SUBSTITUTE(Table362[[#This Row],[Rule Name]],"_","|",3),SEARCH("|",SUBSTITUTE(Table362[[#This Row],[Rule Name]],"_","|",3))+1,LEN(Table362[[#This Row],[Rule Name]])) -> CUS0200_NielsenIDRef | R77: Verify the customer Nielsen ID value exists in the General Data in Customer Master Table. | S77: Completeness | T77: Consistency | U77: $P_I_NielsenID | V77: KNA1 | W77: NIELS | X77: Nielsen ID | Y77: TNLS | Z77: NIELS | AA77: ="BEGIN RETURN exists('DS_IS_RDS', '"&Table362[[#This Row],[Lookup Table]]&"', '"&Table362[[#This Row],[Lookup Field]]&"', "&Table362[[#This Row],[IS Parameter]]&"); END" -> BEGIN RETURN exists('DS_IS_RDS', 'TNLS', 'NIELS', $P_I_NielsenID); END | AB77: =Table362[[#This Row],[IS Parameter]]&" IS NOT NULL AND "& Table362[[#This Row],[IS Parameter]]&" != ''" -> $P_I_NielsenID IS NOT NULL AND $P_I_NielsenID != '' | AC77: QUAC.checkValueExists('{$lookuptabname}','{$lookupfieldname}') | AE77: =IF(Table362[[#This Row],[Entity]]="Customer","KUNNR",IF(Table362[[#This Row],[Entity]]="Vendor","LIFNR","MATNR"))&","&Table362[[#This Row],[Field]] -> KUNNR,NIELS | AF77: ="VW_"&Table362[[#This Row],[New Rule Name]] -> VW_CUS0200_NielsenIDRef | AG77: ="create view "&Table362[[#This Row],[View Name]]&" as select "&IF(Table362[[#This Row],[Entity]]="Customer","KUNNR",IF(Table362[[#This Row],[Entity]]="Vendor","LIFNR","MATNR"))&", "&Table362[[#This Row],[Field]]&" from "&Table362[[#This Row],[Table]] -> create view VW_CUS0200_NielsenIDRef as select KUNNR, NIELS from KNA1 | AK77: 20
A78: 70 | B78: IS_RDS | C78: Material | D78: Logistics | E78: Material Master | F78: Sales Data for Material | G78: SalesOrg2 | J78: =VLOOKUP(V78,Table_to_BRG!A:D,3,FALSE) -> Sales data | K78: =VLOOKUP(V78,Table_to_BRG!A:D,2,FALSE) -> Sales | P78: ZB_G13_MATL_AccountAssignmentGroupRef | Q78: =UPPER(LEFT(Table362[[#This Row],[Entity]],3))&RIGHT("00"&Table362[[#This Row],[Rule '# by Entity]],3)&"0_"&MID(SUBSTITUTE(Table362[[#This Row],[Rule Name]],"_","|",3),SEARCH("|",SUBSTITUTE(Table362[[#This Row],[Rule Name]],"_","|",3))+1,LEN(Table362[[#This Row],[Rule Name]])) -> MAT1310_AccountAssignmentGroupRef | R78: Verify the account assignment group value exists in the Account Assignment Groups table. | S78: Consistency | U78: $P_I_AcctAssgnGroup | V78: MVKE | W78: KTGRM | X78: Account assignment group for this material | Y78: TVKM | Z78: KTGRM | AA78: ="BEGIN RETURN exists('DS_IS_RDS', '"&Table362[[#This Row],[Lookup Table]]&"', '"&Table362[[#This Row],[Lookup Field]]&"', "&Table362[[#This Row],[IS Parameter]]&"); END" -> BEGIN RETURN exists('DS_IS_RDS', 'TVKM', 'KTGRM', $P_I_AcctAssgnGroup); END | AB78: =Table362[[#This Row],[IS Parameter]]&" IS NOT NULL AND rtrim("&Table362[[#This Row],[IS Parameter]]&", ' ') != ''" -> $P_I_AcctAssgnGroup IS NOT NULL AND rtrim($P_I_AcctAssgnGroup, ' ') != '' | AC78: QUAC.checkValueExists('{$lookuptabname}','{$lookupfieldname}') | AE78: =IF(Table362[[#This Row],[Entity]]="Customer","KUNNR",IF(Table362[[#This Row],[Entity]]="Vendor","LIFNR","MATNR"))&",VKORG,VTWEG,"&Table362[[#This Row],[Field]] -> MATNR,VKORG,VTWEG,KTGRM | AF78: ="VW_"&Table362[[#This Row],[New Rule Name]] -> VW_MAT1310_AccountAssignmentGroupRef | AG78: ="create view "&Table362[[#This Row],[View Name]]&" as select "&IF(Table362[[#This Row],[Entity]]="Customer","KUNNR",IF(Table362[[#This Row],[Entity]]="Vendor","LIFNR","MATNR"))&", VKORG, VTWEG, "&Table362[[#This Row],[Field]]&" from "&Table362[[#This Row],[Table]] -> create view VW_MAT1310_AccountAssignmentGroupRef as select MATNR, VKORG, VTWEG, KTGRM from MVKE | AK78: 131
A79: 77 | B79: IS_RDS | C79: Material | D79: Logistics | E79: Material Master | F79: General Material Data | G79: BasicData2 | H79: PlantData | J79: =VLOOKUP(V79,Table_to_BRG!A:D,3,FALSE) -> General data | K79: =VLOOKUP(V79,Table_to_BRG!A:D,2,FALSE) -> General | P79: ZB_G13_MATL_CrossPlantCMRef | Q79: =UPPER(LEFT(Table362[[#This Row],[Entity]],3))&RIGHT("00"&Table362[[#This Row],[Rule '# by Entity]],3)&"0_"&MID(SUBSTITUTE(Table362[[#This Row],[Rule Name]],"_","|",3),SEARCH("|",SUBSTITUTE(Table362[[#This Row],[Rule Name]],"_","|",3))+1,LEN(Table362[[#This Row],[Rule Name]])) -> MAT1370_CrossPlantCMRef | R79: Verify the cross plant CM value exists in the Material Master Data table. | S79: Consistency | U79: $P_I_XPlantCM | V79: MARA | W79: SATNR | X79: Cross-Plant Configurable Material | Y79: MARA | Z79: MATNR | AA79: ="BEGIN RETURN exists('DS_IS_RDS', '"&Table362[[#This Row],[Lookup Table]]&"', '"&Table362[[#This Row],[Lookup Field]]&"', "&Table362[[#This Row],[IS Parameter]]&"); END" -> BEGIN RETURN exists('DS_IS_RDS', 'MARA', 'MATNR', $P_I_XPlantCM); END | AB79: =Table362[[#This Row],[IS Parameter]]&" IS NOT NULL AND rtrim("&Table362[[#This Row],[IS Parameter]]&", ' ') != ''" -> $P_I_XPlantCM IS NOT NULL AND rtrim($P_I_XPlantCM, ' ') != '' | AC79: QUAC.checkValueExists('{$lookuptabname}','{$lookupfieldname}') | AE79: =IF(Table362[[#This Row],[Entity]]="Customer","KUNNR",IF(Table362[[#This Row],[Entity]]="Vendor","LIFNR","MATNR"))&","&Table362[[#This Row],[Field]] -> MATNR,SATNR | AF79: ="VW_"&Table362[[#This Row],[New Rule Name]] -> VW_MAT1370_CrossPlantCMRef | AH79: The specified lookup table is a generated view, which is not valid for lookups. Does does MARA-SATNR have a corresponding lookup table? | AK79: 137
A80: 71 | B80: IS_RDS | C80: Vendor | D80: Finance | E80: Financial Accounting | F80: Vendor Master (Bank Details) | G80: GeneralData | H80: PaymentTransactions | I80: Bank | J80: =VLOOKUP(V80,Table_to_BRG!A:D,3,FALSE) -> Bank data | K80: =VLOOKUP(V80,Table_to_BRG!A:D,2,FALSE) -> Bank details | P80: ZB_G15_VNDR_BankAccountNumberPopulated | Q80: =UPPER(LEFT(Table362[[#This Row],[Entity]],3))&RIGHT("00"&Table362[[#This Row],[Rule '# by Entity]],3)&"0_"&MID(SUBSTITUTE(Table362[[#This Row],[Rule Name]],"_","|",3),SEARCH("|",SUBSTITUTE(Table362[[#This Row],[Rule Name]],"_","|",3))+1,LEN(Table362[[#This Row],[Rule Name]])) -> VEN0560_BankAccountNumberPopulated | R80: Verify the bank account number field is not empty. | S80: Completeness | U80: $P_I_BankAccount | V80: LFBK | W80: BANKN | X80: Bank account number | AA80: BEGIN RETURN $P_I_BankAccount IS NOT NULL AND $P_I_BankAccount != ''; END | AC80: QUAC.checkValueIsNotEmpty() | AE80: =IF(Table362[[#This Row],[Entity]]="Customer","KUNNR",IF(Table362[[#This Row],[Entity]]="Vendor","LIFNR","MATNR"))&",BANKS,BANKL,"&Table362[[#This Row],[Field]] -> LIFNR,BANKS,BANKL,BANKN | AF80: ="VW_"&Table362[[#This Row],[New Rule Name]] -> VW_VEN0560_BankAccountNumberPopulated | AG80: ="create view "&Table362[[#This Row],[View Name]]&" as select "&IF(Table362[[#This Row],[Entity]]="Customer","KUNNR",IF(Table362[[#This Row],[Entity]]="Vendor","LIFNR","MATNR"))&", BANKS, BANKL, "&Table362[[#This Row],[Field]]&" from "&Table362[[#This Row],[Table]] -> create view VW_VEN0560_BankAccountNumberPopulated as select LIFNR, BANKS, BANKL, BANKN from LFBK | AI80: bankacct71v | AK80: 56
A81: 73 | B81: IS_RDS | C81: Customer | D81: Finance | E81: Financial Accounting | F81: Customer Master (Company Code) | G81: CompanyCodeData | H81: PaymentTransactions | J81: =VLOOKUP(V81,Table_to_BRG!A:D,3,FALSE) -> Company Code data | K81: =VLOOKUP(V81,Table_to_BRG!A:D,2,FALSE) -> Company Code | P81: ZB_G14_CUST_TermsOfPaymentKeyPopulated | Q81: =UPPER(LEFT(Table362[[#This Row],[Entity]],3))&RIGHT("00"&Table362[[#This Row],[Rule '# by Entity]],3)&"0_"&MID(SUBSTITUTE(Table362[[#This Row],[Rule Name]],"_","|",3),SEARCH("|",SUBSTITUTE(Table362[[#This Row],[Rule Name]],"_","|",3))+1,LEN(Table362[[#This Row],[Rule Name]])) -> CUS0450_TermsOfPaymentKeyPopulated | R81: Verify the terms of payment key field is not empty. | S81: Completeness | U81: $P_I_TermsOfPayment | V81: KNB1 | W81: ZTERM | X81: Terms of Payment Key | AA81: BEGIN RETURN $P_I_TermsOfPayment IS NOT NULL AND $P_I_TermsOfPayment != ''; END | AC81: QUAC.checkValueIsNotEmpty() | AE81: =IF(Table362[[#This Row],[Entity]]="Customer","KUNNR",IF(Table362[[#This Row],[Entity]]="Vendor","LIFNR","MATNR"))&",BUKRS"&","&Table362[[#This Row],[Field]] -> KUNNR,BUKRS,ZTERM | AF81: ="VW_"&Table362[[#This Row],[New Rule Name]] -> VW_CUS0450_TermsOfPaymentKeyPopulated | AG81: ="create view "&Table362[[#This Row],[View Name]]&" as select "&IF(Table362[[#This Row],[Entity]]="Customer","KUNNR",IF(Table362[[#This Row],[Entity]]="Vendor","LIFNR","MATNR"))&", BUKRS, "&Table362[[#This Row],[Field]]&" from "&Table362[[#This Row],[Table]] -> create view VW_CUS0450_TermsOfPaymentKeyPopulated as select KUNNR, BUKRS, ZTERM from KNB1 | AI81: top02c | AK81: 45
A82: 74 | B82: IS_RDS | C82: Vendor | J82: =VLOOKUP(V82,Table_to_BRG!A:D,3,FALSE) -> Payment advice | K82: =VLOOKUP(V82,Table_to_BRG!A:D,2,FALSE) -> Payment Advice Header | P82: ZB_G15_VNDR_SelectionRuleRef | Q82: =UPPER(LEFT(Table362[[#This Row],[Entity]],3))&RIGHT("00"&Table362[[#This Row],[Rule '# by Entity]],3)&"0_"&MID(SUBSTITUTE(Table362[[#This Row],[Rule Name]],"_","|",3),SEARCH("|",SUBSTITUTE(Table362[[#This Row],[Rule Name]],"_","|",3))+1,LEN(Table362[[#This Row],[Rule Name]])) -> VEN0720_SelectionRuleRef | R82: Verify the vendor selection rule value exists in the Selection Rules for Payment Advices table. | S82: Consistency | U82: $P_I_SelectionRule | V82: AVIK | W82: SREGL | X82: Selection Rule for Payment Advices | Y82: T053A | Z82: SREGL | AA82: ="BEGIN RETURN exists('DS_IS_RDS', '"&Table362[[#This Row],[Lookup Table]]&"', '"&Table362[[#This Row],[Lookup Field]]&"', "&Table362[[#This Row],[IS Parameter]]&"); END" -> BEGIN RETURN exists('DS_IS_RDS', 'T053A', 'SREGL', $P_I_SelectionRule); END | AC82: QUAC.checkValueExists('{$lookuptabname}','{$lookupfieldname}') | AE82: BUKRS,KOART,KONTO,AVSID,SREGL | AF82: ="VW_"&Table362[[#This Row],[New Rule Name]] -> VW_VEN0720_SelectionRuleRef | AG82: ="create view "&Table362[[#This Row],[View Name]]&" as select BUKRS, KOART, KONTO, AVSID, "&Table362[[#This Row],[Field]]&" from "&Table362[[#This Row],[Table]] -> create view VW_VEN0720_SelectionRuleRef as select BUKRS, KOART, KONTO, AVSID, SREGL from AVIK | AI82: selectrule74v | AK82: 72
A83: 75 | B83: IS_RDS | C83: Vendor | D83: Logistics | E83: Vendor Master | F83: Vendor Master Record purchasing organization Data | G83: PurchaseOrgData | J83: =VLOOKUP(V83,Table_to_BRG!A:D,3,FALSE) -> Purchasing data | K83: =VLOOKUP(V83,Table_to_BRG!A:D,2,FALSE) -> Purchasing org. | P83: ZB_G15_VNDR_PriceMarkingAgreedRef | Q83: =UPPER(LEFT(Table362[[#This Row],[Entity]],3))&RIGHT("00"&Table362[[#This Row],[Rule '# by Entity]],3)&"0_"&MID(SUBSTITUTE(Table362[[#This Row],[Rule Name]],"_","|",3),SEARCH("|",SUBSTITUTE(Table362[[#This Row],[Rule Name]],"_","|",3))+1,LEN(Table362[[#This Row],[Rule Name]])) -> VEN0640_PriceMarkingAgreedRef | R83: Verify the price marking agreed value exists in the Price Marking Agreement table. | S83: Consistency | U83: $P_I_PriceMarkingAgreed | V83: LFM1 | W83: LIPRE | X83: Price marking, vendor | Y83: TWYAZ | Z83: LIPRE | AA83: ="BEGIN RETURN exists('DS_IS_RDS', '"&Table362[[#This Row],[Lookup Table]]&"', '"&Table362[[#This Row],[Lookup Field]]&"', "&Table362[[#This Row],[IS Parameter]]&"); END" -> BEGIN RETURN exists('DS_IS_RDS', 'TWYAZ', 'LIPRE', $P_I_PriceMarkingAgreed); END | AC83: QUAC.checkValueExists('{$lookuptabname}','{$lookupfieldname}') | AE83: =IF(Table362[[#This Row],[Entity]]="Customer","KUNNR",IF(Table362[[#This Row],[Entity]]="Vendor","LIFNR","MATNR"))&",EKORG,"&Table362[[#This Row],[Field]] -> LIFNR,EKORG,LIPRE | AF83: ="VW_"&Table362[[#This Row],[New Rule Name]] -> VW_VEN0640_PriceMarkingAgreedRef | AG83: ="create view "&Table362[[#This Row],[View Name]]&" as select "&IF(Table362[[#This Row],[Entity]]="Customer","KUNNR",IF(Table362[[#This Row],[Entity]]="Vendor","LIFNR","MATNR"))&", EKORG, "&Table362[[#This Row],[Field]]&" from "&Table362[[#This Row],[Table]] -> create view VW_VEN0640_PriceMarkingAgreedRef as select LIFNR, EKORG, LIPRE from LFM1 | AK83: 64
